Workbook

Sheet Leia-me
A1: Planilha de precificação – versão corrigida (mesmas fórmulas do sistema)
A3: O que estava errado nas planilhas anteriores
A4: • Lucro, IR e cartão eram somados "por fora" do custo: lucro de 30% virava ~20% do preço e o IR de 15% virava ~13%.
A5: Agora todos os percentuais incidem sobre o PREÇO: preço = custo direto ÷ (1 − cartão − comissão − taxas − IR − lucro).
A6: • A comissão de 7% nunca era calculada (coluna vazia) e na aba HOF virava R$ 50/hora. O cartão só existia em 3 abas.
A7: • Cabeçalhos diziam "lucro 20%" com fórmula de 30%; havia células #REF!; implantes com material R$ 7 e sem horas.
A8: • O custo da estrutura por hora assumia 100% de ocupação (R$ 30,36/h). Com a ocupação como parâmetro (65%) dá R$ 46,71/h.
A9: • Materiais eram só listas de nomes. Agora cada material tem preço da embalagem, rendimento e perda; o custo entra pela quantidade usada.
A11: Como usar
A12: 1) Aba Parâmetros: despesas (o custo mensal sai sozinho), salas/horas/ocupação, hora clínica, cartão, comissão, lucro, regime de IR e taxas adicionais.
A13: 2) Aba Materiais: preço da embalagem, rendimento (quantas unidades de uso) e % de perda → custo por unidade de uso.
A14: 3) Aba Itens: materiais e quantidades de cada procedimento (o nome do procedimento tem que ser igual ao da aba Procedimentos).
... A26: Fonte: planilhas da clínica (despesas e procedimentos) e modelo de precificação; percentuais de IR são sugestões, valide com o contador.

Sheet Parâmetros
A1: Parâmetros da clínica
A3: Despesa | B3: Tipo | C3: Valor (R$)
A4: Telefone e internet | B4: Fixa mensal | C4: 149.9
A5: Salário recepção | B5: Fixa mensal | C5: 2500
A6: FGTS | B6: Fixa mensal | C6: 179
A7: Sanepar | B7: Fixa mensal | C7: 170
A8: Copel | B8: Fixa mensal | C8: 700
A9: BioAccess | B9: Fixa mensal | C9: 145
A10: Contabilidade | B10: Fixa mensal | C10: 165
A11: GPS | B11: Fixa mensal | C11: 850
A12: Diarista | B12: Fixa mensal | C12: 600
A13: Sistema | B13: Fixa mensal | C13: 300
A14: Aluguel | B14: Fixa mensal | C14: 3700
A15: Produtos de limpeza | B15: Variável mensal | C15: 200
... A32: Decoração | B32: Publicidade mensal | C32: 200
A44: Resumo do custo mensal
A45: Fixas mensais | B45: =SUMIF($B$4:$B$42,"Fixa mensal",$C$4:$C$42)
A46: Variáveis mensais | B46: =SUMIF($B$4:$B$42,"Variável mensal",$C$4:$C$42)
A47: Eventuais anuais ÷ 12 | B47: =SUMIF($B$4:$B$42,"Eventual anual",$C$4:$C$42)/12
A48: Publicidade mensal | B48: =SUMIF($B$4:$B$42,"Publicidade mensal",$C$4:$C$42)
A49: CUSTO MENSAL DA CLÍNICA | B49: =SUM(B45:B48)
A51: Estrutura e horas
A52: Salas (cadeiras) em uso | B52: 4
A53: Horas por semana, por sala | B53: 35
A54: Semanas por mês | B54: 4 | E54: 4,33 = 52 ÷ 12 se preferir a média
A55: Ocupação da agenda | B55: 0.65 | E55: Parte das horas abertas que realmente vira atendimento
A56: Horas produtivas por mês | B56: =B52*B53*B54*B55
A57: CUSTO DA ESTRUTURA POR HORA | B57: =IF(B56=0,0,B49/B56)
A59: Profissional e percentuais sobre o preço
A60: Hora clínica do profissional (R$/h) | B60: 50 | E60: Remuneração do dentista por hora de cadeira
A61: Taxa da máquina de cartão | B61: 0.04 | E61: Média de débito, crédito e parcelado
A62: Comissão (padrão) | B62: 0.07 | E62: Cada procedimento pode ter a sua (aba Procedimentos)
A63: Lucro desejado (padrão) | B63: 0.3
A64: Regime do IR (1 = pessoa física, 2 = pessoa jurídica) | B64: 2 | E64: PF: IR incide sobre o lucro (carnê-leão). PJ: tributos incidem sobre o faturamento (Simples / Presumido)
A65: IR pessoa física | B65: 0.275 | E65: Alíquota efetiva da sua faixa (teto 27,5%)
A66: Tributos pessoa jurídica | B66: 0.15 | E66: Simples 6% a 15,5%; Presumido 11,33% + ISS. Valide com o contador
A67: IR usado no preço | B67: =IF(B64=2,B66,B65)
A69: Taxas adicionais sobre o preço (1 = ativa, 0 = desligada)
A70: Taxa | B70: Percentual | C70: Ativa (1/0) | E70: Quando usar
A71: ISS | B71: 0.05 | C71: 0 | E71: Imposto municipal sobre serviços (2% a 5%). No Simples Nacional já está no DAS: deixe 0.
A72: Inadimplência | B72: 0.03 | C72: 0 | E72: Provisão para pacientes que não pagam.
A73: Antecipação de recebíveis | B73: 0.03 | C73: 0 | E73: Custo de antecipar as parcelas do cartão.
A74: Garantia e retrabalho | B74: 0.02 | C74: 0 | E74: Reserva para refazer procedimentos sem cobrar.
A75: Margem de negociação | B75: 0.05 | C75: 0 | E75: Espaço para dar desconto sem perder o lucro desejado.
A76: Convênios / planos | B76: 0 | C76: 0 | E76: Desconto médio das tabelas de convênio.
A77: Marketing por procedimento | B77: 0 | C77: 0 | E77: Se preferir ratear a captação por procedimento.
A78: Taxas adicionais ativas | B78: =SUMPRODUCT($B$71:$B$77,$C$71:$C$77)
A79: Percentuais sobre o preço, sem o lucro | B79: =B61+B62+B78
A80: Total com IR e lucro padrão | B80: =B79+B67+B63
A81: Verificação | B81: =IF(B80>=1,"ERRO: percentuais somam 100% ou mais","OK")

Sheet Materiais
A1: Material | B1: Embalagem | C1: Preço da embalagem (R$) | D1: Rendimento (unidades de uso) | E1: Unidade de uso | F1: Perda | G1: Custo por unidade de uso (R$)
A2: Resina composta A2 | B2: Seringa 4 g | C2: 89.9 | D2: 40 | E2: 0,1 g | F2: 0.1 | G2: =IF(OR(A2="",D2=0),0,C2/(D2*(1-F2)))
A3: Sistema adesivo | B3: Frasco 5 ml | C3: 120 | D3: 100 | E3: aplicação | F3: 0.1 | G3: =IF(OR(A3="",D3=0),0,C3/(D3*(1-F3)))
A4: Ácido fosfórico 37% | B4: Seringa 3 ml | C4: 12 | D4: 30 | E4: aplicação | F4: 0.1 | G4: =IF(OR(A4="",D4=0),0,C4/(D4*(1-F4)))
A5: Anestésico (tubete) | B5: Caixa 50 tubetes | C5: 95 | D5: 50 | E5: tubete | F5: 0 | G5: =IF(OR(A5="",D5=0),0,C5/(D5*(1-F5)))
A6: Agulha gengival curta | B6: Caixa 100 | C6: 45 | D6: 100 | E6: unidade | F6: 0 | G6: =IF(OR(A6="",D6=0),0,C6/(D6*(1-F6)))
A7: Luvas de procedimento | B7: Caixa 100 | C7: 38 | D7: 100 | E7: unidade | F7: 0 | G7: =IF(OR(A7="",D7=0),0,C7/(D7*(1-F7)))
A8: Máscara descartável | B8: Caixa 50 | C8: 22 | D8: 50 | E8: unidade | F8: 0 | G8: =IF(OR(A8="",D8=0),0,C8/(D8*(1-F8)))
A9: Babador descartável | B9: Pacote 100 | C9: 28 | D9: 100 | E9: unidade | F9: 0 | G9: =IF(OR(A9="",D9=0),0,C9/(D9*(1-F9)))
A10: Sugador descartável | B10: Pacote 40 | C10: 14 | D10: 40 | E10: unidade | F10: 0 | G10: =IF(OR(A10="",D10=0),0,C10/(D10*(1-F10)))
A11: Pasta profilática | B11: Pote 90 g | C11: 18 | D11: 90 | E11: 1 g | F11: 0.15 | G11: =IF(OR(A11="",D11=0),0,C11/(D11*(1-F11)))
A12: Gaze | B12: Pacote 500 | C12: 20 | D12: 500 | E12: unidade | F12: 0 | G12: =IF(OR(A12="",D12=0),0,C12/(D12*(1-F12)))
G13: =IF(OR(A13="",D13=0),0,C13/(D13*(1-F13)))
G14: =IF(OR(A14="",D14=0),0,C14/(D14*(1-F14)))
G15: =IF(OR(A15="",D15=0),0,C15/(D15*(1-F15)))
G16: =IF(OR(A16="",D16=0),0,C16/(D16*(1-F16)))
G17: =IF(OR(A17="",D17=0),0,C17/(D17*(1-F17)))
G18: =IF(OR(A18="",D18=0),0,C18/(D18*(1-F18)))
G19: =IF(OR(A19="",D19=0),0,C19/(D19*(1-F19)))
G20: =IF(OR(A20="",D20=0),0,C20/(D20*(1-F20)))
G21: =IF(OR(A21="",D21=0),0,C21/(D21*(1-F21)))
G22: =IF(OR(A22="",D22=0),0,C22/(D22*(1-F22)))
G23: =IF(OR(A23="",D23=0),0,C23/(D23*(1-F23)))
G24: =IF(OR(A24="",D24=0),0,C24/(D24*(1-F24)))
... G52: =IF(OR(A52="",D52=0),0,C52/(D52*(1-F52)))
A54: Valores de exemplo (fictícios): substitua pelos preços reais ou use a pesquisa de mercado do sistema.

Sheet Itens
A1: Procedimento | B1: Material | C1: Quantidade (unidades de uso) | D1: Custo unitário (R$) | E1: Custo da linha (R$)
A2: Profilaxia | B2: Pasta profilática | C2: 3 | D2: =IF(B2="",0,IFERROR(INDEX(Materiais!$G$2:$G$52,MATCH(B2,Materiais!$A$2:$A$52,0)),0)) | E2: =IF(B2="",0,C2*D2)
A3: Profilaxia | B3: Luvas de procedimento | C3: 2 | D3: =IF(B3="",0,IFERROR(INDEX(Materiais!$G$2:$G$52,MATCH(B3,Materiais!$A$2:$A$52,0)),0)) | E3: =IF(B3="",0,C3*D3)
A4: Profilaxia | B4: Sugador descartável | C4: 1 | D4: =IF(B4="",0,IFERROR(INDEX(Materiais!$G$2:$G$52,MATCH(B4,Materiais!$A$2:$A$52,0)),0)) | E4: =IF(B4="",0,C4*D4)
A5: Restauração simples 1 face | B5: Resina composta A2 | C5: 2 | D5: =IF(B5="",0,IFERROR(INDEX(Materiais!$G$2:$G$52,MATCH(B5,Materiais!$A$2:$A$52,0)),0)) | E5: =IF(B5="",0,C5*D5)
A6: Restauração simples 1 face | B6: Sistema adesivo | C6: 1 | D6: =IF(B6="",0,IFERROR(INDEX(Materiais!$G$2:$G$52,MATCH(B6,Materiais!$A$2:$A$52,0)),0)) | E6: =IF(B6="",0,C6*D6)
A7: Restauração simples 1 face | B7: Anestésico (tubete) | C7: 1 | D7: =IF(B7="",0,IFERROR(INDEX(Materiais!$G$2:$G$52,MATCH(B7,Materiais!$A$2:$A$52,0)),0)) | E7: =IF(B7="",0,C7*D7)
A8: Restauração simples 1 face | B8: Luvas de procedimento | C8: 2 | D8: =IF(B8="",0,IFERROR(INDEX(Materiais!$G$2:$G$52,MATCH(B8,Materiais!$A$2:$A$52,0)),0)) | E8: =IF(B8="",0,C8*D8)
D9: =IF(B9="",0,IFERROR(INDEX(Materiais!$G$2:$G$52,MATCH(B9,Materiais!$A$2:$A$52,0)),0)) | E9: =IF(B9="",0,C9*D9)
D10: =IF(B10="",0,IFERROR(INDEX(Materiais!$G$2:$G$52,MATCH(B10,Materiais!$A$2:$A$52,0)),0)) | E10: =IF(B10="",0,C10*D10)
D11: =IF(B11="",0,IFERROR(INDEX(Materiais!$G$2:$G$52,MATCH(B11,Materiais!$A$2:$A$52,0)),0)) | E11: =IF(B11="",0,C11*D11)
D12: =IF(B12="",0,IFERROR(INDEX(Materiais!$G$2:$G$52,MATCH(B12,Materiais!$A$2:$A$52,0)),0)) | E12: =IF(B12="",0,C12*D12)
D13: =IF(B13="",0,IFERROR(INDEX(Materiais!$G$2:$G$52,MATCH(B13,Materiais!$A$2:$A$52,0)),0)) | E13: =IF(B13="",0,C13*D13)
D14: =IF(B14="",0,IFERROR(INDEX(Materiais!$G$2:$G$52,MATCH(B14,Materiais!$A$2:$A$52,0)),0)) | E14: =IF(B14="",0,C14*D14)
D15: =IF(B15="",0,IFERROR(INDEX(Materiais!$G$2:$G$52,MATCH(B15,Materiais!$A$2:$A$52,0)),0)) | E15: =IF(B15="",0,C15*D15)
D16: =IF(B16="",0,IFERROR(INDEX(Materiais!$G$2:$G$52,MATCH(B16,Materiais!$A$2:$A$52,0)),0)) | E16: =IF(B16="",0,C16*D16)
D17: =IF(B17="",0,IFERROR(INDEX(Materiais!$G$2:$G$52,MATCH(B17,Materiais!$A$2:$A$52,0)),0)) | E17: =IF(B17="",0,C17*D17)
D18: =IF(B18="",0,IFERROR(INDEX(Materiais!$G$2:$G$52,MATCH(B18,Materiais!$A$2:$A$52,0)),0)) | E18: =IF(B18="",0,C18*D18)
D19: =IF(B19="",0,IFERROR(INDEX(Materiais!$G$2:$G$52,MATCH(B19,Materiais!$A$2:$A$52,0)),0)) | E19: =IF(B19="",0,C19*D19)
D20: =IF(B20="",0,IFERROR(INDEX(Materiais!$G$2:$G$52,MATCH(B20,Materiais!$A$2:$A$52,0)),0)) | E20: =IF(B20="",0,C20*D20)
... D158: =IF(B158="",0,IFERROR(INDEX(Materiais!$G$2:$G$52,MATCH(B158,Materiais!$A$2:$A$52,0)),0)) | E158: =IF(B158="",0,C158*D158)

Sheet Procedimentos
A1: Código | B1: Procedimento | C1: Categoria | D1: Tempo (min) | E1: Laboratório / terceiros (R$) | F1: Outros materiais (R$) | G1: Valor cobrado hoje (R$) | H1: Comissão própria (vazio = padrão) | I1: Lucro próprio (vazio = padrão) | J1: Materiais (R$) | K1: Estrutura (R$) | L1: Hora clínica (R$) | M1: CUSTO DIRETO (R$) | N1: Comissão usada | O1: Lucro usado | P1: Preço PJ (R$) | Q1: Preço PF (R$) | R1: PREÇO SUGERIDO (regime escolhido) | S1: Preço mínimo (lucro zero) | T1: Cartão (R$) | U1: Comissão (R$) | V1: Taxas (R$) | W1: IR (R$) | X1: Lucro (R$) | Y1: Lucro real (%) | Z1: Sugerido − atual (R$) | AA1: Alerta
A2: 1.0 | B2: Profilaxia | C2: Clínica Geral | D2: 60 | E2: 0 | F2: 2 | G2: 150 | J2: =IF($B2="","",SUMIFS(Itens!$E$2:$E$158,Itens!$A$2:$A$158,$B2)+N(F2)) | K2: =IF($B2="","",N(D2)/60*Parâmetros!$B$57) | L2: =IF($B2="","",N(D2)/60*Parâmetros!$B$60) | M2: =IF($B2="","",J2+N(E2)+K2+L2) | N2: =IF($B2="","",IF(H2="",Parâmetros!$B$62,H2)) | O2: =IF($B2="","",IF(I2="",Parâmetros!$B$63,I2)) | P2: =IF($B2="","",IF(1-(Parâmetros!$B$61+N2+Parâmetros!$B$78)-Parâmetros!$B$66-O2<=0,"ERRO",M2/(1-(Parâmetros!$B$61+N2+Parâmetros!$B$78)-Parâmetros!$B$66-O2))) | Q2: =IF($B2="","",IF((1-Parâmetros!$B$65)*(1-(Parâmetros!$B$61+N2+Parâmetros!$B$78))-O2<=0,"ERRO",(1-Parâmetros!$B$65)*M2/((1-Parâmetros!$B$65)*(1-(Parâmetros!$B$61+N2+Parâmetros!$B$78))-O2))) | R2: =IF($B2="","",IF(Parâmetros!$B$64=2,P2,Q2)) | S2: =IF($B2="","",IF(Parâmetros!$B$64=2,IF(1-(Parâmetros!$B$61+N2+Parâmetros!$B$78)-Parâmetros!$B$66<=0,"ERRO",M2/(1-(Parâmetros!$B$61+N2+Parâmetros!$B$78)-Parâmetros!$B$66)),IF((1-Parâmetros!$B$65)*(1-(Parâmetros!$B$61+N2+Parâmetros!$B$78))<=0,"ERRO",(1-Parâmetros!$B$65)*M2/((1-Parâmetros!$B$65)*(1-(Parâmetros!$B$61+N2+Parâmetros!$B$78)))))) | T2: =IF($B2="","",IF(ISNUMBER(R2),R2*Parâmetros!$B$61,"")) | U2: =IF($B2="","",IF(ISNUMBER(R2),R2*N2,"")) | V2: =IF($B2="","",IF(ISNUMBER(R2),R2*Parâmetros!$B$78,"")) | W2: =IF($B2="","",IF(ISNUMBER(R2),IF(Parâmetros!$B$64=2,R2*Parâmetros!$B$66,Parâmetros!$B$65*(R2-M2-R2*(Parâmetros!$B$61+N2+Parâmetros!$B$78))),"")) | X2: =IF($B2="","",IF(ISNUMBER(R2),R2-M2-T2-U2-V2-W2,"")) | Y2: =IF($B2="","",IF(AND(ISNUMBER(R2),R2>0),X2/R2,"")) | Z2: =IF($B2="","",IF(AND(ISNUMBER(R2),ISNUMBER(G2)),R2-G2,"")) | AA2: =IF($B2="","",IF(NOT(ISNUMBER(R2)),"Percentuais ≥ 100%",IF(N(D2)=0,"Sem tempo",IF(J2=0,"Sem materiais",""))))
A3: 2.0 | B3: Clareamento laser (1 sessão) | C3: Clínica Geral | D3: 90 | E3: 0 | F3: 63 | G3: 700 | J3: =IF($B3="","",SUMIFS(Itens!$E$2:$E$158,Itens!$A$2:$A$158,$B3)+N(F3)) | K3: =IF($B3="","",N(D3)/60*Parâmetros!$B$57) | L3: =IF($B3="","",N(D3)/60*Parâmetros!$B$60) | M3: =IF($B3="","",J3+N(E3)+K3+L3) | N3: =IF($B3="","",IF(H3="",Parâmetros!$B$62,H3)) | O3: =IF($B3="","",IF(I3="",Parâmetros!$B$63,I3)) | P3: =IF($B3="","",IF(1-(Parâmetros!$B$61+N3+Parâmetros!$B$78)-Parâmetros!$B$66-O3<=0,"ERRO",M3/(1-(Parâmetros!$B$61+N3+Parâmetros!$B$78)-Parâmetros!$B$66-O3))) | Q3: =IF($B3="","",IF((1-Parâmetros!$B$65)*(1-(Parâmetros!$B$61+N3+Parâmetros!$B$78))-O3<=0,"ERRO",(1-Parâmetros!$B$65)*M3/((1-Parâmetros!$B$65)*(1-(Parâmetros!$B$61+N3+Parâmetros!$B$78))-O3))) | R3: =IF($B3="","",IF(Parâmetros!$B$64=2,P3,Q3)) | S3: =IF($B3="","",IF(Parâmetros!$B$64=2,IF(1-(Parâmetros!$B$61+N3+Parâmetros!$B$78)-Parâmetros!$B$66<=0,"ERRO",M3/(1-(Parâmetros!$B$61+N3+Parâmetros!$B$78)-Parâmetros!$B$66)),IF((1-Parâmetros!$B$65)*(1-(Parâmetros!$B$61+N3+Parâmetros!$B$78))<=0,"ERRO",(1-Parâmetros!$B$65)*M3/((1-Parâmetros!$B$65)*(1-(Parâmetros!$B$61+N3+Parâmetros!$B$78)))))) | T3: =IF($B3="","",IF(ISNUMBER(R3),R3*Parâmetros!$B$61,"")) | U3: =IF($B3="","",IF(ISNUMBER(R3),R3*N3,"")) | V3: =IF($B3="","",IF(ISNUMBER(R3),R3*Parâmetros!$B$78,"")) | W3: =IF($B3="","",IF(ISNUMBER(R3),IF(Parâmetros!$B$64=2,R3*Parâmetros!$B$66,Parâmetros!$B$65*(R3-M3-R3*(Parâmetros!$B$61+N3+Parâmetros!$B$78))),"")) | X3: =IF($B3="","",IF(ISNUMBER(R3),R3-M3-T3-U3-V3-W3,"")) | Y3: =IF($B3="","",IF(AND(ISNUMBER(R3),R3>0),X3/R3,"")) | Z3: =IF($B3="","",IF(AND(ISNUMBER(R3),ISNUMBER(G3)),R3-G3,"")) | AA3: =IF($B3="","",IF(NOT(ISNUMBER(R3)),"Percentuais ≥ 100%",IF(N(D3)=0,"Sem tempo",IF(J3=0,"Sem materiais",""))))
A4: 2.1 | B4: Clareamento laser (2 sessões) | C4: Clínica Geral | D4: 180 | E4: 0 | F4: 126 | G4: 1200 | J4: =IF($B4="","",SUMIFS(Itens!$E$2:$E$158,Itens!$A$2:$A$158,$B4)+N(F4)) | K4: =IF($B4="","",N(D4)/60*Parâmetros!$B$57) | L4: =IF($B4="","",N(D4)/60*Parâmetros!$B$60) | M4: =IF($B4="","",J4+N(E4)+K4+L4) | N4: =IF($B4="","",IF(H4="",Parâmetros!$B$62,H4)) | O4: =IF($B4="","",IF(I4="",Parâmetros!$B$63,I4)) | P4: =IF($B4="","",IF(1-(Parâmetros!$B$61+N4+Parâmetros!$B$78)-Parâmetros!$B$66-O4<=0,"ERRO",M4/(1-(Parâmetros!$B$61+N4+Parâmetros!$B$78)-Parâmetros!$B$66-O4))) | Q4: =IF($B4="","",IF((1-Parâmetros!$B$65)*(1-(Parâmetros!$B$61+N4+Parâmetros!$B$78))-O4<=0,"ERRO",(1-Parâmetros!$B$65)*M4/((1-Parâmetros!$B$65)*(1-(Parâmetros!$B$61+N4+Parâmetros!$B$78))-O4))) | R4: =IF($B4="","",IF(Parâmetros!$B$64=2,P4,Q4)) | S4: =IF($B4="","",IF(Parâmetros!$B$64=2,IF(1-(Parâmetros!$B$61+N4+Parâmetros!$B$78)-Parâmetros!$B$66<=0,"ERRO",M4/(1-(Parâmetros!$B$61+N4+Parâmetros!$B$78)-Parâmetros!$B$66)),IF((1-Parâmetros!$B$65)*(1-(Parâmetros!$B$61+N4+Parâmetros!$B$78))<=0,"ERRO",(1-Parâmetros!$B$65)*M4/((1-Parâmetros!$B$65)*(1-(Parâmetros!$B$61+N4+Parâmetros!$B$78)))))) | T4: =IF($B4="","",IF(ISNUMBER(R4),R4*Parâmetros!$B$61,"")) | U4: =IF($B4="","",IF(ISNUMBER(R4),R4*N4,"")) | V4: =IF($B4="","",IF(ISNUMBER(R4),R4*Parâmetros!$B$78,"")) | W4: =IF($B4="","",IF(ISNUMBER(R4),IF(Parâmetros!$B$64=2,R4*Parâmetros!$B$66,Parâmetros!$B$65*(R4-M4-R4*(Parâmetros!$B$61+N4+Parâmetros!$B$78))),"")) | X4: =IF($B4="","",IF(ISNUMBER(R4),R4-M4-T4-U4-V4-W4,"")) | Y4: =IF($B4="","",IF(AND(ISNUMBER(R4),R4>0),X4/R4,"")) | Z4: =IF($B4="","",IF(AND(ISNUMBER(R4),ISNUMBER(G4)),R4-G4,"")) | AA4: =IF($B4="","",IF(NOT(ISNUMBER(R4)),"Percentuais ≥ 100%",IF(N(D4)=0,"Sem tempo",IF(J4=0,"Sem materiais",""))))
A5: 2.2 | B5: Clareamento laser (sessão avulsa) | C5: Clínica Geral | D5: 90 | E5: 0 | F5: 63 | G5: 700 | J5: =IF($B5="","",SUMIFS(Itens!$E$2:$E$158,Itens!$A$2:$A$158,$B5)+N(F5)) | K5: =IF($B5="","",N(D5)/60*Parâmetros!$B$57) | L5: =IF($B5="","",N(D5)/60*Parâmetros!$B$60) | M5: =IF($B5="","",J5+N(E5)+K5+L5) | N5: =IF($B5="","",IF(H5="",Parâmetros!$B$62,H5)) | O5: =IF($B5="","",IF(I5="",Parâmetros!$B$63,I5)) | P5: =IF($B5="","",IF(1-(Parâmetros!$B$61+N5+Parâmetros!$B$78)-Parâmetros!$B$66-O5<=0,"ERRO",M5/(1-(Parâmetros!$B$61+N5+Parâmetros!$B$78)-Parâmetros!$B$66-O5))) | Q5: =IF($B5="","",IF((1-Parâmetros!$B$65)*(1-(Parâmetros!$B$61+N5+Parâmetros!$B$78))-O5<=0,"ERRO",(1-Parâmetros!$B$65)*M5/((1-Parâmetros!$B$65)*(1-(Parâmetros!$B$61+N5+Parâmetros!$B$78))-O5))) | R5: =IF($B5="","",IF(Parâmetros!$B$64=2,P5,Q5)) | S5: =IF($B5="","",IF(Parâmetros!$B$64=2,IF(1-(Parâmetros!$B$61+N5+Parâmetros!$B$78)-Parâmetros!$B$66<=0,"ERRO",M5/(1-(Parâmetros!$B$61+N5+Parâmetros!$B$78)-Parâmetros!$B$66)),IF((1-Parâmetros!$B$65)*(1-(Parâmetros!$B$61+N5+Parâmetros!$B$78))<=0,"ERRO",(1-Parâmetros!$B$65)*M5/((1-Parâmetros!$B$65)*(1-(Parâmetros!$B$61+N5+Parâmetros!$B$78)))))) | T5: =IF($B5="","",IF(ISNUMBER(R5),R5*Parâmetros!$B$61,"")) | U5: =IF($B5="","",IF(ISNUMBER(R5),R5*N5,"")) | V5: =IF($B5="","",IF(ISNUMBER(R5),R5*Parâmetros!$B$78,"")) | W5: =IF($B5="","",IF(ISNUMBER(R5),IF(Parâmetros!$B$64=2,R5*Parâmetros!$B$66,Parâmetros!$B$65*(R5-M5-R5*(Parâmetros!$B$61+N5+Parâmetros!$B$78))),"")) | X5: =IF($B5="","",IF(ISNUMBER(R5),R5-M5-T5-U5-V5-W5,"")) | Y5: =IF($B5="","",IF(AND(ISNUMBER(R5),R5>0),X5/R5,"")) | Z5: =IF($B5="","",IF(AND(ISNUMBER(R5),ISNUMBER(G5)),R5-G5,"")) | AA5: =IF($B5="","",IF(NOT(ISNUMBER(R5)),"Percentuais ≥ 100%",IF(N(D5)=0,"Sem tempo",IF(J5=0,"Sem materiais",""))))
A6: 2.3 | B6: Clareamento caseiro (2 seringas) | C6: Clínica Geral | D6: 60 | E6: 0 | F6: 70 | G6: 650 | J6: =IF($B6="","",SUMIFS(Itens!$E$2:$E$158,Itens!$A$2:$A$158,$B6)+N(F6)) | K6: =IF($B6="","",N(D6)/60*Parâmetros!$B$57) | L6: =IF($B6="","",N(D6)/60*Parâmetros!$B$60) | M6: =IF($B6="","",J6+N(E6)+K6+L6) | N6: =IF($B6="","",IF(H6="",Parâmetros!$B$62,H6)) | O6: =IF($B6="","",IF(I6="",Parâmetros!$B$63,I6)) | P6: =IF($B6="","",IF(1-(Parâmetros!$B$61+N6+Parâmetros!$B$78)-Parâmetros!$B$66-O6<=0,"ERRO",M6/(1-(Parâmetros!$B$61+N6+Parâmetros!$B$78)-Parâmetros!$B$66-O6))) | Q6: =IF($B6="","",IF((1-Parâmetros!$B$65)*(1-(Parâmetros!$B$61+N6+Parâmetros!$B$78))-O6<=0,"ERRO",(1-Parâmetros!$B$65)*M6/((1-Parâmetros!$B$65)*(1-(Parâmetros!$B$61+N6+Parâmetros!$B$78))-O6))) | R6: =IF($B6="","",IF(Parâmetros!$B$64=2,P6,Q6)) | S6: =IF($B6="","",IF(Parâmetros!$B$64=2,IF(1-(Parâmetros!$B$61+N6+Parâmetros!$B$78)-Parâmetros!$B$66<=0,"ERRO",M6/(1-(Parâmetros!$B$61+N6+Parâmetros!$B$78)-Parâmetros!$B$66)),IF((1-Parâmetros!$B$65)*(1-(Parâmetros!$B$61+N6+Parâmetros!$B$78))<=0,"ERRO",(1-Parâmetros!$B$65)*M6/((1-Parâmetros!$B$65)*(1-(Parâmetros!$B$61+N6+Parâmetros!$B$78)))))) | T6: =IF($B6="","",IF(ISNUMBER(R6),R6*Parâmetros!$B$61,"")) | U6: =IF($B6="","",IF(ISNUMBER(R6),R6*N6,"")) | V6: =IF($B6="","",IF(ISNUMBER(R6),R6*Parâmetros!$B$78,"")) | W6: =IF($B6="","",IF(ISNUMBER(R6),IF(Parâmetros!$B$64=2,R6*Parâmetros!$B$66,Parâmetros!$B$65*(R6-M6-R6*(Parâmetros!$B$61+N6+Parâmetros!$B$78))),"")) | X6: =IF($B6="","",IF(ISNUMBER(R6),R6-M6-T6-U6-V6-W6,"")) | Y6: =IF($B6="","",IF(AND(ISNUMBER(R6),R6>0),X6/R6,"")) | Z6: =IF($B6="","",IF(AND(ISNUMBER(R6),ISNUMBER(G6)),R6-G6,"")) | AA6: =IF($B6="","",IF(NOT(ISNUMBER(R6)),"Percentuais ≥ 100%",IF(N(D6)=0,"Sem tempo",IF(J6=0,"Sem materiais",""))))
A7: 2.4 | B7: Seringa avulsa clareador | C7: Clínica Geral | D7: 0 | E7: 0 | F7: 20 | G7: 350 | J7: =IF($B7="","",SUMIFS(Itens!$E$2:$E$158,Itens!$A$2:$A$158,$B7)+N(F7)) | K7: =IF($B7="","",N(D7)/60*Parâmetros!$B$57) | L7: =IF($B7="","",N(D7)/60*Parâmetros!$B$60) | M7: =IF($B7="","",J7+N(E7)+K7+L7) | N7: =IF($B7="","",IF(H7="",Parâmetros!$B$62,H7)) | O7: =IF($B7="","",IF(I7="",Parâmetros!$B$63,I7)) | P7: =IF($B7="","",IF(1-(Parâmetros!$B$61+N7+Parâmetros!$B$78)-Parâmetros!$B$66-O7<=0,"ERRO",M7/(1-(Parâmetros!$B$61+N7+Parâmetros!$B$78)-Parâmetros!$B$66-O7))) | Q7: =IF($B7="","",IF((1-Parâmetros!$B$65)*(1-(Parâmetros!$B$61+N7+Parâmetros!$B$78))-O7<=0,"ERRO",(1-Parâmetros!$B$65)*M7/((1-Parâmetros!$B$65)*(1-(Parâmetros!$B$61+N7+Parâmetros!$B$78))-O7))) | R7: =IF($B7="","",IF(Parâmetros!$B$64=2,P7,Q7)) | S7: =IF($B7="","",IF(Parâmetros!$B$64=2,IF(1-(Parâmetros!$B$61+N7+Parâmetros!$B$78)-Parâmetros!$B$66<=0,"ERRO",M7/(1-(Parâmetros!$B$61+N7+Parâmetros!$B$78)-Parâmetros!$B$66)),IF((1-Parâmetros!$B$65)*(1-(Parâmetros!$B$61+N7+Parâmetros!$B$78))<=0,"ERRO",(1-Parâmetros!$B$65)*M7/((1-Parâmetros!$B$65)*(1-(Parâmetros!$B$61+N7+Parâmetros!$B$78)))))) | T7: =IF($B7="","",IF(ISNUMBER(R7),R7*Parâmetros!$B$61,"")) | U7: =IF($B7="","",IF(ISNUMBER(R7),R7*N7,"")) | V7: =IF($B7="","",IF(ISNUMBER(R7),R7*Parâmetros!$B$78,"")) | W7: =IF($B7="","",IF(ISNUMBER(R7),IF(Parâmetros!$B$64=2,R7*Parâmetros!$B$66,Parâmetros!$B$65*(R7-M7-R7*(Parâmetros!$B$61+N7+Parâmetros!$B$78))),"")) | X7: =IF($B7="","",IF(ISNUMBER(R7),R7-M7-T7-U7-V7-W7,"")) | Y7: =IF($B7="","",IF(AND(ISNUMBER(R7),R7>0),X7/R7,"")) | Z7: =IF($B7="","",IF(AND(ISNUMBER(R7),ISNUMBER(G7)),R7-G7,"")) | AA7: =IF($B7="","",IF(NOT(ISNUMBER(R7)),"Percentuais ≥ 100%",IF(N(D7)=0,"Sem tempo",IF(J7=0,"Sem materiais",""))))
B8: Clareamento interno unitário | C8: Clínica Geral | D8: 90 | E8: 0 | F8: 20 | J8: =IF($B8="","",SUMIFS(Itens!$E$2:$E$158,Itens!$A$2:$A$158,$B8)+N(F8)) | K8: =IF($B8="","",N(D8)/60*Parâmetros!$B$57) | L8: =IF($B8="","",N(D8)/60*Parâmetros!$B$60) | M8: =IF($B8="","",J8+N(E8)+K8+L8) | N8: =IF($B8="","",IF(H8="",Parâmetros!$B$62,H8)) | O8: =IF($B8="","",IF(I8="",Parâmetros!$B$63,I8)) | P8: =IF($B8="","",IF(1-(Parâmetros!$B$61+N8+Parâmetros!$B$78)-Parâmetros!$B$66-O8<=0,"ERRO",M8/(1-(Parâmetros!$B$61+N8+Parâmetros!$B$78)-Parâmetros!$B$66-O8))) | Q8: =IF($B8="","",IF((1-Parâmetros!$B$65)*(1-(Parâmetros!$B$61+N8+Parâmetros!$B$78))-O8<=0,"ERRO",(1-Parâmetros!$B$65)*M8/((1-Parâmetros!$B$65)*(1-(Parâmetros!$B$61+N8+Parâmetros!$B$78))-O8))) | R8: =IF($B8="","",IF(Parâmetros!$B$64=2,P8,Q8)) | S8: =IF($B8="","",IF(Parâmetros!$B$64=2,IF(1-(Parâmetros!$B$61+N8+Parâmetros!$B$78)-Parâmetros!$B$66<=0,"ERRO",M8/(1-(Parâmetros!$B$61+N8+Parâmetros!$B$78)-Parâmetros!$B$66)),IF((1-Parâmetros!$B$65)*(1-(Parâmetros!$B$61+N8+Parâmetros!$B$78))<=0,"ERRO",(1-Parâmetros!$B$65)*M8/((1-Parâmetros!$B$65)*(1-(Parâmetros!$B$61+N8+Parâmetros!$B$78)))))) | T8: =IF($B8="","",IF(ISNUMBER(R8),R8*Parâmetros!$B$61,"")) | U8: =IF($B8="","",IF(ISNUMBER(R8),R8*N8,"")) | V8: =IF($B8="","",IF(ISNUMBER(R8),R8*Parâmetros!$B$78,"")) | W8: =IF($B8="","",IF(ISNUMBER(R8),IF(Parâmetros!$B$64=2,R8*Parâmetros!$B$66,Parâmetros!$B$65*(R8-M8-R8*(Parâmetros!$B$61+N8+Parâmetros!$B$78))),"")) | X8: =IF($B8="","",IF(ISNUMBER(R8),R8-M8-T8-U8-V8-W8,"")) | Y8: =IF($B8="","",IF(AND(ISNUMBER(R8),R8>0),X8/R8,"")) | Z8: =IF($B8="","",IF(AND(ISNUMBER(R8),ISNUMBER(G8)),R8-G8,"")) | AA8: =IF($B8="","",IF(NOT(ISNUMBER(R8)),"Percentuais ≥ 100%",IF(N(D8)=0,"Sem tempo",IF(J8=0,"Sem materiais",""))))
A9: 3.0 | B9: Restauração simples 1 face | C9: Clínica Geral | D9: 60 | E9: 0 | F9: 30 | J9: =IF($B9="","",SUMIFS(Itens!$E$2:$E$158,Itens!$A$2:$A$158,$B9)+N(F9)) | K9: =IF($B9="","",N(D9)/60*Parâmetros!$B$57) | L9: =IF($B9="","",N(D9)/60*Parâmetros!$B$60) | M9: =IF($B9="","",J9+N(E9)+K9+L9) | N9: =IF($B9="","",IF(H9="",Parâmetros!$B$62,H9)) | O9: =IF($B9="","",IF(I9="",Parâmetros!$B$63,I9)) | P9: =IF($B9="","",IF(1-(Parâmetros!$B$61+N9+Parâmetros!$B$78)-Parâmetros!$B$66-O9<=0,"ERRO",M9/(1-(Parâmetros!$B$61+N9+Parâmetros!$B$78)-Parâmetros!$B$66-O9))) | Q9: =IF($B9="","",IF((1-Parâmetros!$B$65)*(1-(Parâmetros!$B$61+N9+Parâmetros!$B$78))-O9<=0,"ERRO",(1-Parâmetros!$B$65)*M9/((1-Parâmetros!$B$65)*(1-(Parâmetros!$B$61+N9+Parâmetros!$B$78))-O9))) | R9: =IF($B9="","",IF(Parâmetros!$B$64=2,P9,Q9)) | S9: =IF($B9="","",IF(Parâmetros!$B$64=2,IF(1-(Parâmetros!$B$61+N9+Parâmetros!$B$78)-Parâmetros!$B$66<=0,"ERRO",M9/(1-(Parâmetros!$B$61+N9+Parâmetros!$B$78)-Parâmetros!$B$66)),IF((1-Parâmetros!$B$65)*(1-(Parâmetros!$B$61+N9+Parâmetros!$B$78))<=0,"ERRO",(1-Parâmetros!$B$65)*M9/((1-Parâmetros!$B$65)*(1-(Parâmetros!$B$61+N9+Parâmetros!$B$78)))))) | T9: =IF($B9="","",IF(ISNUMBER(R9),R9*Parâmetros!$B$61,"")) | U9: =IF($B9="","",IF(ISNUMBER(R9),R9*N9,"")) | V9: =IF($B9="","",IF(ISNUMBER(R9),R9*Parâmetros!$B$78,"")) | W9: =IF($B9="","",IF(ISNUMBER(R9),IF(Parâmetros!$B$64=2,R9*Parâmetros!$B$66,Parâmetros!$B$65*(R9-M9-R9*(Parâmetros!$B$61+N9+Parâmetros!$B$78))),"")) | X9: =IF($B9="","",IF(ISNUMBER(R9),R9-M9-T9-U9-V9-W9,"")) | Y9: =IF($B9="","",IF(AND(ISNUMBER(R9),R9>0),X9/R9,"")) | Z9: =IF($B9="","",IF(AND(ISNUMBER(R9),ISNUMBER(G9)),R9-G9,"")) | AA9: =IF($B9="","",IF(NOT(ISNUMBER(R9)),"Percentuais ≥ 100%",IF(N(D9)=0,"Sem tempo",IF(J9=0,"Sem materiais",""))))
A10: 3.1 | B10: Restauração simples 2 faces | C10: Clínica Geral | D10: 60 | E10: 0 | F10: 40 | J10: =IF($B10="","",SUMIFS(Itens!$E$2:$E$158,Itens!$A$2:$A$158,$B10)+N(F10)) | K10: =IF($B10="","",N(D10)/60*Parâmetros!$B$57) | L10: =IF($B10="","",N(D10)/60*Parâmetros!$B$60) | M10: =IF($B10="","",J10+N(E10)+K10+L10) | N10: =IF($B10="","",IF(H10="",Parâmetros!$B$62,H10)) | O10: =IF($B10="","",IF(I10="",Parâmetros!$B$63,I10)) | P10: =IF($B10="","",IF(1-(Parâmetros!$B$61+N10+Parâmetros!$B$78)-Parâmetros!$B$66-O10<=0,"ERRO",M10/(1-(Parâmetros!$B$61+N10+Parâmetros!$B$78)-Parâmetros!$B$66-O10))) | Q10: =IF($B10="","",IF((1-Parâmetros!$B$65)*(1-(Parâmetros!$B$61+N10+Parâmetros!$B$78))-O10<=0,"ERRO",(1-Parâmetros!$B$65)*M10/((1-Parâmetros!$B$65)*(1-(Parâmetros!$B$61+N10+Parâmetros!$B$78))-O10))) | R10: =IF($B10="","",IF(Parâmetros!$B$64=2,P10,Q10)) | S10: =IF($B10="","",IF(Parâmetros!$B$64=2,IF(1-(Parâmetros!$B$61+N10+Parâmetros!$B$78)-Parâmetros!$B$66<=0,"ERRO",M10/(1-(Parâmetros!$B$61+N10+Parâmetros!$B$78)-Parâmetros!$B$66)),IF((1-Parâmetros!$B$65)*(1-(Parâmetros!$B$61+N10+Parâmetros!$B$78))<=0,"ERRO",(1-Parâmetros!$B$65)*M10/((1-Parâmetros!$B$65)*(1-(Parâmetros!$B$61+N10+Parâmetros!$B$78)))))) | T10: =IF($B10="","",IF(ISNUMBER(R10),R10*Parâmetros!$B$61,"")) | U10: =IF($B10="","",IF(ISNUMBER(R10),R10*N10,"")) | V10: =IF($B10="","",IF(ISNUMBER(R10),R10*Parâmetros!$B$78,"")) | W10: =IF($B10="","",IF(ISNUMBER(R10),IF(Parâmetros!$B$64=2,R10*Parâmetros!$B$66,Parâmetros!$B$65*(R10-M10-R10*(Parâmetros!$B$61+N10+Parâmetros!$B$78))),"")) | X10: =IF($B10="","",IF(ISNUMBER(R10),R10-M10-T10-U10-V10-W10,"")) | Y10: =IF($B10="","",IF(AND(ISNUMBER(R10),R10>0),X10/R10,"")) | Z10: =IF($B10="","",IF(AND(ISNUMBER(R10),ISNUMBER(G10)),R10-G10,"")) | AA10: =IF($B10="","",IF(NOT(ISNUMBER(R10)),"Percentuais ≥ 100%",IF(N(D10)=0,"Sem tempo",IF(J10=0,"Sem materiais",""))))
A11: 3.2 | B11: Restauração simples 3 faces | C11: Clínica Geral | D11: 60 | E11: 0 | F11: 50 | J11: =IF($B11="","",SUMIFS(Itens!$E$2:$E$158,Itens!$A$2:$A$158,$B11)+N(F11)) | K11: =IF($B11="","",N(D11)/60*Parâmetros!$B$57) | L11: =IF($B11="","",N(D11)/60*Parâmetros!$B$60) | M11: =IF($B11="","",J11+N(E11)+K11+L11) | N11: =IF($B11="","",IF(H11="",Parâmetros!$B$62,H11)) | O11: =IF($B11="","",IF(I11="",Parâmetros!$B$63,I11)) | P11: =IF($B11="","",IF(1-(Parâmetros!$B$61+N11+Parâmetros!$B$78)-Parâmetros!$B$66-O11<=0,"ERRO",M11/(1-(Parâmetros!$B$61+N11+Parâmetros!$B$78)-Parâmetros!$B$66-O11))) | Q11: =IF($B11="","",IF((1-Parâmetros!$B$65)*(1-(Parâmetros!$B$61+N11+Parâmetros!$B$78))-O11<=0,"ERRO",(1-Parâmetros!$B$65)*M11/((1-Parâmetros!$B$65)*(1-(Parâmetros!$B$61+N11+Parâmetros!$B$78))-O11))) | R11: =IF($B11="","",IF(Parâmetros!$B$64=2,P11,Q11)) | S11: =IF($B11="","",IF(Parâmetros!$B$64=2,IF(1-(Parâmetros!$B$61+N11+Parâmetros!$B$78)-Parâmetros!$B$66<=0,"ERRO",M11/(1-(Parâmetros!$B$61+N11+Parâmetros!$B$78)-Parâmetros!$B$66)),IF((1-Parâmetros!$B$65)*(1-(Parâmetros!$B$61+N11+Parâmetros!$B$78))<=0,"ERRO",(1-Parâmetros!$B$65)*M11/((1-Parâmetros!$B$65)*(1-(Parâmetros!$B$61+N11+Parâmetros!$B$78)))))) | T11: =IF($B11="","",IF(ISNUMBER(R11),R11*Parâmetros!$B$61,"")) | U11: =IF($B11="","",IF(ISNUMBER(R11),R11*N11,"")) | V11: =IF($B11="","",IF(ISNUMBER(R11),R11*Parâmetros!$B$78,"")) | W11: =IF($B11="","",IF(ISNUMBER(R11),IF(Parâmetros!$B$64=2,R11*Parâmetros!$B$66,Parâmetros!$B$65*(R11-M11-R11*(Parâmetros!$B$61+N11+Parâmetros!$B$78))),"")) | X11: =IF($B11="","",IF(ISNUMBER(R11),R11-M11-T11-U11-V11-W11,"")) | Y11: =IF($B11="","",IF(AND(ISNUMBER(R11),R11>0),X11/R11,"")) | Z11: =IF($B11="","",IF(AND(ISNUMBER(R11),ISNUMBER(G11)),R11-G11,"")) | AA11: =IF($B11="","",IF(NOT(ISNUMBER(R11)),"Percentuais ≥ 100%",IF(N(D11)=0,"Sem tempo",IF(J11=0,"Sem materiais",""))))
A12: 3.3 | B12: Restauração em resina com pino fibra de vidro | C12: Clínica Geral | D12: 120 | E12: 0 | F12: 150 | J12: =IF($B12="","",SUMIFS(Itens!$E$2:$E$158,Itens!$A$2:$A$158,$B12)+N(F12)) | K12: =IF($B12="","",N(D12)/60*Parâmetros!$B$57) | L12: =IF($B12="","",N(D12)/60*Parâmetros!$B$60) | M12: =IF($B12="","",J12+N(E12)+K12+L12) | N12: =IF($B12="","",IF(H12="",Parâmetros!$B$62,H12)) | O12: =IF($B12="","",IF(I12="",Parâmetros!$B$63,I12)) | P12: =IF($B12="","",IF(1-(Parâmetros!$B$61+N12+Parâmetros!$B$78)-Parâmetros!$B$66-O12<=0,"ERRO",M12/(1-(Parâmetros!$B$61+N12+Parâmetros!$B$78)-Parâmetros!$B$66-O12))) | Q12: =IF($B12="","",IF((1-Parâmetros!$B$65)*(1-(Parâmetros!$B$61+N12+Parâmetros!$B$78))-O12<=0,"ERRO",(1-Parâmetros!$B$65)*M12/((1-Parâmetros!$B$65)*(1-(Parâmetros!$B$61+N12+Parâmetros!$B$78))-O12))) | R12: =IF($B12="","",IF(Parâmetros!$B$64=2,P12,Q12)) | S12: =IF($B12="","",IF(Parâmetros!$B$64=2,IF(1-(Parâmetros!$B$61+N12+Parâmetros!$B$78)-Parâmetros!$B$66<=0,"ERRO",M12/(1-(Parâmetros!$B$61+N12+Parâmetros!$B$78)-Parâmetros!$B$66)),IF((1-Parâmetros!$B$65)*(1-(Parâmetros!$B$61+N12+Parâmetros!$B$78))<=0,"ERRO",(1-Parâmetros!$B$65)*M12/((1-Parâmetros!$B$65)*(1-(Parâmetros!$B$61+N12+Parâmetros!$B$78)))))) | T12: =IF($B12="","",IF(ISNUMBER(R12),R12*Parâmetros!$B$61,"")) | U12: =IF($B12="","",IF(ISNUMBER(R12),R12*N12,"")) | V12: =IF($B12="","",IF(ISNUMBER(R12),R12*Parâmetros!$B$78,"")) | W12: =IF($B12="","",IF(ISNUMBER(R12),IF(Parâmetros!$B$64=2,R12*Parâmetros!$B$66,Parâmetros!$B$65*(R12-M12-R12*(Parâmetros!$B$61+N12+Parâmetros!$B$78))),"")) | X12: =IF($B12="","",IF(ISNUMBER(R12),R12-M12-T12-U12-V12-W12,"")) | Y12: =IF($B12="","",IF(AND(ISNUMBER(R12),R12>0),X12/R12,"")) | Z12: =IF($B12="","",IF(AND(ISNUMBER(R12),ISNUMBER(G12)),R12-G12,"")) | AA12: =IF($B12="","",IF(NOT(ISNUMBER(R12)),"Percentuais ≥ 100%",IF(N(D12)=0,"Sem tempo",IF(J12=0,"Sem materiais",""))))
A13: 3.4 | B13: Restauração estética / faceta | C13: Clínica Geral | D13: 120 | E13: 0 | F13: 34.49 | J13: =IF($B13="","",SUMIFS(Itens!$E$2:$E$158,Itens!$A$2:$A$158,$B13)+N(F13)) | K13: =IF($B13="","",N(D13)/60*Parâmetros!$B$57) | L13: =IF($B13="","",N(D13)/60*Parâmetros!$B$60) | M13: =IF($B13="","",J13+N(E13)+K13+L13) | N13: =IF($B13="","",IF(H13="",Parâmetros!$B$62,H13)) | O13: =IF($B13="","",IF(I13="",Parâmetros!$B$63,I13)) | P13: =IF($B13="","",IF(1-(Parâmetros!$B$61+N13+Parâmetros!$B$78)-Parâmetros!$B$66-O13<=0,"ERRO",M13/(1-(Parâmetros!$B$61+N13+Parâmetros!$B$78)-Parâmetros!$B$66-O13))) | Q13: =IF($B13="","",IF((1-Parâmetros!$B$65)*(1-(Parâmetros!$B$61+N13+Parâmetros!$B$78))-O13<=0,"ERRO",(1-Parâmetros!$B$65)*M13/((1-Parâmetros!$B$65)*(1-(Parâmetros!$B$61+N13+Parâmetros!$B$78))-O13))) | R13: =IF($B13="","",IF(Parâmetros!$B$64=2,P13,Q13)) | S13: =IF($B13="","",IF(Parâmetros!$B$64=2,IF(1-(Parâmetros!$B$61+N13+Parâmetros!$B$78)-Parâmetros!$B$66<=0,"ERRO",M13/(1-(Parâmetros!$B$61+N13+Parâmetros!$B$78)-Parâmetros!$B$66)),IF((1-Parâmetros!$B$65)*(1-(Parâmetros!$B$61+N13+Parâmetros!$B$78))<=0,"ERRO",(1-Parâmetros!$B$65)*M13/((1-Parâmetros!$B$65)*(1-(Parâmetros!$B$61+N13+Parâmetros!$B$78)))))) | T13: =IF($B13="","",IF(ISNUMBER(R13),R13*Parâmetros!$B$61,"")) | U13: =IF($B13="","",IF(ISNUMBER(R13),R13*N13,"")) | V13: =IF($B13="","",IF(ISNUMBER(R13),R13*Parâmetros!$B$78,"")) | W13: =IF($B13="","",IF(ISNUMBER(R13),IF(Parâmetros!$B$64=2,R13*Parâmetros!$B$66,Parâmetros!$B$65*(R13-M13-R13*(Parâmetros!$B$61+N13+Parâmetros!$B$78))),"")) | X13: =IF($B13="","",IF(ISNUMBER(R13),R13-M13-T13-U13-V13-W13,"")) | Y13: =IF($B13="","",IF(AND(ISNUMBER(R13),R13>0),X13/R13,"")) | Z13: =IF($B13="","",IF(AND(ISNUMBER(R13),ISNUMBER(G13)),R13-G13,"")) | AA13: =IF($B13="","",IF(NOT(ISNUMBER(R13)),"Percentuais ≥ 100%",IF(N(D13)=0,"Sem tempo",IF(J13=0,"Sem materiais",""))))
A14: 3.5 | B14: Biobase | C14: Clínica Geral | D14: 120 | E14: 0 | F14: 45.25 | J14: =IF($B14="","",SUMIFS(Itens!$E$2:$E$158,Itens!$A$2:$A$158,$B14)+N(F14)) | K14: =IF($B14="","",N(D14)/60*Parâmetros!$B$57) | L14: =IF($B14="","",N(D14)/60*Parâmetros!$B$60) | M14: =IF($B14="","",J14+N(E14)+K14+L14) | N14: =IF($B14="","",IF(H14="",Parâmetros!$B$62,H14)) | O14: =IF($B14="","",IF(I14="",Parâmetros!$B$63,I14)) | P14: =IF($B14="","",IF(1-(Parâmetros!$B$61+N14+Parâmetros!$B$78)-Parâmetros!$B$66-O14<=0,"ERRO",M14/(1-(Parâmetros!$B$61+N14+Parâmetros!$B$78)-Parâmetros!$B$66-O14))) | Q14: =IF($B14="","",IF((1-Parâmetros!$B$65)*(1-(Parâmetros!$B$61+N14+Parâmetros!$B$78))-O14<=0,"ERRO",(1-Parâmetros!$B$65)*M14/((1-Parâmetros!$B$65)*(1-(Parâmetros!$B$61+N14+Parâmetros!$B$78))-O14))) | R14: =IF($B14="","",IF(Parâmetros!$B$64=2,P14,Q14)) | S14: =IF($B14="","",IF(Parâmetros!$B$64=2,IF(1-(Parâmetros!$B$61+N14+Parâmetros!$B$78)-Parâmetros!$B$66<=0,"ERRO",M14/(1-(Parâmetros!$B$61+N14+Parâmetros!$B$78)-Parâmetros!$B$66)),IF((1-Parâmetros!$B$65)*(1-(Parâmetros!$B$61+N14+Parâmetros!$B$78))<=0,"ERRO",(1-Parâmetros!$B$65)*M14/((1-Parâmetros!$B$65)*(1-(Parâmetros!$B$61+N14+Parâmetros!$B$78)))))) | T14: =IF($B14="","",IF(ISNUMBER(R14),R14*Parâmetros!$B$61,"")) | U14: =IF($B14="","",IF(ISNUMBER(R14),R14*N14,"")) | V14: =IF($B14="","",IF(ISNUMBER(R14),R14*Parâmetros!$B$78,"")) | W14: =IF($B14="","",IF(ISNUMBER(R14),IF(Parâmetros!$B$64=2,R14*Parâmetros!$B$66,Parâmetros!$B$65*(R14-M14-R14*(Parâmetros!$B$61+N14+Parâmetros!$B$78))),"")) | X14: =IF($B14="","",IF(ISNUMBER(R14),R14-M14-T14-U14-V14-W14,"")) | Y14: =IF($B14="","",IF(AND(ISNUMBER(R14),R14>0),X14/R14,"")) | Z14: =IF($B14="","",IF(AND(ISNUMBER(R14),ISNUMBER(G14)),R14-G14,"")) | AA14: =IF($B14="","",IF(NOT(ISNUMBER(R14)),"Percentuais ≥ 100%",IF(N(D14)=0,"Sem tempo",IF(J14=0,"Sem materiais",""))))
A15: 3.6 | B15: Peça em resina técnica direta indireta | C15: Clínica Geral | D15: 120 | E15: 0 | F15: 41.38 | J15: =IF($B15="","",SUMIFS(Itens!$E$2:$E$158,Itens!$A$2:$A$158,$B15)+N(F15)) | K15: =IF($B15="","",N(D15)/60*Parâmetros!$B$57) | L15: =IF($B15="","",N(D15)/60*Parâmetros!$B$60) | M15: =IF($B15="","",J15+N(E15)+K15+L15) | N15: =IF($B15="","",IF(H15="",Parâmetros!$B$62,H15)) | O15: =IF($B15="","",IF(I15="",Parâmetros!$B$63,I15)) | P15: =IF($B15="","",IF(1-(Parâmetros!$B$61+N15+Parâmetros!$B$78)-Parâmetros!$B$66-O15<=0,"ERRO",M15/(1-(Parâmetros!$B$61+N15+Parâmetros!$B$78)-Parâmetros!$B$66-O15))) | Q15: =IF($B15="","",IF((1-Parâmetros!$B$65)*(1-(Parâmetros!$B$61+N15+Parâmetros!$B$78))-O15<=0,"ERRO",(1-Parâmetros!$B$65)*M15/((1-Parâmetros!$B$65)*(1-(Parâmetros!$B$61+N15+Parâmetros!$B$78))-O15))) | R15: =IF($B15="","",IF(Parâmetros!$B$64=2,P15,Q15)) | S15: =IF($B15="","",IF(Parâmetros!$B$64=2,IF(1-(Parâmetros!$B$61+N15+Parâmetros!$B$78)-Parâmetros!$B$66<=0,"ERRO",M15/(1-(Parâmetros!$B$61+N15+Parâmetros!$B$78)-Parâmetros!$B$66)),IF((1-Parâmetros!$B$65)*(1-(Parâmetros!$B$61+N15+Parâmetros!$B$78))<=0,"ERRO",(1-Parâmetros!$B$65)*M15/((1-Parâmetros!$B$65)*(1-(Parâmetros!$B$61+N15+Parâmetros!$B$78)))))) | T15: =IF($B15="","",IF(ISNUMBER(R15),R15*Parâmetros!$B$61,"")) | U15: =IF($B15="","",IF(ISNUMBER(R15),R15*N15,"")) | V15: =IF($B15="","",IF(ISNUMBER(R15),R15*Parâmetros!$B$78,"")) | W15: =IF($B15="","",IF(ISNUMBER(R15),IF(Parâmetros!$B$64=2,R15*Parâmetros!$B$66,Parâmetros!$B$65*(R15-M15-R15*(Parâmetros!$B$61+N15+Parâmetros!$B$78))),"")) | X15: =IF($B15="","",IF(ISNUMBER(R15),R15-M15-T15-U15-V15-W15,"")) | Y15: =IF($B15="","",IF(AND(ISNUMBER(R15),R15>0),X15/R15,"")) | Z15: =IF($B15="","",IF(AND(ISNUMBER(R15),ISNUMBER(G15)),R15-G15,"")) | AA15: =IF($B15="","",IF(NOT(ISNUMBER(R15)),"Percentuais ≥ 100%",IF(N(D15)=0,"Sem tempo",IF(J15=0,"Sem materiais",""))))
A16: 4.0 | B16: Tratamento endodôntico unirradicular | C16: Clínica Geral | D16: 90 | E16: 0 | F16: 120 | J16: =IF($B16="","",SUMIFS(Itens!$E$2:$E$158,Itens!$A$2:$A$158,$B16)+N(F16)) | K16: =IF($B16="","",N(D16)/60*Parâmetros!$B$57) | L16: =IF($B16="","",N(D16)/60*Parâmetros!$B$60) | M16: =IF($B16="","",J16+N(E16)+K16+L16) | N16: =IF($B16="","",IF(H16="",Parâmetros!$B$62,H16)) | O16: =IF($B16="","",IF(I16="",Parâmetros!$B$63,I16)) | P16: =IF($B16="","",IF(1-(Parâmetros!$B$61+N16+Parâmetros!$B$78)-Parâmetros!$B$66-O16<=0,"ERRO",M16/(1-(Parâmetros!$B$61+N16+Parâmetros!$B$78)-Parâmetros!$B$66-O16))) | Q16: =IF($B16="","",IF((1-Parâmetros!$B$65)*(1-(Parâmetros!$B$61+N16+Parâmetros!$B$78))-O16<=0,"ERRO",(1-Parâmetros!$B$65)*M16/((1-Parâmetros!$B$65)*(1-(Parâmetros!$B$61+N16+Parâmetros!$B$78))-O16))) | R16: =IF($B16="","",IF(Parâmetros!$B$64=2,P16,Q16)) | S16: =IF($B16="","",IF(Parâmetros!$B$64=2,IF(1-(Parâmetros!$B$61+N16+Parâmetros!$B$78)-Parâmetros!$B$66<=0,"ERRO",M16/(1-(Parâmetros!$B$61+N16+Parâmetros!$B$78)-Parâmetros!$B$66)),IF((1-Parâmetros!$B$65)*(1-(Parâmetros!$B$61+N16+Parâmetros!$B$78))<=0,"ERRO",(1-Parâmetros!$B$65)*M16/((1-Parâmetros!$B$65)*(1-(Parâmetros!$B$61+N16+Parâmetros!$B$78)))))) | T16: =IF($B16="","",IF(ISNUMBER(R16),R16*Parâmetros!$B$61,"")) | U16: =IF($B16="","",IF(ISNUMBER(R16),R16*N16,"")) | V16: =IF($B16="","",IF(ISNUMBER(R16),R16*Parâmetros!$B$78,"")) | W16: =IF($B16="","",IF(ISNUMBER(R16),IF(Parâmetros!$B$64=2,R16*Parâmetros!$B$66,Parâmetros!$B$65*(R16-M16-R16*(Parâmetros!$B$61+N16+Parâmetros!$B$78))),"")) | X16: =IF($B16="","",IF(ISNUMBER(R16),R16-M16-T16-U16-V16-W16,"")) | Y16: =IF($B16="","",IF(AND(ISNUMBER(R16),R16>0),X16/R16,"")) | Z16: =IF($B16="","",IF(AND(ISNUMBER(R16),ISNUMBER(G16)),R16-G16,"")) | AA16: =IF($B16="","",IF(NOT(ISNUMBER(R16)),"Percentuais ≥ 100%",IF(N(D16)=0,"Sem tempo",IF(J16=0,"Sem materiais",""))))
A17: 4.1 | B17: Tratamento endodôntico birradicular | C17: Clínica Geral | D17: 90 | E17: 0 | F17: 130 | J17: =IF($B17="","",SUMIFS(Itens!$E$2:$E$158,Itens!$A$2:$A$158,$B17)+N(F17)) | K17: =IF($B17="","",N(D17)/60*Parâmetros!$B$57) | L17: =IF($B17="","",N(D17)/60*Parâmetros!$B$60) | M17: =IF($B17="","",J17+N(E17)+K17+L17) | N17: =IF($B17="","",IF(H17="",Parâmetros!$B$62,H17)) | O17: =IF($B17="","",IF(I17="",Parâmetros!$B$63,I17)) | P17: =IF($B17="","",IF(1-(Parâmetros!$B$61+N17+Parâmetros!$B$78)-Parâmetros!$B$66-O17<=0,"ERRO",M17/(1-(Parâmetros!$B$61+N17+Parâmetros!$B$78)-Parâmetros!$B$66-O17))) | Q17: =IF($B17="","",IF((1-Parâmetros!$B$65)*(1-(Parâmetros!$B$61+N17+Parâmetros!$B$78))-O17<=0,"ERRO",(1-Parâmetros!$B$65)*M17/((1-Parâmetros!$B$65)*(1-(Parâmetros!$B$61+N17+Parâmetros!$B$78))-O17))) | R17: =IF($B17="","",IF(Parâmetros!$B$64=2,P17,Q17)) | S17: =IF($B17="","",IF(Parâmetros!$B$64=2,IF(1-(Parâmetros!$B$61+N17+Parâmetros!$B$78)-Parâmetros!$B$66<=0,"ERRO",M17/(1-(Parâmetros!$B$61+N17+Parâmetros!$B$78)-Parâmetros!$B$66)),IF((1-Parâmetros!$B$65)*(1-(Parâmetros!$B$61+N17+Parâmetros!$B$78))<=0,"ERRO",(1-Parâmetros!$B$65)*M17/((1-Parâmetros!$B$65)*(1-(Parâmetros!$B$61+N17+Parâmetros!$B$78)))))) | T17: =IF($B17="","",IF(ISNUMBER(R17),R17*Parâmetros!$B$61,"")) | U17: =IF($B17="","",IF(ISNUMBER(R17),R17*N17,"")) | V17: =IF($B17="","",IF(ISNUMBER(R17),R17*Parâmetros!$B$78,"")) | W17: =IF($B17="","",IF(ISNUMBER(R17),IF(Parâmetros!$B$64=2,R17*Parâmetros!$B$66,Parâmetros!$B$65*(R17-M17-R17*(Parâmetros!$B$61+N17+Parâmetros!$B$78))),"")) | X17: =IF($B17="","",IF(ISNUMBER(R17),R17-M17-T17-U17-V17-W17,"")) | Y17: =IF($B17="","",IF(AND(ISNUMBER(R17),R17>0),X17/R17,"")) | Z17: =IF($B17="","",IF(AND(ISNUMBER(R17),ISNUMBER(G17)),R17-G17,"")) | AA17: =IF($B17="","",IF(NOT(ISNUMBER(R17)),"Percentuais ≥ 100%",IF(N(D17)=0,"Sem tempo",IF(J17=0,"Sem materiais",""))))
A18: 4.2 | B18: Tratamento endodôntico molar | C18: Clínica Geral | D18: 120 | E18: 0 | F18: 150 | J18: =IF($B18="","",SUMIFS(Itens!$E$2:$E$158,Itens!$A$2:$A$158,$B18)+N(F18)) | K18: =IF($B18="","",N(D18)/60*Parâmetros!$B$57) | L18: =IF($B18="","",N(D18)/60*Parâmetros!$B$60) | M18: =IF($B18="","",J18+N(E18)+K18+L18) | N18: =IF($B18="","",IF(H18="",Parâmetros!$B$62,H18)) | O18: =IF($B18="","",IF(I18="",Parâmetros!$B$63,I18)) | P18: =IF($B18="","",IF(1-(Parâmetros!$B$61+N18+Parâmetros!$B$78)-Parâmetros!$B$66-O18<=0,"ERRO",M18/(1-(Parâmetros!$B$61+N18+Parâmetros!$B$78)-Parâmetros!$B$66-O18))) | Q18: =IF($B18="","",IF((1-Parâmetros!$B$65)*(1-(Parâmetros!$B$61+N18+Parâmetros!$B$78))-O18<=0,"ERRO",(1-Parâmetros!$B$65)*M18/((1-Parâmetros!$B$65)*(1-(Parâmetros!$B$61+N18+Parâmetros!$B$78))-O18))) | R18: =IF($B18="","",IF(Parâmetros!$B$64=2,P18,Q18)) | S18: =IF($B18="","",IF(Parâmetros!$B$64=2,IF(1-(Parâmetros!$B$61+N18+Parâmetros!$B$78)-Parâmetros!$B$66<=0,"ERRO",M18/(1-(Parâmetros!$B$61+N18+Parâmetros!$B$78)-Parâmetros!$B$66)),IF((1-Parâmetros!$B$65)*(1-(Parâmetros!$B$61+N18+Parâmetros!$B$78))<=0,"ERRO",(1-Parâmetros!$B$65)*M18/((1-Parâmetros!$B$65)*(1-(Parâmetros!$B$61+N18+Parâmetros!$B$78)))))) | T18: =IF($B18="","",IF(ISNUMBER(R18),R18*Parâmetros!$B$61,"")) | U18: =IF($B18="","",IF(ISNUMBER(R18),R18*N18,"")) | V18: =IF($B18="","",IF(ISNUMBER(R18),R18*Parâmetros!$B$78,"")) | W18: =IF($B18="","",IF(ISNUMBER(R18),IF(Parâmetros!$B$64=2,R18*Parâmetros!$B$66,Parâmetros!$B$65*(R18-M18-R18*(Parâmetros!$B$61+N18+Parâmetros!$B$78))),"")) | X18: =IF($B18="","",IF(ISNUMBER(R18),R18-M18-T18-U18-V18-W18,"")) | Y18: =IF($B18="","",IF(AND(ISNUMBER(R18),R18>0),X18/R18,"")) | Z18: =IF($B18="","",IF(AND(ISNUMBER(R18),ISNUMBER(G18)),R18-G18,"")) | AA18: =IF($B18="","",IF(NOT(ISNUMBER(R18)),"Percentuais ≥ 100%",IF(N(D18)=0,"Sem tempo",IF(J18=0,"Sem materiais",""))))
A19: 4.3 | B19: Retratamento endodôntico unirradicular | C19: Clínica Geral | D19: 90 | E19: 0 | F19: 130 | J19: =IF($B19="","",SUMIFS(Itens!$E$2:$E$158,Itens!$A$2:$A$158,$B19)+N(F19)) | K19: =IF($B19="","",N(D19)/60*Parâmetros!$B$57) | L19: =IF($B19="","",N(D19)/60*Parâmetros!$B$60) | M19: =IF($B19="","",J19+N(E19)+K19+L19) | N19: =IF($B19="","",IF(H19="",Parâmetros!$B$62,H19)) | O19: =IF($B19="","",IF(I19="",Parâmetros!$B$63,I19)) | P19: =IF($B19="","",IF(1-(Parâmetros!$B$61+N19+Parâmetros!$B$78)-Parâmetros!$B$66-O19<=0,"ERRO",M19/(1-(Parâmetros!$B$61+N19+Parâmetros!$B$78)-Parâmetros!$B$66-O19))) | Q19: =IF($B19="","",IF((1-Parâmetros!$B$65)*(1-(Parâmetros!$B$61+N19+Parâmetros!$B$78))-O19<=0,"ERRO",(1-Parâmetros!$B$65)*M19/((1-Parâmetros!$B$65)*(1-(Parâmetros!$B$61+N19+Parâmetros!$B$78))-O19))) | R19: =IF($B19="","",IF(Parâmetros!$B$64=2,P19,Q19)) | S19: =IF($B19="","",IF(Parâmetros!$B$64=2,IF(1-(Parâmetros!$B$61+N19+Parâmetros!$B$78)-Parâmetros!$B$66<=0,"ERRO",M19/(1-(Parâmetros!$B$61+N19+Parâmetros!$B$78)-Parâmetros!$B$66)),IF((1-Parâmetros!$B$65)*(1-(Parâmetros!$B$61+N19+Parâmetros!$B$78))<=0,"ERRO",(1-Parâmetros!$B$65)*M19/((1-Parâmetros!$B$65)*(1-(Parâmetros!$B$61+N19+Parâmetros!$B$78)))))) | T19: =IF($B19="","",IF(ISNUMBER(R19),R19*Parâmetros!$B$61,"")) | U19: =IF($B19="","",IF(ISNUMBER(R19),R19*N19,"")) | V19: =IF($B19="","",IF(ISNUMBER(R19),R19*Parâmetros!$B$78,"")) | W19: =IF($B19="","",IF(ISNUMBER(R19),IF(Parâmetros!$B$64=2,R19*Parâmetros!$B$66,Parâmetros!$B$65*(R19-M19-R19*(Parâmetros!$B$61+N19+Parâmetros!$B$78))),"")) | X19: =IF($B19="","",IF(ISNUMBER(R19),R19-M19-T19-U19-V19-W19,"")) | Y19: =IF($B19="","",IF(AND(ISNUMBER(R19),R19>0),X19/R19,"")) | Z19: =IF($B19="","",IF(AND(ISNUMBER(R19),ISNUMBER(G19)),R19-G19,"")) | AA19: =IF($B19="","",IF(NOT(ISNUMBER(R19)),"Percentuais ≥ 100%",IF(N(D19)=0,"Sem tempo",IF(J19=0,"Sem materiais",""))))
A20: 4.4 | B20: Retratamento endodôntico birradicular | C20: Clínica Geral | D20: 90 | E20: 0 | F20: 140 | J20: =IF($B20="","",SUMIFS(Itens!$E$2:$E$158,Itens!$A$2:$A$158,$B20)+N(F20)) | K20: =IF($B20="","",N(D20)/60*Parâmetros!$B$57) | L20: =IF($B20="","",N(D20)/60*Parâmetros!$B$60) | M20: =IF($B20="","",J20+N(E20)+K20+L20) | N20: =IF($B20="","",IF(H20="",Parâmetros!$B$62,H20)) | O20: =IF($B20="","",IF(I20="",Parâmetros!$B$63,I20)) | P20: =IF($B20="","",IF(1-(Parâmetros!$B$61+N20+Parâmetros!$B$78)-Parâmetros!$B$66-O20<=0,"ERRO",M20/(1-(Parâmetros!$B$61+N20+Parâmetros!$B$78)-Parâmetros!$B$66-O20))) | Q20: =IF($B20="","",IF((1-Parâmetros!$B$65)*(1-(Parâmetros!$B$61+N20+Parâmetros!$B$78))-O20<=0,"ERRO",(1-Parâmetros!$B$65)*M20/((1-Parâmetros!$B$65)*(1-(Parâmetros!$B$61+N20+Parâmetros!$B$78))-O20))) | R20: =IF($B20="","",IF(Parâmetros!$B$64=2,P20,Q20)) | S20: =IF($B20="","",IF(Parâmetros!$B$64=2,IF(1-(Parâmetros!$B$61+N20+Parâmetros!$B$78)-Parâmetros!$B$66<=0,"ERRO",M20/(1-(Parâmetros!$B$61+N20+Parâmetros!$B$78)-Parâmetros!$B$66)),IF((1-Parâmetros!$B$65)*(1-(Parâmetros!$B$61+N20+Parâmetros!$B$78))<=0,"ERRO",(1-Parâmetros!$B$65)*M20/((1-Parâmetros!$B$65)*(1-(Parâmetros!$B$61+N20+Parâmetros!$B$78)))))) | T20: =IF($B20="","",IF(ISNUMBER(R20),R20*Parâmetros!$B$61,"")) | U20: =IF($B20="","",IF(ISNUMBER(R20),R20*N20,"")) | V20: =IF($B20="","",IF(ISNUMBER(R20),R20*Parâmetros!$B$78,"")) | W20: =IF($B20="","",IF(ISNUMBER(R20),IF(Parâmetros!$B$64=2,R20*Parâmetros!$B$66,Parâmetros!$B$65*(R20-M20-R20*(Parâmetros!$B$61+N20+Parâmetros!$B$78))),"")) | X20: =IF($B20="","",IF(ISNUMBER(R20),R20-M20-T20-U20-V20-W20,"")) | Y20: =IF($B20="","",IF(AND(ISNUMBER(R20),R20>0),X20/R20,"")) | Z20: =IF($B20="","",IF(AND(ISNUMBER(R20),ISNUMBER(G20)),R20-G20,"")) | AA20: =IF($B20="","",IF(NOT(ISNUMBER(R20)),"Percentuais ≥ 100%",IF(N(D20)=0,"Sem tempo",IF(J20=0,"Sem materiais",""))))
... A29: 6.1 | B29: Raspagem periodontal a retalho | C29: Clínica Geral | D29: 90 | E29: 0 | F29: 60 | J29: =IF($B29="","",SUMIFS(Itens!$E$2:$E$158,Itens!$A$2:$A$158,$B29)+N(F29)) | K29: =IF($B29="","",N(D29)/60*Parâmetros!$B$57) | L29: =IF($B29="","",N(D29)/60*Parâmetros!$B$60) | M29: =IF($B29="","",J29+N(E29)+K29+L29) | N29: =IF($B29="","",IF(H29="",Parâmetros!$B$62,H29)) | O29: =IF($B29="","",IF(I29="",Parâmetros!$B$63,I29)) | P29: =IF($B29="","",IF(1-(Parâmetros!$B$61+N29+Parâmetros!$B$78)-Parâmetros!$B$66-O29<=0,"ERRO",M29/(1-(Parâmetros!$B$61+N29+Parâmetros!$B$78)-Parâmetros!$B$66-O29))) | Q29: =IF($B29="","",IF((1-Parâmetros!$B$65)*(1-(Parâmetros!$B$61+N29+Parâmetros!$B$78))-O29<=0,"ERRO",(1-Parâmetros!$B$65)*M29/((1-Parâmetros!$B$65)*(1-(Parâmetros!$B$61+N29+Parâmetros!$B$78))-O29))) | R29: =IF($B29="","",IF(Parâmetros!$B$64=2,P29,Q29)) | S29: =IF($B29="","",IF(Parâmetros!$B$64=2,IF(1-(Parâmetros!$B$61+N29+Parâmetros!$B$78)-Parâmetros!$B$66<=0,"ERRO",M29/(1-(Parâmetros!$B$61+N29+Parâmetros!$B$78)-Parâmetros!$B$66)),IF((1-Parâmetros!$B$65)*(1-(Parâmetros!$B$61+N29+Parâmetros!$B$78))<=0,"ERRO",(1-Parâmetros!$B$65)*M29/((1-Parâmetros!$B$65)*(1-(Parâmetros!$B$61+N29+Parâmetros!$B$78)))))) | T29: =IF($B29="","",IF(ISNUMBER(R29),R29*Parâmetros!$B$61,"")) | U29: =IF($B29="","",IF(ISNUMBER(R29),R29*N29,"")) | V29: =IF($B29="","",IF(ISNUMBER(R29),R29*Parâmetros!$B$78,"")) | W29: =IF($B29="","",IF(ISNUMBER(R29),IF(Parâmetros!$B$64=2,R29*Parâmetros!$B$66,Parâmetros!$B$65*(R29-M29-R29*(Parâmetros!$B$61+N29+Parâmetros!$B$78))),"")) | X29: =IF($B29="","",IF(ISNUMBER(R29),R29-M29-T29-U29-V29-W29,"")) | Y29: =IF($B29="","",IF(AND(ISNUMBER(R29),R29>0),X29/R29,"")) | Z29: =IF($B29="","",IF(AND(ISNUMBER(R29),ISNUMBER(G29)),R29-G29,"")) | AA29: =IF($B29="","",IF(NOT(ISNUMBER(R29)),"Percentuais ≥ 100%",IF(N(D29)=0,"Sem tempo",IF(J29=0,"Sem materiais",""))))
A30: 7.0 | B30: Implante unitário | C30: Implante | D30: 0 | E30: 0 | F30: 0 | I30: 0.2 | J30: =IF($B30="","",SUMIFS(Itens!$E$2:$E$158,Itens!$A$2:$A$158,$B30)+N(F30)) | K30: =IF($B30="","",N(D30)/60*Parâmetros!$B$57) | L30: =IF($B30="","",N(D30)/60*Parâmetros!$B$60) | M30: =IF($B30="","",J30+N(E30)+K30+L30) | N30: =IF($B30="","",IF(H30="",Parâmetros!$B$62,H30)) | O30: =IF($B30="","",IF(I30="",Parâmetros!$B$63,I30)) | P30: =IF($B30="","",IF(1-(Parâmetros!$B$61+N30+Parâmetros!$B$78)-Parâmetros!$B$66-O30<=0,"ERRO",M30/(1-(Parâmetros!$B$61+N30+Parâmetros!$B$78)-Parâmetros!$B$66-O30))) | Q30: =IF($B30="","",IF((1-Parâmetros!$B$65)*(1-(Parâmetros!$B$61+N30+Parâmetros!$B$78))-O30<=0,"ERRO",(1-Parâmetros!$B$65)*M30/((1-Parâmetros!$B$65)*(1-(Parâmetros!$B$61+N30+Parâmetros!$B$78))-O30))) | R30: =IF($B30="","",IF(Parâmetros!$B$64=2,P30,Q30)) | S30: =IF($B30="","",IF(Parâmetros!$B$64=2,IF(1-(Parâmetros!$B$61+N30+Parâmetros!$B$78)-Parâmetros!$B$66<=0,"ERRO",M30/(1-(Parâmetros!$B$61+N30+Parâmetros!$B$78)-Parâmetros!$B$66)),IF((1-Parâmetros!$B$65)*(1-(Parâmetros!$B$61+N30+Parâmetros!$B$78))<=0,"ERRO",(1-Parâmetros!$B$65)*M30/((1-Parâmetros!$B$65)*(1-(Parâmetros!$B$61+N30+Parâmetros!$B$78)))))) | T30: =IF($B30="","",IF(ISNUMBER(R30),R30*Parâmetros!$B$61,"")) | U30: =IF($B30="","",IF(ISNUMBER(R30),R30*N30,"")) | V30: =IF($B30="","",IF(ISNUMBER(R30),R30*Parâmetros!$B$78,"")) | W30: =IF($B30="","",IF(ISNUMBER(R30),IF(Parâmetros!$B$64=2,R30*Parâmetros!$B$66,Parâmetros!$B$65*(R30-M30-R30*(Parâmetros!$B$61+N30+Parâmetros!$B$78))),"")) | X30: =IF($B30="","",IF(ISNUMBER(R30),R30-M30-T30-U30-V30-W30,"")) | Y30: =IF($B30="","",IF(AND(ISNUMBER(R30),R30>0),X30/R30,"")) | Z30: =IF($B30="","",IF(AND(ISNUMBER(R30),ISNUMBER(G30)),R30-G30,"")) | AA30: =IF($B30="","",IF(NOT(ISNUMBER(R30)),"Percentuais ≥ 100%",IF(N(D30)=0,"Sem tempo",IF(J30=0,"Sem materiais",""))))
A31: 7.1 | B31: Implante unitário com enxerto ósseo | C31: Implante | D31: 0 | E31: 0 | F31: 0 | I31: 0.2 | J31: =IF($B31="","",SUMIFS(Itens!$E$2:$E$158,Itens!$A$2:$A$158,$B31)+N(F31)) | K31: =IF($B31="","",N(D31)/60*Parâmetros!$B$57) | L31: =IF($B31="","",N(D31)/60*Parâmetros!$B$60) | M31: =IF($B31="","",J31+N(E31)+K31+L31) | N31: =IF($B31="","",IF(H31="",Parâmetros!$B$62,H31)) | O31: =IF($B31="","",IF(I31="",Parâmetros!$B$63,I31)) | P31: =IF($B31="","",IF(1-(Parâmetros!$B$61+N31+Parâmetros!$B$78)-Parâmetros!$B$66-O31<=0,"ERRO",M31/(1-(Parâmetros!$B$61+N31+Parâmetros!$B$78)-Parâmetros!$B$66-O31))) | Q31: =IF($B31="","",IF((1-Parâmetros!$B$65)*(1-(Parâmetros!$B$61+N31+Parâmetros!$B$78))-O31<=0,"ERRO",(1-Parâmetros!$B$65)*M31/((1-Parâmetros!$B$65)*(1-(Parâmetros!$B$61+N31+Parâmetros!$B$78))-O31))) | R31: =IF($B31="","",IF(Parâmetros!$B$64=2,P31,Q31)) | S31: =IF($B31="","",IF(Parâmetros!$B$64=2,IF(1-(Parâmetros!$B$61+N31+Parâmetros!$B$78)-Parâmetros!$B$66<=0,"ERRO",M31/(1-(Parâmetros!$B$61+N31+Parâmetros!$B$78)-Parâmetros!$B$66)),IF((1-Parâmetros!$B$65)*(1-(Parâmetros!$B$61+N31+Parâmetros!$B$78))<=0,"ERRO",(1-Parâmetros!$B$65)*M31/((1-Parâmetros!$B$65)*(1-(Parâmetros!$B$61+N31+Parâmetros!$B$78)))))) | T31: =IF($B31="","",IF(ISNUMBER(R31),R31*Parâmetros!$B$61,"")) | U31: =IF($B31="","",IF(ISNUMBER(R31),R31*N31,"")) | V31: =IF($B31="","",IF(ISNUMBER(R31),R31*Parâmetros!$B$78,"")) | W31: =IF($B31="","",IF(ISNUMBER(R31),IF(Parâmetros!$B$64=2,R31*Parâmetros!$B$66,Parâmetros!$B$65*(R31-M31-R31*(Parâmetros!$B$61+N31+Parâmetros!$B$78))),"")) | X31: =IF($B31="","",IF(ISNUMBER(R31),R31-M31-T31-U31-V31-W31,"")) | Y31: =IF($B31="","",IF(AND(ISNUMBER(R31),R31>0),X31/R31,"")) | Z31: =IF($B31="","",IF(AND(ISNUMBER(R31),ISNUMBER(G31)),R31-G31,"")) | AA31: =IF($B31="","",IF(NOT(ISNUMBER(R31)),"Percentuais ≥ 100%",IF(N(D31)=0,"Sem tempo",IF(J31=0,"Sem materiais",""))))
A32: 8.0 | B32: Manutenção ortodontica convencional nac | C32: Ortodontia | D32: 30 | E32: 0 | F32: 7 | G32: 120 | J32: =IF($B32="","",SUMIFS(Itens!$E$2:$E$158,Itens!$A$2:$A$158,$B32)+N(F32)) | K32: =IF($B32="","",N(D32)/60*Parâmetros!$B$57) | L32: =IF($B32="","",N(D32)/60*Parâmetros!$B$60) | M32: =IF($B32="","",J32+N(E32)+K32+L32) | N32: =IF($B32="","",IF(H32="",Parâmetros!$B$62,H32)) | O32: =IF($B32="","",IF(I32="",Parâmetros!$B$63,I32)) | P32: =IF($B32="","",IF(1-(Parâmetros!$B$61+N32+Parâmetros!$B$78)-Parâmetros!$B$66-O32<=0,"ERRO",M32/(1-(Parâmetros!$B$61+N32+Parâmetros!$B$78)-Parâmetros!$B$66-O32))) | Q32: =IF($B32="","",IF((1-Parâmetros!$B$65)*(1-(Parâmetros!$B$61+N32+Parâmetros!$B$78))-O32<=0,"ERRO",(1-Parâmetros!$B$65)*M32/((1-Parâmetros!$B$65)*(1-(Parâmetros!$B$61+N32+Parâmetros!$B$78))-O32))) | R32: =IF($B32="","",IF(Parâmetros!$B$64=2,P32,Q32)) | S32: =IF($B32="","",IF(Parâmetros!$B$64=2,IF(1-(Parâmetros!$B$61+N32+Parâmetros!$B$78)-Parâmetros!$B$66<=0,"ERRO",M32/(1-(Parâmetros!$B$61+N32+Parâmetros!$B$78)-Parâmetros!$B$66)),IF((1-Parâmetros!$B$65)*(1-(Parâmetros!$B$61+N32+Parâmetros!$B$78))<=0,"ERRO",(1-Parâmetros!$B$65)*M32/((1-Parâmetros!$B$65)*(1-(Parâmetros!$B$61+N32+Parâmetros!$B$78)))))) | T32: =IF($B32="","",IF(ISNUMBER(R32),R32*Parâmetros!$B$61,"")) | U32: =IF($B32="","",IF(ISNUMBER(R32),R32*N32,"")) | V32: =IF($B32="","",IF(ISNUMBER(R32),R32*Parâmetros!$B$78,"")) | W32: =IF($B32="","",IF(ISNUMBER(R32),IF(Parâmetros!$B$64=2,R32*Parâmetros!$B$66,Parâmetros!$B$65*(R32-M32-R32*(Parâmetros!$B$61+N32+Parâmetros!$B$78))),"")) | X32: =IF($B32="","",IF(ISNUMBER(R32),R32-M32-T32-U32-V32-W32,"")) | Y32: =IF($B32="","",IF(AND(ISNUMBER(R32),R32>0),X32/R32,"")) | Z32: =IF($B32="","",IF(AND(ISNUMBER(R32),ISNUMBER(G32)),R32-G32,"")) | AA32: =IF($B32="","",IF(NOT(ISNUMBER(R32)),"Percentuais ≥ 100%",IF(N(D32)=0,"Sem tempo",IF(J32=0,"Sem materiais",""))))
A33: 8.1 | B33: Manutenção ortodontica convencional imp | C33: Ortodontia | D33: 30 | E33: 0 | F33: 7.5 | G33: 120 | J33: =IF($B33="","",SUMIFS(Itens!$E$2:$E$158,Itens!$A$2:$A$158,$B33)+N(F33)) | K33: =IF($B33="","",N(D33)/60*Parâmetros!$B$57) | L33: =IF($B33="","",N(D33)/60*Parâmetros!$B$60) | M33: =IF($B33="","",J33+N(E33)+K33+L33) | N33: =IF($B33="","",IF(H33="",Parâmetros!$B$62,H33)) | O33: =IF($B33="","",IF(I33="",Parâmetros!$B$63,I33)) | P33: =IF($B33="","",IF(1-(Parâmetros!$B$61+N33+Parâmetros!$B$78)-Parâmetros!$B$66-O33<=0,"ERRO",M33/(1-(Parâmetros!$B$61+N33+Parâmetros!$B$78)-Parâmetros!$B$66-O33))) | Q33: =IF($B33="","",IF((1-Parâmetros!$B$65)*(1-(Parâmetros!$B$61+N33+Parâmetros!$B$78))-O33<=0,"ERRO",(1-Parâmetros!$B$65)*M33/((1-Parâmetros!$B$65)*(1-(Parâmetros!$B$61+N33+Parâmetros!$B$78))-O33))) | R33: =IF($B33="","",IF(Parâmetros!$B$64=2,P33,Q33)) | S33: =IF($B33="","",IF(Parâmetros!$B$64=2,IF(1-(Parâmetros!$B$61+N33+Parâmetros!$B$78)-Parâmetros!$B$66<=0,"ERRO",M33/(1-(Parâmetros!$B$61+N33+Parâmetros!$B$78)-Parâmetros!$B$66)),IF((1-Parâmetros!$B$65)*(1-(Parâmetros!$B$61+N33+Parâmetros!$B$78))<=0,"ERRO",(1-Parâmetros!$B$65)*M33/((1-Parâmetros!$B$65)*(1-(Parâmetros!$B$61+N33+Parâmetros!$B$78)))))) | T33: =IF($B33="","",IF(ISNUMBER(R33),R33*Parâmetros!$B$61,"")) | U33: =IF($B33="","",IF(ISNUMBER(R33),R33*N33,"")) | V33: =IF($B33="","",IF(ISNUMBER(R33),R33*Parâmetros!$B$78,"")) | W33: =IF($B33="","",IF(ISNUMBER(R33),IF(Parâmetros!$B$64=2,R33*Parâmetros!$B$66,Parâmetros!$B$65*(R33-M33-R33*(Parâmetros!$B$61+N33+Parâmetros!$B$78))),"")) | X33: =IF($B33="","",IF(ISNUMBER(R33),R33-M33-T33-U33-V33-W33,"")) | Y33: =IF($B33="","",IF(AND(ISNUMBER(R33),R33>0),X33/R33,"")) | Z33: =IF($B33="","",IF(AND(ISNUMBER(R33),ISNUMBER(G33)),R33-G33,"")) | AA33: =IF($B33="","",IF(NOT(ISNUMBER(R33)),"Percentuais ≥ 100%",IF(N(D33)=0,"Sem tempo",IF(J33=0,"Sem materiais",""))))
A34: 8.2 | B34: Manutenção ortodontica autoligado metálico | C34: Ortodontia | D34: 30 | E34: 0 | F34: 20 | G34: 220 | J34: =IF($B34="","",SUMIFS(Itens!$E$2:$E$158,Itens!$A$2:$A$158,$B34)+N(F34)) | K34: =IF($B34="","",N(D34)/60*Parâmetros!$B$57) | L34: =IF($B34="","",N(D34)/60*Parâmetros!$B$60) | M34: =IF($B34="","",J34+N(E34)+K34+L34) | N34: =IF($B34="","",IF(H34="",Parâmetros!$B$62,H34)) | O34: =IF($B34="","",IF(I34="",Parâmetros!$B$63,I34)) | P34: =IF($B34="","",IF(1-(Parâmetros!$B$61+N34+Parâmetros!$B$78)-Parâmetros!$B$66-O34<=0,"ERRO",M34/(1-(Parâmetros!$B$61+N34+Parâmetros!$B$78)-Parâmetros!$B$66-O34))) | Q34: =IF($B34="","",IF((1-Parâmetros!$B$65)*(1-(Parâmetros!$B$61+N34+Parâmetros!$B$78))-O34<=0,"ERRO",(1-Parâmetros!$B$65)*M34/((1-Parâmetros!$B$65)*(1-(Parâmetros!$B$61+N34+Parâmetros!$B$78))-O34))) | R34: =IF($B34="","",IF(Parâmetros!$B$64=2,P34,Q34)) | S34: =IF($B34="","",IF(Parâmetros!$B$64=2,IF(1-(Parâmetros!$B$61+N34+Parâmetros!$B$78)-Parâmetros!$B$66<=0,"ERRO",M34/(1-(Parâmetros!$B$61+N34+Parâmetros!$B$78)-Parâmetros!$B$66)),IF((1-Parâmetros!$B$65)*(1-(Parâmetros!$B$61+N34+Parâmetros!$B$78))<=0,"ERRO",(1-Parâmetros!$B$65)*M34/((1-Parâmetros!$B$65)*(1-(Parâmetros!$B$61+N34+Parâmetros!$B$78)))))) | T34: =IF($B34="","",IF(ISNUMBER(R34),R34*Parâmetros!$B$61,"")) | U34: =IF($B34="","",IF(ISNUMBER(R34),R34*N34,"")) | V34: =IF($B34="","",IF(ISNUMBER(R34),R34*Parâmetros!$B$78,"")) | W34: =IF($B34="","",IF(ISNUMBER(R34),IF(Parâmetros!$B$64=2,R34*Parâmetros!$B$66,Parâmetros!$B$65*(R34-M34-R34*(Parâmetros!$B$61+N34+Parâmetros!$B$78))),"")) | X34: =IF($B34="","",IF(ISNUMBER(R34),R34-M34-T34-U34-V34-W34,"")) | Y34: =IF($B34="","",IF(AND(ISNUMBER(R34),R34>0),X34/R34,"")) | Z34: =IF($B34="","",IF(AND(ISNUMBER(R34),ISNUMBER(G34)),R34-G34,"")) | AA34: =IF($B34="","",IF(NOT(ISNUMBER(R34)),"Percentuais ≥ 100%",IF(N(D34)=0,"Sem tempo",IF(J34=0,"Sem materiais",""))))
A35: 8.3 | B35: Manutenção ortodontica safira | C35: Ortodontia | D35: 30 | E35: 0 | F35: 60 | G35: 260 | J35: =IF($B35="","",SUMIFS(Itens!$E$2:$E$158,Itens!$A$2:$A$158,$B35)+N(F35)) | K35: =IF($B35="","",N(D35)/60*Parâmetros!$B$57) | L35: =IF($B35="","",N(D35)/60*Parâmetros!$B$60) | M35: =IF($B35="","",J35+N(E35)+K35+L35) | N35: =IF($B35="","",IF(H35="",Parâmetros!$B$62,H35)) | O35: =IF($B35="","",IF(I35="",Parâmetros!$B$63,I35)) | P35: =IF($B35="","",IF(1-(Parâmetros!$B$61+N35+Parâmetros!$B$78)-Parâmetros!$B$66-O35<=0,"ERRO",M35/(1-(Parâmetros!$B$61+N35+Parâmetros!$B$78)-Parâmetros!$B$66-O35))) | Q35: =IF($B35="","",IF((1-Parâmetros!$B$65)*(1-(Parâmetros!$B$61+N35+Parâmetros!$B$78))-O35<=0,"ERRO",(1-Parâmetros!$B$65)*M35/((1-Parâmetros!$B$65)*(1-(Parâmetros!$B$61+N35+Parâmetros!$B$78))-O35))) | R35: =IF($B35="","",IF(Parâmetros!$B$64=2,P35,Q35)) | S35: =IF($B35="","",IF(Parâmetros!$B$64=2,IF(1-(Parâmetros!$B$61+N35+Parâmetros!$B$78)-Parâmetros!$B$66<=0,"ERRO",M35/(1-(Parâmetros!$B$61+N35+Parâmetros!$B$78)-Parâmetros!$B$66)),IF((1-Parâmetros!$B$65)*(1-(Parâmetros!$B$61+N35+Parâmetros!$B$78))<=0,"ERRO",(1-Parâmetros!$B$65)*M35/((1-Parâmetros!$B$65)*(1-(Parâmetros!$B$61+N35+Parâmetros!$B$78)))))) | T35: =IF($B35="","",IF(ISNUMBER(R35),R35*Parâmetros!$B$61,"")) | U35: =IF($B35="","",IF(ISNUMBER(R35),R35*N35,"")) | V35: =IF($B35="","",IF(ISNUMBER(R35),R35*Parâmetros!$B$78,"")) | W35: =IF($B35="","",IF(ISNUMBER(R35),IF(Parâmetros!$B$64=2,R35*Parâmetros!$B$66,Parâmetros!$B$65*(R35-M35-R35*(Parâmetros!$B$61+N35+Parâmetros!$B$78))),"")) | X35: =IF($B35="","",IF(ISNUMBER(R35),R35-M35-T35-U35-V35-W35,"")) | Y35: =IF($B35="","",IF(AND(ISNUMBER(R35),R35>0),X35/R35,"")) | Z35: =IF($B35="","",IF(AND(ISNUMBER(R35),ISNUMBER(G35)),R35-G35,"")) | AA35: =IF($B35="","",IF(NOT(ISNUMBER(R35)),"Percentuais ≥ 100%",IF(N(D35)=0,"Sem tempo",IF(J35=0,"Sem materiais",""))))
A36: 9.0 | B36: Instalação aparelho metálico conv nacional | C36: Ortodontia | D36: 90 | E36: 0 | F36: 36.78 | G36: 450 | J36: =IF($B36="","",SUMIFS(Itens!$E$2:$E$158,Itens!$A$2:$A$158,$B36)+N(F36)) | K36: =IF($B36="","",N(D36)/60*Parâmetros!$B$57) | L36: =IF($B36="","",N(D36)/60*Parâmetros!$B$60) | M36: =IF($B36="","",J36+N(E36)+K36+L36) | N36: =IF($B36="","",IF(H36="",Parâmetros!$B$62,H36)) | O36: =IF($B36="","",IF(I36="",Parâmetros!$B$63,I36)) | P36: =IF($B36="","",IF(1-(Parâmetros!$B$61+N36+Parâmetros!$B$78)-Parâmetros!$B$66-O36<=0,"ERRO",M36/(1-(Parâmetros!$B$61+N36+Parâmetros!$B$78)-Parâmetros!$B$66-O36))) | Q36: =IF($B36="","",IF((1-Parâmetros!$B$65)*(1-(Parâmetros!$B$61+N36+Parâmetros!$B$78))-O36<=0,"ERRO",(1-Parâmetros!$B$65)*M36/((1-Parâmetros!$B$65)*(1-(Parâmetros!$B$61+N36+Parâmetros!$B$78))-O36))) | R36: =IF($B36="","",IF(Parâmetros!$B$64=2,P36,Q36)) | S36: =IF($B36="","",IF(Parâmetros!$B$64=2,IF(1-(Parâmetros!$B$61+N36+Parâmetros!$B$78)-Parâmetros!$B$66<=0,"ERRO",M36/(1-(Parâmetros!$B$61+N36+Parâmetros!$B$78)-Parâmetros!$B$66)),IF((1-Parâmetros!$B$65)*(1-(Parâmetros!$B$61+N36+Parâmetros!$B$78))<=0,"ERRO",(1-Parâmetros!$B$65)*M36/((1-Parâmetros!$B$65)*(1-(Parâmetros!$B$61+N36+Parâmetros!$B$78)))))) | T36: =IF($B36="","",IF(ISNUMBER(R36),R36*Parâmetros!$B$61,"")) | U36: =IF($B36="","",IF(ISNUMBER(R36),R36*N36,"")) | V36: =IF($B36="","",IF(ISNUMBER(R36),R36*Parâmetros!$B$78,"")) | W36: =IF($B36="","",IF(ISNUMBER(R36),IF(Parâmetros!$B$64=2,R36*Parâmetros!$B$66,Parâmetros!$B$65*(R36-M36-R36*(Parâmetros!$B$61+N36+Parâmetros!$B$78))),"")) | X36: =IF($B36="","",IF(ISNUMBER(R36),R36-M36-T36-U36-V36-W36,"")) | Y36: =IF($B36="","",IF(AND(ISNUMBER(R36),R36>0),X36/R36,"")) | Z36: =IF($B36="","",IF(AND(ISNUMBER(R36),ISNUMBER(G36)),R36-G36,"")) | AA36: =IF($B36="","",IF(NOT(ISNUMBER(R36)),"Percentuais ≥ 100%",IF(N(D36)=0,"Sem tempo",IF(J36=0,"Sem materiais",""))))
A37: 9.1 | B37: Instalação aparelho metálico conv importado | C37: Ortodontia | D37: 90 | E37: 0 | F37: 39.78 | G37: 700 | J37: =IF($B37="","",SUMIFS(Itens!$E$2:$E$158,Itens!$A$2:$A$158,$B37)+N(F37)) | K37: =IF($B37="","",N(D37)/60*Parâmetros!$B$57) | L37: =IF($B37="","",N(D37)/60*Parâmetros!$B$60) | M37: =IF($B37="","",J37+N(E37)+K37+L37) | N37: =IF($B37="","",IF(H37="",Parâmetros!$B$62,H37)) | O37: =IF($B37="","",IF(I37="",Parâmetros!$B$63,I37)) | P37: =IF($B37="","",IF(1-(Parâmetros!$B$61+N37+Parâmetros!$B$78)-Parâmetros!$B$66-O37<=0,"ERRO",M37/(1-(Parâmetros!$B$61+N37+Parâmetros!$B$78)-Parâmetros!$B$66-O37))) | Q37: =IF($B37="","",IF((1-Parâmetros!$B$65)*(1-(Parâmetros!$B$61+N37+Parâmetros!$B$78))-O37<=0,"ERRO",(1-Parâmetros!$B$65)*M37/((1-Parâmetros!$B$65)*(1-(Parâmetros!$B$61+N37+Parâmetros!$B$78))-O37))) | R37: =IF($B37="","",IF(Parâmetros!$B$64=2,P37,Q37)) | S37: =IF($B37="","",IF(Parâmetros!$B$64=2,IF(1-(Parâmetros!$B$61+N37+Parâmetros!$B$78)-Parâmetros!$B$66<=0,"ERRO",M37/(1-(Parâmetros!$B$61+N37+Parâmetros!$B$78)-Parâmetros!$B$66)),IF((1-Parâmetros!$B$65)*(1-(Parâmetros!$B$61+N37+Parâmetros!$B$78))<=0,"ERRO",(1-Parâmetros!$B$65)*M37/((1-Parâmetros!$B$65)*(1-(Parâmetros!$B$61+N37+Parâmetros!$B$78)))))) | T37: =IF($B37="","",IF(ISNUMBER(R37),R37*Parâmetros!$B$61,"")) | U37: =IF($B37="","",IF(ISNUMBER(R37),R37*N37,"")) | V37: =IF($B37="","",IF(ISNUMBER(R37),R37*Parâmetros!$B$78,"")) | W37: =IF($B37="","",IF(ISNUMBER(R37),IF(Parâmetros!$B$64=2,R37*Parâmetros!$B$66,Parâmetros!$B$65*(R37-M37-R37*(Parâmetros!$B$61+N37+Parâmetros!$B$78))),"")) | X37: =IF($B37="","",IF(ISNUMBER(R37),R37-M37-T37-U37-V37-W37,"")) | Y37: =IF($B37="","",IF(AND(ISNUMBER(R37),R37>0),X37/R37,"")) | Z37: =IF($B37="","",IF(AND(ISNUMBER(R37),ISNUMBER(G37)),R37-G37,"")) | AA37: =IF($B37="","",IF(NOT(ISNUMBER(R37)),"Percentuais ≥ 100%",IF(N(D37)=0,"Sem tempo",IF(J37=0,"Sem materiais",""))))
A38: 9.2 | B38: Instalação aparelho autoligado metálico | C38: Ortodontia | D38: 90 | E38: 0 | F38: 297.48 | G38: 1200 | J38: =IF($B38="","",SUMIFS(Itens!$E$2:$E$158,Itens!$A$2:$A$158,$B38)+N(F38)) | K38: =IF($B38="","",N(D38)/60*Parâmetros!$B$57) | L38: =IF($B38="","",N(D38)/60*Parâmetros!$B$60) | M38: =IF($B38="","",J38+N(E38)+K38+L38) | N38: =IF($B38="","",IF(H38="",Parâmetros!$B$62,H38)) | O38: =IF($B38="","",IF(I38="",Parâmetros!$B$63,I38)) | P38: =IF($B38="","",IF(1-(Parâmetros!$B$61+N38+Parâmetros!$B$78)-Parâmetros!$B$66-O38<=0,"ERRO",M38/(1-(Parâmetros!$B$61+N38+Parâmetros!$B$78)-Parâmetros!$B$66-O38))) | Q38: =IF($B38="","",IF((1-Parâmetros!$B$65)*(1-(Parâmetros!$B$61+N38+Parâmetros!$B$78))-O38<=0,"ERRO",(1-Parâmetros!$B$65)*M38/((1-Parâmetros!$B$65)*(1-(Parâmetros!$B$61+N38+Parâmetros!$B$78))-O38))) | R38: =IF($B38="","",IF(Parâmetros!$B$64=2,P38,Q38)) | S38: =IF($B38="","",IF(Parâmetros!$B$64=2,IF(1-(Parâmetros!$B$61+N38+Parâmetros!$B$78)-Parâmetros!$B$66<=0,"ERRO",M38/(1-(Parâmetros!$B$61+N38+Parâmetros!$B$78)-Parâmetros!$B$66)),IF((1-Parâmetros!$B$65)*(1-(Parâmetros!$B$61+N38+Parâmetros!$B$78))<=0,"ERRO",(1-Parâmetros!$B$65)*M38/((1-Parâmetros!$B$65)*(1-(Parâmetros!$B$61+N38+Parâmetros!$B$78)))))) | T38: =IF($B38="","",IF(ISNUMBER(R38),R38*Parâmetros!$B$61,"")) | U38: =IF($B38="","",IF(ISNUMBER(R38),R38*N38,"")) | V38: =IF($B38="","",IF(ISNUMBER(R38),R38*Parâmetros!$B$78,"")) | W38: =IF($B38="","",IF(ISNUMBER(R38),IF(Parâmetros!$B$64=2,R38*Parâmetros!$B$66,Parâmetros!$B$65*(R38-M38-R38*(Parâmetros!$B$61+N38+Parâmetros!$B$78))),"")) | X38: =IF($B38="","",IF(ISNUMBER(R38),R38-M38-T38-U38-V38-W38,"")) | Y38: =IF($B38="","",IF(AND(ISNUMBER(R38),R38>0),X38/R38,"")) | Z38: =IF($B38="","",IF(AND(ISNUMBER(R38),ISNUMBER(G38)),R38-G38,"")) | AA38: =IF($B38="","",IF(NOT(ISNUMBER(R38)),"Percentuais ≥ 100%",IF(N(D38)=0,"Sem tempo",IF(J38=0,"Sem materiais",""))))
A39: 9.3 | B39: Instalação aparelho safira | C39: Ortodontia | D39: 90 | E39: 0 | F39: 808.78 | G39: 2600 | J39: =IF($B39="","",SUMIFS(Itens!$E$2:$E$158,Itens!$A$2:$A$158,$B39)+N(F39)) | K39: =IF($B39="","",N(D39)/60*Parâmetros!$B$57) | L39: =IF($B39="","",N(D39)/60*Parâmetros!$B$60) | M39: =IF($B39="","",J39+N(E39)+K39+L39) | N39: =IF($B39="","",IF(H39="",Parâmetros!$B$62,H39)) | O39: =IF($B39="","",IF(I39="",Parâmetros!$B$63,I39)) | P39: =IF($B39="","",IF(1-(Parâmetros!$B$61+N39+Parâmetros!$B$78)-Parâmetros!$B$66-O39<=0,"ERRO",M39/(1-(Parâmetros!$B$61+N39+Parâmetros!$B$78)-Parâmetros!$B$66-O39))) | Q39: =IF($B39="","",IF((1-Parâmetros!$B$65)*(1-(Parâmetros!$B$61+N39+Parâmetros!$B$78))-O39<=0,"ERRO",(1-Parâmetros!$B$65)*M39/((1-Parâmetros!$B$65)*(1-(Parâmetros!$B$61+N39+Parâmetros!$B$78))-O39))) | R39: =IF($B39="","",IF(Parâmetros!$B$64=2,P39,Q39)) | S39: =IF($B39="","",IF(Parâmetros!$B$64=2,IF(1-(Parâmetros!$B$61+N39+Parâmetros!$B$78)-Parâmetros!$B$66<=0,"ERRO",M39/(1-(Parâmetros!$B$61+N39+Parâmetros!$B$78)-Parâmetros!$B$66)),IF((1-Parâmetros!$B$65)*(1-(Parâmetros!$B$61+N39+Parâmetros!$B$78))<=0,"ERRO",(1-Parâmetros!$B$65)*M39/((1-Parâmetros!$B$65)*(1-(Parâmetros!$B$61+N39+Parâmetros!$B$78)))))) | T39: =IF($B39="","",IF(ISNUMBER(R39),R39*Parâmetros!$B$61,"")) | U39: =IF($B39="","",IF(ISNUMBER(R39),R39*N39,"")) | V39: =IF($B39="","",IF(ISNUMBER(R39),R39*Parâmetros!$B$78,"")) | W39: =IF($B39="","",IF(ISNUMBER(R39),IF(Parâmetros!$B$64=2,R39*Parâmetros!$B$66,Parâmetros!$B$65*(R39-M39-R39*(Parâmetros!$B$61+N39+Parâmetros!$B$78))),"")) | X39: =IF($B39="","",IF(ISNUMBER(R39),R39-M39-T39-U39-V39-W39,"")) | Y39: =IF($B39="","",IF(AND(ISNUMBER(R39),R39>0),X39/R39,"")) | Z39: =IF($B39="","",IF(AND(ISNUMBER(R39),ISNUMBER(G39)),R39-G39,"")) | AA39: =IF($B39="","",IF(NOT(ISNUMBER(R39)),"Percentuais ≥ 100%",IF(N(D39)=0,"Sem tempo",IF(J39=0,"Sem materiais",""))))
A40: 10.0 | B40: Invisalign light | C40: Ortodontia | D40: 180 | E40: 0 | F40: 5607 | G40: 7000 | J40: =IF($B40="","",SUMIFS(Itens!$E$2:$E$158,Itens!$A$2:$A$158,$B40)+N(F40)) | K40: =IF($B40="","",N(D40)/60*Parâmetros!$B$57) | L40: =IF($B40="","",N(D40)/60*Parâmetros!$B$60) | M40: =IF($B40="","",J40+N(E40)+K40+L40) | N40: =IF($B40="","",IF(H40="",Parâmetros!$B$62,H40)) | O40: =IF($B40="","",IF(I40="",Parâmetros!$B$63,I40)) | P40: =IF($B40="","",IF(1-(Parâmetros!$B$61+N40+Parâmetros!$B$78)-Parâmetros!$B$66-O40<=0,"ERRO",M40/(1-(Parâmetros!$B$61+N40+Parâmetros!$B$78)-Parâmetros!$B$66-O40))) | Q40: =IF($B40="","",IF((1-Parâmetros!$B$65)*(1-(Parâmetros!$B$61+N40+Parâmetros!$B$78))-O40<=0,"ERRO",(1-Parâmetros!$B$65)*M40/((1-Parâmetros!$B$65)*(1-(Parâmetros!$B$61+N40+Parâmetros!$B$78))-O40))) | R40: =IF($B40="","",IF(Parâmetros!$B$64=2,P40,Q40)) | S40: =IF($B40="","",IF(Parâmetros!$B$64=2,IF(1-(Parâmetros!$B$61+N40+Parâmetros!$B$78)-Parâmetros!$B$66<=0,"ERRO",M40/(1-(Parâmetros!$B$61+N40+Parâmetros!$B$78)-Parâmetros!$B$66)),IF((1-Parâmetros!$B$65)*(1-(Parâmetros!$B$61+N40+Parâmetros!$B$78))<=0,"ERRO",(1-Parâmetros!$B$65)*M40/((1-Parâmetros!$B$65)*(1-(Parâmetros!$B$61+N40+Parâmetros!$B$78)))))) | T40: =IF($B40="","",IF(ISNUMBER(R40),R40*Parâmetros!$B$61,"")) | U40: =IF($B40="","",IF(ISNUMBER(R40),R40*N40,"")) | V40: =IF($B40="","",IF(ISNUMBER(R40),R40*Parâmetros!$B$78,"")) | W40: =IF($B40="","",IF(ISNUMBER(R40),IF(Parâmetros!$B$64=2,R40*Parâmetros!$B$66,Parâmetros!$B$65*(R40-M40-R40*(Parâmetros!$B$61+N40+Parâmetros!$B$78))),"")) | X40: =IF($B40="","",IF(ISNUMBER(R40),R40-M40-T40-U40-V40-W40,"")) | Y40: =IF($B40="","",IF(AND(ISNUMBER(R40),R40>0),X40/R40,"")) | Z40: =IF($B40="","",IF(AND(ISNUMBER(R40),ISNUMBER(G40)),R40-G40,"")) | AA40: =IF($B40="","",IF(NOT(ISNUMBER(R40)),"Percentuais ≥ 100%",IF(N(D40)=0,"Sem tempo",IF(J40=0,"Sem materiais",""))))
A41: 10.1 | B41: Invisalign moderate | C41: Ortodontia | D41: 420 | E41: 0 | F41: 7639 | G41: 10000 | J41: =IF($B41="","",SUMIFS(Itens!$E$2:$E$158,Itens!$A$2:$A$158,$B41)+N(F41)) | K41: =IF($B41="","",N(D41)/60*Parâmetros!$B$57) | L41: =IF($B41="","",N(D41)/60*Parâmetros!$B$60) | M41: =IF($B41="","",J41+N(E41)+K41+L41) | N41: =IF($B41="","",IF(H41="",Parâmetros!$B$62,H41)) | O41: =IF($B41="","",IF(I41="",Parâmetros!$B$63,I41)) | P41: =IF($B41="","",IF(1-(Parâmetros!$B$61+N41+Parâmetros!$B$78)-Parâmetros!$B$66-O41<=0,"ERRO",M41/(1-(Parâmetros!$B$61+N41+Parâmetros!$B$78)-Parâmetros!$B$66-O41))) | Q41: =IF($B41="","",IF((1-Parâmetros!$B$65)*(1-(Parâmetros!$B$61+N41+Parâmetros!$B$78))-O41<=0,"ERRO",(1-Parâmetros!$B$65)*M41/((1-Parâmetros!$B$65)*(1-(Parâmetros!$B$61+N41+Parâmetros!$B$78))-O41))) | R41: =IF($B41="","",IF(Parâmetros!$B$64=2,P41,Q41)) | S41: =IF($B41="","",IF(Parâmetros!$B$64=2,IF(1-(Parâmetros!$B$61+N41+Parâmetros!$B$78)-Parâmetros!$B$66<=0,"ERRO",M41/(1-(Parâmetros!$B$61+N41+Parâmetros!$B$78)-Parâmetros!$B$66)),IF((1-Parâmetros!$B$65)*(1-(Parâmetros!$B$61+N41+Parâmetros!$B$78))<=0,"ERRO",(1-Parâmetros!$B$65)*M41/((1-Parâmetros!$B$65)*(1-(Parâmetros!$B$61+N41+Parâmetros!$B$78)))))) | T41: =IF($B41="","",IF(ISNUMBER(R41),R41*Parâmetros!$B$61,"")) | U41: =IF($B41="","",IF(ISNUMBER(R41),R41*N41,"")) | V41: =IF($B41="","",IF(ISNUMBER(R41),R41*Parâmetros!$B$78,"")) | W41: =IF($B41="","",IF(ISNUMBER(R41),IF(Parâmetros!$B$64=2,R41*Parâmetros!$B$66,Parâmetros!$B$65*(R41-M41-R41*(Parâmetros!$B$61+N41+Parâmetros!$B$78))),"")) | X41: =IF($B41="","",IF(ISNUMBER(R41),R41-M41-T41-U41-V41-W41,"")) | Y41: =IF($B41="","",IF(AND(ISNUMBER(R41),R41>0),X41/R41,"")) | Z41: =IF($B41="","",IF(AND(ISNUMBER(R41),ISNUMBER(G41)),R41-G41,"")) | AA41: =IF($B41="","",IF(NOT(ISNUMBER(R41)),"Percentuais ≥ 100%",IF(N(D41)=0,"Sem tempo",IF(J41=0,"Sem materiais",""))))
A42: 10.2 | B42: Invisalign comprehensive | C42: Ortodontia | D42: 900 | E42: 0 | F42: 8480 | G42: 14000 | J42: =IF($B42="","",SUMIFS(Itens!$E$2:$E$158,Itens!$A$2:$A$158,$B42)+N(F42)) | K42: =IF($B42="","",N(D42)/60*Parâmetros!$B$57) | L42: =IF($B42="","",N(D42)/60*Parâmetros!$B$60) | M42: =IF($B42="","",J42+N(E42)+K42+L42) | N42: =IF($B42="","",IF(H42="",Parâmetros!$B$62,H42)) | O42: =IF($B42="","",IF(I42="",Parâmetros!$B$63,I42)) | P42: =IF($B42="","",IF(1-(Parâmetros!$B$61+N42+Parâmetros!$B$78)-Parâmetros!$B$66-O42<=0,"ERRO",M42/(1-(Parâmetros!$B$61+N42+Parâmetros!$B$78)-Parâmetros!$B$66-O42))) | Q42: =IF($B42="","",IF((1-Parâmetros!$B$65)*(1-(Parâmetros!$B$61+N42+Parâmetros!$B$78))-O42<=0,"ERRO",(1-Parâmetros!$B$65)*M42/((1-Parâmetros!$B$65)*(1-(Parâmetros!$B$61+N42+Parâmetros!$B$78))-O42))) | R42: =IF($B42="","",IF(Parâmetros!$B$64=2,P42,Q42)) | S42: =IF($B42="","",IF(Parâmetros!$B$64=2,IF(1-(Parâmetros!$B$61+N42+Parâmetros!$B$78)-Parâmetros!$B$66<=0,"ERRO",M42/(1-(Parâmetros!$B$61+N42+Parâmetros!$B$78)-Parâmetros!$B$66)),IF((1-Parâmetros!$B$65)*(1-(Parâmetros!$B$61+N42+Parâmetros!$B$78))<=0,"ERRO",(1-Parâmetros!$B$65)*M42/((1-Parâmetros!$B$65)*(1-(Parâmetros!$B$61+N42+Parâmetros!$B$78)))))) | T42: =IF($B42="","",IF(ISNUMBER(R42),R42*Parâmetros!$B$61,"")) | U42: =IF($B42="","",IF(ISNUMBER(R42),R42*N42,"")) | V42: =IF($B42="","",IF(ISNUMBER(R42),R42*Parâmetros!$B$78,"")) | W42: =IF($B42="","",IF(ISNUMBER(R42),IF(Parâmetros!$B$64=2,R42*Parâmetros!$B$66,Parâmetros!$B$65*(R42-M42-R42*(Parâmetros!$B$61+N42+Parâmetros!$B$78))),"")) | X42: =IF($B42="","",IF(ISNUMBER(R42),R42-M42-T42-U42-V42-W42,"")) | Y42: =IF($B42="","",IF(AND(ISNUMBER(R42),R42>0),X42/R42,"")) | Z42: =IF($B42="","",IF(AND(ISNUMBER(R42),ISNUMBER(G42)),R42-G42,"")) | AA42: =IF($B42="","",IF(NOT(ISNUMBER(R42)),"Percentuais ≥ 100%",IF(N(D42)=0,"Sem tempo",IF(J42=0,"Sem materiais",""))))
A43: 10.3 | B43: Contenção invisalign | C43: Ortodontia | D43: 60 | E43: 0 | F43: 555 | G43: 1000 | J43: =IF($B43="","",SUMIFS(Itens!$E$2:$E$158,Itens!$A$2:$A$158,$B43)+N(F43)) | K43: =IF($B43="","",N(D43)/60*Parâmetros!$B$57) | L43: =IF($B43="","",N(D43)/60*Parâmetros!$B$60) | M43: =IF($B43="","",J43+N(E43)+K43+L43) | N43: =IF($B43="","",IF(H43="",Parâmetros!$B$62,H43)) | O43: =IF($B43="","",IF(I43="",Parâmetros!$B$63,I43)) | P43: =IF($B43="","",IF(1-(Parâmetros!$B$61+N43+Parâmetros!$B$78)-Parâmetros!$B$66-O43<=0,"ERRO",M43/(1-(Parâmetros!$B$61+N43+Parâmetros!$B$78)-Parâmetros!$B$66-O43))) | Q43: =IF($B43="","",IF((1-Parâmetros!$B$65)*(1-(Parâmetros!$B$61+N43+Parâmetros!$B$78))-O43<=0,"ERRO",(1-Parâmetros!$B$65)*M43/((1-Parâmetros!$B$65)*(1-(Parâmetros!$B$61+N43+Parâmetros!$B$78))-O43))) | R43: =IF($B43="","",IF(Parâmetros!$B$64=2,P43,Q43)) | S43: =IF($B43="","",IF(Parâmetros!$B$64=2,IF(1-(Parâmetros!$B$61+N43+Parâmetros!$B$78)-Parâmetros!$B$66<=0,"ERRO",M43/(1-(Parâmetros!$B$61+N43+Parâmetros!$B$78)-Parâmetros!$B$66)),IF((1-Parâmetros!$B$65)*(1-(Parâmetros!$B$61+N43+Parâmetros!$B$78))<=0,"ERRO",(1-Parâmetros!$B$65)*M43/((1-Parâmetros!$B$65)*(1-(Parâmetros!$B$61+N43+Parâmetros!$B$78)))))) | T43: =IF($B43="","",IF(ISNUMBER(R43),R43*Parâmetros!$B$61,"")) | U43: =IF($B43="","",IF(ISNUMBER(R43),R43*N43,"")) | V43: =IF($B43="","",IF(ISNUMBER(R43),R43*Parâmetros!$B$78,"")) | W43: =IF($B43="","",IF(ISNUMBER(R43),IF(Parâmetros!$B$64=2,R43*Parâmetros!$B$66,Parâmetros!$B$65*(R43-M43-R43*(Parâmetros!$B$61+N43+Parâmetros!$B$78))),"")) | X43: =IF($B43="","",IF(ISNUMBER(R43),R43-M43-T43-U43-V43-W43,"")) | Y43: =IF($B43="","",IF(AND(ISNUMBER(R43),R43>0),X43/R43,"")) | Z43: =IF($B43="","",IF(AND(ISNUMBER(R43),ISNUMBER(G43)),R43-G43,"")) | AA43: =IF($B43="","",IF(NOT(ISNUMBER(R43)),"Percentuais ≥ 100%",IF(N(D43)=0,"Sem tempo",IF(J43=0,"Sem materiais",""))))
... A52: 12.3 | B52: Aparelho bionator | C52: Ortodontia | D52: 60 | E52: 0 | F52: 280 | G52: 700 | J52: =IF($B52="","",SUMIFS(Itens!$E$2:$E$158,Itens!$A$2:$A$158,$B52)+N(F52)) | K52: =IF($B52="","",N(D52)/60*Parâmetros!$B$57) | L52: =IF($B52="","",N(D52)/60*Parâmetros!$B$60) | M52: =IF($B52="","",J52+N(E52)+K52+L52) | N52: =IF($B52="","",IF(H52="",Parâmetros!$B$62,H52)) | O52: =IF($B52="","",IF(I52="",Parâmetros!$B$63,I52)) | P52: =IF($B52="","",IF(1-(Parâmetros!$B$61+N52+Parâmetros!$B$78)-Parâmetros!$B$66-O52<=0,"ERRO",M52/(1-(Parâmetros!$B$61+N52+Parâmetros!$B$78)-Parâmetros!$B$66-O52))) | Q52: =IF($B52="","",IF((1-Parâmetros!$B$65)*(1-(Parâmetros!$B$61+N52+Parâmetros!$B$78))-O52<=0,"ERRO",(1-Parâmetros!$B$65)*M52/((1-Parâmetros!$B$65)*(1-(Parâmetros!$B$61+N52+Parâmetros!$B$78))-O52))) | R52: =IF($B52="","",IF(Parâmetros!$B$64=2,P52,Q52)) | S52: =IF($B52="","",IF(Parâmetros!$B$64=2,IF(1-(Parâmetros!$B$61+N52+Parâmetros!$B$78)-Parâmetros!$B$66<=0,"ERRO",M52/(1-(Parâmetros!$B$61+N52+Parâmetros!$B$78)-Parâmetros!$B$66)),IF((1-Parâmetros!$B$65)*(1-(Parâmetros!$B$61+N52+Parâmetros!$B$78))<=0,"ERRO",(1-Parâmetros!$B$65)*M52/((1-Parâmetros!$B$65)*(1-(Parâmetros!$B$61+N52+Parâmetros!$B$78)))))) | T52: =IF($B52="","",IF(ISNUMBER(R52),R52*Parâmetros!$B$61,"")) | U52: =IF($B52="","",IF(ISNUMBER(R52),R52*N52,"")) | V52: =IF($B52="","",IF(ISNUMBER(R52),R52*Parâmetros!$B$78,"")) | W52: =IF($B52="","",IF(ISNUMBER(R52),IF(Parâmetros!$B$64=2,R52*Parâmetros!$B$66,Parâmetros!$B$65*(R52-M52-R52*(Parâmetros!$B$61+N52+Parâmetros!$B$78))),"")) | X52: =IF($B52="","",IF(ISNUMBER(R52),R52-M52-T52-U52-V52-W52,"")) | Y52: =IF($B52="","",IF(AND(ISNUMBER(R52),R52>0),X52/R52,"")) | Z52: =IF($B52="","",IF(AND(ISNUMBER(R52),ISNUMBER(G52)),R52-G52,"")) | AA52: =IF($B52="","",IF(NOT(ISNUMBER(R52)),"Percentuais ≥ 100%",IF(N(D52)=0,"Sem tempo",IF(J52=0,"Sem materiais",""))))
A53: 100.0 | B53: Preenchimento labial 1 seringa rennova fill | C53: HOF | D53: 90 | E53: 0 | F53: 450 | G53: 880 | I53: 0.2 | J53: =IF($B53="","",SUMIFS(Itens!$E$2:$E$158,Itens!$A$2:$A$158,$B53)+N(F53)) | K53: =IF($B53="","",N(D53)/60*Parâmetros!$B$57) | L53: =IF($B53="","",N(D53)/60*Parâmetros!$B$60) | M53: =IF($B53="","",J53+N(E53)+K53+L53) | N53: =IF($B53="","",IF(H53="",Parâmetros!$B$62,H53)) | O53: =IF($B53="","",IF(I53="",Parâmetros!$B$63,I53)) | P53: =IF($B53="","",IF(1-(Parâmetros!$B$61+N53+Parâmetros!$B$78)-Parâmetros!$B$66-O53<=0,"ERRO",M53/(1-(Parâmetros!$B$61+N53+Parâmetros!$B$78)-Parâmetros!$B$66-O53))) | Q53: =IF($B53="","",IF((1-Parâmetros!$B$65)*(1-(Parâmetros!$B$61+N53+Parâmetros!$B$78))-O53<=0,"ERRO",(1-Parâmetros!$B$65)*M53/((1-Parâmetros!$B$65)*(1-(Parâmetros!$B$61+N53+Parâmetros!$B$78))-O53))) | R53: =IF($B53="","",IF(Parâmetros!$B$64=2,P53,Q53)) | S53: =IF($B53="","",IF(Parâmetros!$B$64=2,IF(1-(Parâmetros!$B$61+N53+Parâmetros!$B$78)-Parâmetros!$B$66<=0,"ERRO",M53/(1-(Parâmetros!$B$61+N53+Parâmetros!$B$78)-Parâmetros!$B$66)),IF((1-Parâmetros!$B$65)*(1-(Parâmetros!$B$61+N53+Parâmetros!$B$78))<=0,"ERRO",(1-Parâmetros!$B$65)*M53/((1-Parâmetros!$B$65)*(1-(Parâmetros!$B$61+N53+Parâmetros!$B$78)))))) | T53: =IF($B53="","",IF(ISNUMBER(R53),R53*Parâmetros!$B$61,"")) | U53: =IF($B53="","",IF(ISNUMBER(R53),R53*N53,"")) | V53: =IF($B53="","",IF(ISNUMBER(R53),R53*Parâmetros!$B$78,"")) | W53: =IF($B53="","",IF(ISNUMBER(R53),IF(Parâmetros!$B$64=2,R53*Parâmetros!$B$66,Parâmetros!$B$65*(R53-M53-R53*(Parâmetros!$B$61+N53+Parâmetros!$B$78))),"")) | X53: =IF($B53="","",IF(ISNUMBER(R53),R53-M53-T53-U53-V53-W53,"")) | Y53: =IF($B53="","",IF(AND(ISNUMBER(R53),R53>0),X53/R53,"")) | Z53: =IF($B53="","",IF(AND(ISNUMBER(R53),ISNUMBER(G53)),R53-G53,"")) | AA53: =IF($B53="","",IF(NOT(ISNUMBER(R53)),"Percentuais ≥ 100%",IF(N(D53)=0,"Sem tempo",IF(J53=0,"Sem materiais",""))))
A54: 100.1 | B54: Preenchimento labial 1 seringa kissye restylane | C54: HOF | D54: 90 | E54: 0 | F54: 550 | G54: 1200 | I54: 0.2 | J54: =IF($B54="","",SUMIFS(Itens!$E$2:$E$158,Itens!$A$2:$A$158,$B54)+N(F54)) | K54: =IF($B54="","",N(D54)/60*Parâmetros!$B$57) | L54: =IF($B54="","",N(D54)/60*Parâmetros!$B$60) | M54: =IF($B54="","",J54+N(E54)+K54+L54) | N54: =IF($B54="","",IF(H54="",Parâmetros!$B$62,H54)) | O54: =IF($B54="","",IF(I54="",Parâmetros!$B$63,I54)) | P54: =IF($B54="","",IF(1-(Parâmetros!$B$61+N54+Parâmetros!$B$78)-Parâmetros!$B$66-O54<=0,"ERRO",M54/(1-(Parâmetros!$B$61+N54+Parâmetros!$B$78)-Parâmetros!$B$66-O54))) | Q54: =IF($B54="","",IF((1-Parâmetros!$B$65)*(1-(Parâmetros!$B$61+N54+Parâmetros!$B$78))-O54<=0,"ERRO",(1-Parâmetros!$B$65)*M54/((1-Parâmetros!$B$65)*(1-(Parâmetros!$B$61+N54+Parâmetros!$B$78))-O54))) | R54: =IF($B54="","",IF(Parâmetros!$B$64=2,P54,Q54)) | S54: =IF($B54="","",IF(Parâmetros!$B$64=2,IF(1-(Parâmetros!$B$61+N54+Parâmetros!$B$78)-Parâmetros!$B$66<=0,"ERRO",M54/(1-(Parâmetros!$B$61+N54+Parâmetros!$B$78)-Parâmetros!$B$66)),IF((1-Parâmetros!$B$65)*(1-(Parâmetros!$B$61+N54+Parâmetros!$B$78))<=0,"ERRO",(1-Parâmetros!$B$65)*M54/((1-Parâmetros!$B$65)*(1-(Parâmetros!$B$61+N54+Parâmetros!$B$78)))))) | T54: =IF($B54="","",IF(ISNUMBER(R54),R54*Parâmetros!$B$61,"")) | U54: =IF($B54="","",IF(ISNUMBER(R54),R54*N54,"")) | V54: =IF($B54="","",IF(ISNUMBER(R54),R54*Parâmetros!$B$78,"")) | W54: =IF($B54="","",IF(ISNUMBER(R54),IF(Parâmetros!$B$64=2,R54*Parâmetros!$B$66,Parâmetros!$B$65*(R54-M54-R54*(Parâmetros!$B$61+N54+Parâmetros!$B$78))),"")) | X54: =IF($B54="","",IF(ISNUMBER(R54),R54-M54-T54-U54-V54-W54,"")) | Y54: =IF($B54="","",IF(AND(ISNUMBER(R54),R54>0),X54/R54,"")) | Z54: =IF($B54="","",IF(AND(ISNUMBER(R54),ISNUMBER(G54)),R54-G54,"")) | AA54: =IF($B54="","",IF(NOT(ISNUMBER(R54)),"Percentuais ≥ 100%",IF(N(D54)=0,"Sem tempo",IF(J54=0,"Sem materiais",""))))
A55: 100.2 | B55: Seringa preenchedor rennova lift | C55: HOF | D55: 90 | E55: 0 | F55: 450 | G55: 880 | I55: 0.2 | J55: =IF($B55="","",SUMIFS(Itens!$E$2:$E$158,Itens!$A$2:$A$158,$B55)+N(F55)) | K55: =IF($B55="","",N(D55)/60*Parâmetros!$B$57) | L55: =IF($B55="","",N(D55)/60*Parâmetros!$B$60) | M55: =IF($B55="","",J55+N(E55)+K55+L55) | N55: =IF($B55="","",IF(H55="",Parâmetros!$B$62,H55)) | O55: =IF($B55="","",IF(I55="",Parâmetros!$B$63,I55)) | P55: =IF($B55="","",IF(1-(Parâmetros!$B$61+N55+Parâmetros!$B$78)-Parâmetros!$B$66-O55<=0,"ERRO",M55/(1-(Parâmetros!$B$61+N55+Parâmetros!$B$78)-Parâmetros!$B$66-O55))) | Q55: =IF($B55="","",IF((1-Parâmetros!$B$65)*(1-(Parâmetros!$B$61+N55+Parâmetros!$B$78))-O55<=0,"ERRO",(1-Parâmetros!$B$65)*M55/((1-Parâmetros!$B$65)*(1-(Parâmetros!$B$61+N55+Parâmetros!$B$78))-O55))) | R55: =IF($B55="","",IF(Parâmetros!$B$64=2,P55,Q55)) | S55: =IF($B55="","",IF(Parâmetros!$B$64=2,IF(1-(Parâmetros!$B$61+N55+Parâmetros!$B$78)-Parâmetros!$B$66<=0,"ERRO",M55/(1-(Parâmetros!$B$61+N55+Parâmetros!$B$78)-Parâmetros!$B$66)),IF((1-Parâmetros!$B$65)*(1-(Parâmetros!$B$61+N55+Parâmetros!$B$78))<=0,"ERRO",(1-Parâmetros!$B$65)*M55/((1-Parâmetros!$B$65)*(1-(Parâmetros!$B$61+N55+Parâmetros!$B$78)))))) | T55: =IF($B55="","",IF(ISNUMBER(R55),R55*Parâmetros!$B$61,"")) | U55: =IF($B55="","",IF(ISNUMBER(R55),R55*N55,"")) | V55: =IF($B55="","",IF(ISNUMBER(R55),R55*Parâmetros!$B$78,"")) | W55: =IF($B55="","",IF(ISNUMBER(R55),IF(Parâmetros!$B$64=2,R55*Parâmetros!$B$66,Parâmetros!$B$65*(R55-M55-R55*(Parâmetros!$B$61+N55+Parâmetros!$B$78))),"")) | X55: =IF($B55="","",IF(ISNUMBER(R55),R55-M55-T55-U55-V55-W55,"")) | Y55: =IF($B55="","",IF(AND(ISNUMBER(R55),R55>0),X55/R55,"")) | Z55: =IF($B55="","",IF(AND(ISNUMBER(R55),ISNUMBER(G55)),R55-G55,"")) | AA55: =IF($B55="","",IF(NOT(ISNUMBER(R55)),"Percentuais ≥ 100%",IF(N(D55)=0,"Sem tempo",IF(J55=0,"Sem materiais",""))))
A56: 100.3 | B56: Seringa preenchedor restylane | C56: HOF | D56: 90 | E56: 0 | F56: 450 | G56: 1200 | I56: 0.2 | J56: =IF($B56="","",SUMIFS(Itens!$E$2:$E$158,Itens!$A$2:$A$158,$B56)+N(F56)) | K56: =IF($B56="","",N(D56)/60*Parâmetros!$B$57) | L56: =IF($B56="","",N(D56)/60*Parâmetros!$B$60) | M56: =IF($B56="","",J56+N(E56)+K56+L56) | N56: =IF($B56="","",IF(H56="",Parâmetros!$B$62,H56)) | O56: =IF($B56="","",IF(I56="",Parâmetros!$B$63,I56)) | P56: =IF($B56="","",IF(1-(Parâmetros!$B$61+N56+Parâmetros!$B$78)-Parâmetros!$B$66-O56<=0,"ERRO",M56/(1-(Parâmetros!$B$61+N56+Parâmetros!$B$78)-Parâmetros!$B$66-O56))) | Q56: =IF($B56="","",IF((1-Parâmetros!$B$65)*(1-(Parâmetros!$B$61+N56+Parâmetros!$B$78))-O56<=0,"ERRO",(1-Parâmetros!$B$65)*M56/((1-Parâmetros!$B$65)*(1-(Parâmetros!$B$61+N56+Parâmetros!$B$78))-O56))) | R56: =IF($B56="","",IF(Parâmetros!$B$64=2,P56,Q56)) | S56: =IF($B56="","",IF(Parâmetros!$B$64=2,IF(1-(Parâmetros!$B$61+N56+Parâmetros!$B$78)-Parâmetros!$B$66<=0,"ERRO",M56/(1-(Parâmetros!$B$61+N56+Parâmetros!$B$78)-Parâmetros!$B$66)),IF((1-Parâmetros!$B$65)*(1-(Parâmetros!$B$61+N56+Parâmetros!$B$78))<=0,"ERRO",(1-Parâmetros!$B$65)*M56/((1-Parâmetros!$B$65)*(1-(Parâmetros!$B$61+N56+Parâmetros!$B$78)))))) | T56: =IF($B56="","",IF(ISNUMBER(R56),R56*Parâmetros!$B$61,"")) | U56: =IF($B56="","",IF(ISNUMBER(R56),R56*N56,"")) | V56: =IF($B56="","",IF(ISNUMBER(R56),R56*Parâmetros!$B$78,"")) | W56: =IF($B56="","",IF(ISNUMBER(R56),IF(Parâmetros!$B$64=2,R56*Parâmetros!$B$66,Parâmetros!$B$65*(R56-M56-R56*(Parâmetros!$B$61+N56+Parâmetros!$B$78))),"")) | X56: =IF($B56="","",IF(ISNUMBER(R56),R56-M56-T56-U56-V56-W56,"")) | Y56: =IF($B56="","",IF(AND(ISNUMBER(R56),R56>0),X56/R56,"")) | Z56: =IF($B56="","",IF(AND(ISNUMBER(R56),ISNUMBER(G56)),R56-G56,"")) | AA56: =IF($B56="","",IF(NOT(ISNUMBER(R56)),"Percentuais ≥ 100%",IF(N(D56)=0,"Sem tempo",IF(J56=0,"Sem materiais",""))))
B57: Seringa preenchedor deep perfetha | C57: HOF | D57: 90 | E57: 0 | F57: 450 | G57: 1200 | I57: 0.2 | J57: =IF($B57="","",SUMIFS(Itens!$E$2:$E$158,Itens!$A$2:$A$158,$B57)+N(F57)) | K57: =IF($B57="","",N(D57)/60*Parâmetros!$B$57) | L57: =IF($B57="","",N(D57)/60*Parâmetros!$B$60) | M57: =IF($B57="","",J57+N(E57)+K57+L57) | N57: =IF($B57="","",IF(H57="",Parâmetros!$B$62,H57)) | O57: =IF($B57="","",IF(I57="",Parâmetros!$B$63,I57)) | P57: =IF($B57="","",IF(1-(Parâmetros!$B$61+N57+Parâmetros!$B$78)-Parâmetros!$B$66-O57<=0,"ERRO",M57/(1-(Parâmetros!$B$61+N57+Parâmetros!$B$78)-Parâmetros!$B$66-O57))) | Q57: =IF($B57="","",IF((1-Parâmetros!$B$65)*(1-(Parâmetros!$B$61+N57+Parâmetros!$B$78))-O57<=0,"ERRO",(1-Parâmetros!$B$65)*M57/((1-Parâmetros!$B$65)*(1-(Parâmetros!$B$61+N57+Parâmetros!$B$78))-O57))) | R57: =IF($B57="","",IF(Parâmetros!$B$64=2,P57,Q57)) | S57: =IF($B57="","",IF(Parâmetros!$B$64=2,IF(1-(Parâmetros!$B$61+N57+Parâmetros!$B$78)-Parâmetros!$B$66<=0,"ERRO",M57/(1-(Parâmetros!$B$61+N57+Parâmetros!$B$78)-Parâmetros!$B$66)),IF((1-Parâmetros!$B$65)*(1-(Parâmetros!$B$61+N57+Parâmetros!$B$78))<=0,"ERRO",(1-Parâmetros!$B$65)*M57/((1-Parâmetros!$B$65)*(1-(Parâmetros!$B$61+N57+Parâmetros!$B$78)))))) | T57: =IF($B57="","",IF(ISNUMBER(R57),R57*Parâmetros!$B$61,"")) | U57: =IF($B57="","",IF(ISNUMBER(R57),R57*N57,"")) | V57: =IF($B57="","",IF(ISNUMBER(R57),R57*Parâmetros!$B$78,"")) | W57: =IF($B57="","",IF(ISNUMBER(R57),IF(Parâmetros!$B$64=2,R57*Parâmetros!$B$66,Parâmetros!$B$65*(R57-M57-R57*(Parâmetros!$B$61+N57+Parâmetros!$B$78))),"")) | X57: =IF($B57="","",IF(ISNUMBER(R57),R57-M57-T57-U57-V57-W57,"")) | Y57: =IF($B57="","",IF(AND(ISNUMBER(R57),R57>0),X57/R57,"")) | Z57: =IF($B57="","",IF(AND(ISNUMBER(R57),ISNUMBER(G57)),R57-G57,"")) | AA57: =IF($B57="","",IF(NOT(ISNUMBER(R57)),"Percentuais ≥ 100%",IF(N(D57)=0,"Sem tempo",IF(J57=0,"Sem materiais",""))))
B58: Seringa ellanse | C58: HOF | D58: 0 | E58: 0 | F58: 0 | G58: 1200 | I58: 0.2 | J58: =IF($B58="","",SUMIFS(Itens!$E$2:$E$158,Itens!$A$2:$A$158,$B58)+N(F58)) | K58: =IF($B58="","",N(D58)/60*Parâmetros!$B$57) | L58: =IF($B58="","",N(D58)/60*Parâmetros!$B$60) | M58: =IF($B58="","",J58+N(E58)+K58+L58) | N58: =IF($B58="","",IF(H58="",Parâmetros!$B$62,H58)) | O58: =IF($B58="","",IF(I58="",Parâmetros!$B$63,I58)) | P58: =IF($B58="","",IF(1-(Parâmetros!$B$61+N58+Parâmetros!$B$78)-Parâmetros!$B$66-O58<=0,"ERRO",M58/(1-(Parâmetros!$B$61+N58+Parâmetros!$B$78)-Parâmetros!$B$66-O58))) | Q58: =IF($B58="","",IF((1-Parâmetros!$B$65)*(1-(Parâmetros!$B$61+N58+Parâmetros!$B$78))-O58<=0,"ERRO",(1-Parâmetros!$B$65)*M58/((1-Parâmetros!$B$65)*(1-(Parâmetros!$B$61+N58+Parâmetros!$B$78))-O58))) | R58: =IF($B58="","",IF(Parâmetros!$B$64=2,P58,Q58)) | S58: =IF($B58="","",IF(Parâmetros!$B$64=2,IF(1-(Parâmetros!$B$61+N58+Parâmetros!$B$78)-Parâmetros!$B$66<=0,"ERRO",M58/(1-(Parâmetros!$B$61+N58+Parâmetros!$B$78)-Parâmetros!$B$66)),IF((1-Parâmetros!$B$65)*(1-(Parâmetros!$B$61+N58+Parâmetros!$B$78))<=0,"ERRO",(1-Parâmetros!$B$65)*M58/((1-Parâmetros!$B$65)*(1-(Parâmetros!$B$61+N58+Parâmetros!$B$78)))))) | T58: =IF($B58="","",IF(ISNUMBER(R58),R58*Parâmetros!$B$61,"")) | U58: =IF($B58="","",IF(ISNUMBER(R58),R58*N58,"")) | V58: =IF($B58="","",IF(ISNUMBER(R58),R58*Parâmetros!$B$78,"")) | W58: =IF($B58="","",IF(ISNUMBER(R58),IF(Parâmetros!$B$64=2,R58*Parâmetros!$B$66,Parâmetros!$B$65*(R58-M58-R58*(Parâmetros!$B$61+N58+Parâmetros!$B$78))),"")) | X58: =IF($B58="","",IF(ISNUMBER(R58),R58-M58-T58-U58-V58-W58,"")) | Y58: =IF($B58="","",IF(AND(ISNUMBER(R58),R58>0),X58/R58,"")) | Z58: =IF($B58="","",IF(AND(ISNUMBER(R58),ISNUMBER(G58)),R58-G58,"")) | AA58: =IF($B58="","",IF(NOT(ISNUMBER(R58)),"Percentuais ≥ 100%",IF(N(D58)=0,"Sem tempo",IF(J58=0,"Sem materiais",""))))
B59: Bioestimulador hidroxiapatita de cálcio next (sessão) | C59: HOF | D59: 0 | E59: 0 | F59: 0 | I59: 0.2 | J59: =IF($B59="","",SUMIFS(Itens!$E$2:$E$158,Itens!$A$2:$A$158,$B59)+N(F59)) | K59: =IF($B59="","",N(D59)/60*Parâmetros!$B$57) | L59: =IF($B59="","",N(D59)/60*Parâmetros!$B$60) | M59: =IF($B59="","",J59+N(E59)+K59+L59) | N59: =IF($B59="","",IF(H59="",Parâmetros!$B$62,H59)) | O59: =IF($B59="","",IF(I59="",Parâmetros!$B$63,I59)) | P59: =IF($B59="","",IF(1-(Parâmetros!$B$61+N59+Parâmetros!$B$78)-Parâmetros!$B$66-O59<=0,"ERRO",M59/(1-(Parâmetros!$B$61+N59+Parâmetros!$B$78)-Parâmetros!$B$66-O59))) | Q59: =IF($B59="","",IF((1-Parâmetros!$B$65)*(1-(Parâmetros!$B$61+N59+Parâmetros!$B$78))-O59<=0,"ERRO",(1-Parâmetros!$B$65)*M59/((1-Parâmetros!$B$65)*(1-(Parâmetros!$B$61+N59+Parâmetros!$B$78))-O59))) | R59: =IF($B59="","",IF(Parâmetros!$B$64=2,P59,Q59)) | S59: =IF($B59="","",IF(Parâmetros!$B$64=2,IF(1-(Parâmetros!$B$61+N59+Parâmetros!$B$78)-Parâmetros!$B$66<=0,"ERRO",M59/(1-(Parâmetros!$B$61+N59+Parâmetros!$B$78)-Parâmetros!$B$66)),IF((1-Parâmetros!$B$65)*(1-(Parâmetros!$B$61+N59+Parâmetros!$B$78))<=0,"ERRO",(1-Parâmetros!$B$65)*M59/((1-Parâmetros!$B$65)*(1-(Parâmetros!$B$61+N59+Parâmetros!$B$78)))))) | T59: =IF($B59="","",IF(ISNUMBER(R59),R59*Parâmetros!$B$61,"")) | U59: =IF($B59="","",IF(ISNUMBER(R59),R59*N59,"")) | V59: =IF($B59="","",IF(ISNUMBER(R59),R59*Parâmetros!$B$78,"")) | W59: =IF($B59="","",IF(ISNUMBER(R59),IF(Parâmetros!$B$64=2,R59*Parâmetros!$B$66,Parâmetros!$B$65*(R59-M59-R59*(Parâmetros!$B$61+N59+Parâmetros!$B$78))),"")) | X59: =IF($B59="","",IF(ISNUMBER(R59),R59-M59-T59-U59-V59-W59,"")) | Y59: =IF($B59="","",IF(AND(ISNUMBER(R59),R59>0),X59/R59,"")) | Z59: =IF($B59="","",IF(AND(ISNUMBER(R59),ISNUMBER(G59)),R59-G59,"")) | AA59: =IF($B59="","",IF(NOT(ISNUMBER(R59)),"Percentuais ≥ 100%",IF(N(D59)=0,"Sem tempo",IF(J59=0,"Sem materiais",""))))
B60: Bioestimulador hidroxiapatita de cálcio +ac pollatico next | C60: HOF | D60: 0 | E60: 0 | F60: 0 | G60: 800 | I60: 0.2 | J60: =IF($B60="","",SUMIFS(Itens!$E$2:$E$158,Itens!$A$2:$A$158,$B60)+N(F60)) | K60: =IF($B60="","",N(D60)/60*Parâmetros!$B$57) | L60: =IF($B60="","",N(D60)/60*Parâmetros!$B$60) | M60: =IF($B60="","",J60+N(E60)+K60+L60) | N60: =IF($B60="","",IF(H60="",Parâmetros!$B$62,H60)) | O60: =IF($B60="","",IF(I60="",Parâmetros!$B$63,I60)) | P60: =IF($B60="","",IF(1-(Parâmetros!$B$61+N60+Parâmetros!$B$78)-Parâmetros!$B$66-O60<=0,"ERRO",M60/(1-(Parâmetros!$B$61+N60+Parâmetros!$B$78)-Parâmetros!$B$66-O60))) | Q60: =IF($B60="","",IF((1-Parâmetros!$B$65)*(1-(Parâmetros!$B$61+N60+Parâmetros!$B$78))-O60<=0,"ERRO",(1-Parâmetros!$B$65)*M60/((1-Parâmetros!$B$65)*(1-(Parâmetros!$B$61+N60+Parâmetros!$B$78))-O60))) | R60: =IF($B60="","",IF(Parâmetros!$B$64=2,P60,Q60)) | S60: =IF($B60="","",IF(Parâmetros!$B$64=2,IF(1-(Parâmetros!$B$61+N60+Parâmetros!$B$78)-Parâmetros!$B$66<=0,"ERRO",M60/(1-(Parâmetros!$B$61+N60+Parâmetros!$B$78)-Parâmetros!$B$66)),IF((1-Parâmetros!$B$65)*(1-(Parâmetros!$B$61+N60+Parâmetros!$B$78))<=0,"ERRO",(1-Parâmetros!$B$65)*M60/((1-Parâmetros!$B$65)*(1-(Parâmetros!$B$61+N60+Parâmetros!$B$78)))))) | T60: =IF($B60="","",IF(ISNUMBER(R60),R60*Parâmetros!$B$61,"")) | U60: =IF($B60="","",IF(ISNUMBER(R60),R60*N60,"")) | V60: =IF($B60="","",IF(ISNUMBER(R60),R60*Parâmetros!$B$78,"")) | W60: =IF($B60="","",IF(ISNUMBER(R60),IF(Parâmetros!$B$64=2,R60*Parâmetros!$B$66,Parâmetros!$B$65*(R60-M60-R60*(Parâmetros!$B$61+N60+Parâmetros!$B$78))),"")) | X60: =IF($B60="","",IF(ISNUMBER(R60),R60-M60-T60-U60-V60-W60,"")) | Y60: =IF($B60="","",IF(AND(ISNUMBER(R60),R60>0),X60/R60,"")) | Z60: =IF($B60="","",IF(AND(ISNUMBER(R60),ISNUMBER(G60)),R60-G60,"")) | AA60: =IF($B60="","",IF(NOT(ISNUMBER(R60)),"Percentuais ≥ 100%",IF(N(D60)=0,"Sem tempo",IF(J60=0,"Sem materiais",""))))
B61: Microagulhamento com mescla para melasma | C61: HOF | D61: 0 | E61: 0 | F61: 0 | G61: 150 | I61: 0.2 | J61: =IF($B61="","",SUMIFS(Itens!$E$2:$E$158,Itens!$A$2:$A$158,$B61)+N(F61)) | K61: =IF($B61="","",N(D61)/60*Parâmetros!$B$57) | L61: =IF($B61="","",N(D61)/60*Parâmetros!$B$60) | M61: =IF($B61="","",J61+N(E61)+K61+L61) | N61: =IF($B61="","",IF(H61="",Parâmetros!$B$62,H61)) | O61: =IF($B61="","",IF(I61="",Parâmetros!$B$63,I61)) | P61: =IF($B61="","",IF(1-(Parâmetros!$B$61+N61+Parâmetros!$B$78)-Parâmetros!$B$66-O61<=0,"ERRO",M61/(1-(Parâmetros!$B$61+N61+Parâmetros!$B$78)-Parâmetros!$B$66-O61))) | Q61: =IF($B61="","",IF((1-Parâmetros!$B$65)*(1-(Parâmetros!$B$61+N61+Parâmetros!$B$78))-O61<=0,"ERRO",(1-Parâmetros!$B$65)*M61/((1-Parâmetros!$B$65)*(1-(Parâmetros!$B$61+N61+Parâmetros!$B$78))-O61))) | R61: =IF($B61="","",IF(Parâmetros!$B$64=2,P61,Q61)) | S61: =IF($B61="","",IF(Parâmetros!$B$64=2,IF(1-(Parâmetros!$B$61+N61+Parâmetros!$B$78)-Parâmetros!$B$66<=0,"ERRO",M61/(1-(Parâmetros!$B$61+N61+Parâmetros!$B$78)-Parâmetros!$B$66)),IF((1-Parâmetros!$B$65)*(1-(Parâmetros!$B$61+N61+Parâmetros!$B$78))<=0,"ERRO",(1-Parâmetros!$B$65)*M61/((1-Parâmetros!$B$65)*(1-(Parâmetros!$B$61+N61+Parâmetros!$B$78)))))) | T61: =IF($B61="","",IF(ISNUMBER(R61),R61*Parâmetros!$B$61,"")) | U61: =IF($B61="","",IF(ISNUMBER(R61),R61*N61,"")) | V61: =IF($B61="","",IF(ISNUMBER(R61),R61*Parâmetros!$B$78,"")) | W61: =IF($B61="","",IF(ISNUMBER(R61),IF(Parâmetros!$B$64=2,R61*Parâmetros!$B$66,Parâmetros!$B$65*(R61-M61-R61*(Parâmetros!$B$61+N61+Parâmetros!$B$78))),"")) | X61: =IF($B61="","",IF(ISNUMBER(R61),R61-M61-T61-U61-V61-W61,"")) | Y61: =IF($B61="","",IF(AND(ISNUMBER(R61),R61>0),X61/R61,"")) | Z61: =IF($B61="","",IF(AND(ISNUMBER(R61),ISNUMBER(G61)),R61-G61,"")) | AA61: =IF($B61="","",IF(NOT(ISNUMBER(R61)),"Percentuais ≥ 100%",IF(N(D61)=0,"Sem tempo",IF(J61=0,"Sem materiais",""))))
B62: Hidralips | C62: HOF | D62: 0 | E62: 0 | F62: 0 | G62: 150 | I62: 0.2 | J62: =IF($B62="","",SUMIFS(Itens!$E$2:$E$158,Itens!$A$2:$A$158,$B62)+N(F62)) | K62: =IF($B62="","",N(D62)/60*Parâmetros!$B$57) | L62: =IF($B62="","",N(D62)/60*Parâmetros!$B$60) | M62: =IF($B62="","",J62+N(E62)+K62+L62) | N62: =IF($B62="","",IF(H62="",Parâmetros!$B$62,H62)) | O62: =IF($B62="","",IF(I62="",Parâmetros!$B$63,I62)) | P62: =IF($B62="","",IF(1-(Parâmetros!$B$61+N62+Parâmetros!$B$78)-Parâmetros!$B$66-O62<=0,"ERRO",M62/(1-(Parâmetros!$B$61+N62+Parâmetros!$B$78)-Parâmetros!$B$66-O62))) | Q62: =IF($B62="","",IF((1-Parâmetros!$B$65)*(1-(Parâmetros!$B$61+N62+Parâmetros!$B$78))-O62<=0,"ERRO",(1-Parâmetros!$B$65)*M62/((1-Parâmetros!$B$65)*(1-(Parâmetros!$B$61+N62+Parâmetros!$B$78))-O62))) | R62: =IF($B62="","",IF(Parâmetros!$B$64=2,P62,Q62)) | S62: =IF($B62="","",IF(Parâmetros!$B$64=2,IF(1-(Parâmetros!$B$61+N62+Parâmetros!$B$78)-Parâmetros!$B$66<=0,"ERRO",M62/(1-(Parâmetros!$B$61+N62+Parâmetros!$B$78)-Parâmetros!$B$66)),IF((1-Parâmetros!$B$65)*(1-(Parâmetros!$B$61+N62+Parâmetros!$B$78))<=0,"ERRO",(1-Parâmetros!$B$65)*M62/((1-Parâmetros!$B$65)*(1-(Parâmetros!$B$61+N62+Parâmetros!$B$78)))))) | T62: =IF($B62="","",IF(ISNUMBER(R62),R62*Parâmetros!$B$61,"")) | U62: =IF($B62="","",IF(ISNUMBER(R62),R62*N62,"")) | V62: =IF($B62="","",IF(ISNUMBER(R62),R62*Parâmetros!$B$78,"")) | W62: =IF($B62="","",IF(ISNUMBER(R62),IF(Parâmetros!$B$64=2,R62*Parâmetros!$B$66,Parâmetros!$B$65*(R62-M62-R62*(Parâmetros!$B$61+N62+Parâmetros!$B$78))),"")) | X62: =IF($B62="","",IF(ISNUMBER(R62),R62-M62-T62-U62-V62-W62,"")) | Y62: =IF($B62="","",IF(AND(ISNUMBER(R62),R62>0),X62/R62,"")) | Z62: =IF($B62="","",IF(AND(ISNUMBER(R62),ISNUMBER(G62)),R62-G62,"")) | AA62: =IF($B62="","",IF(NOT(ISNUMBER(R62)),"Percentuais ≥ 100%",IF(N(D62)=0,"Sem tempo",IF(J62=0,"Sem materiais",""))))
B63: Peeling ácido retinoico | C63: HOF | D63: 0 | E63: 0 | F63: 0 | I63: 0.2 | J63: =IF($B63="","",SUMIFS(Itens!$E$2:$E$158,Itens!$A$2:$A$158,$B63)+N(F63)) | K63: =IF($B63="","",N(D63)/60*Parâmetros!$B$57) | L63: =IF($B63="","",N(D63)/60*Parâmetros!$B$60) | M63: =IF($B63="","",J63+N(E63)+K63+L63) | N63: =IF($B63="","",IF(H63="",Parâmetros!$B$62,H63)) | O63: =IF($B63="","",IF(I63="",Parâmetros!$B$63,I63)) | P63: =IF($B63="","",IF(1-(Parâmetros!$B$61+N63+Parâmetros!$B$78)-Parâmetros!$B$66-O63<=0,"ERRO",M63/(1-(Parâmetros!$B$61+N63+Parâmetros!$B$78)-Parâmetros!$B$66-O63))) | Q63: =IF($B63="","",IF((1-Parâmetros!$B$65)*(1-(Parâmetros!$B$61+N63+Parâmetros!$B$78))-O63<=0,"ERRO",(1-Parâmetros!$B$65)*M63/((1-Parâmetros!$B$65)*(1-(Parâmetros!$B$61+N63+Parâmetros!$B$78))-O63))) | R63: =IF($B63="","",IF(Parâmetros!$B$64=2,P63,Q63)) | S63: =IF($B63="","",IF(Parâmetros!$B$64=2,IF(1-(Parâmetros!$B$61+N63+Parâmetros!$B$78)-Parâmetros!$B$66<=0,"ERRO",M63/(1-(Parâmetros!$B$61+N63+Parâmetros!$B$78)-Parâmetros!$B$66)),IF((1-Parâmetros!$B$65)*(1-(Parâmetros!$B$61+N63+Parâmetros!$B$78))<=0,"ERRO",(1-Parâmetros!$B$65)*M63/((1-Parâmetros!$B$65)*(1-(Parâmetros!$B$61+N63+Parâmetros!$B$78)))))) | T63: =IF($B63="","",IF(ISNUMBER(R63),R63*Parâmetros!$B$61,"")) | U63: =IF($B63="","",IF(ISNUMBER(R63),R63*N63,"")) | V63: =IF($B63="","",IF(ISNUMBER(R63),R63*Parâmetros!$B$78,"")) | W63: =IF($B63="","",IF(ISNUMBER(R63),IF(Parâmetros!$B$64=2,R63*Parâmetros!$B$66,Parâmetros!$B$65*(R63-M63-R63*(Parâmetros!$B$61+N63+Parâmetros!$B$78))),"")) | X63: =IF($B63="","",IF(ISNUMBER(R63),R63-M63-T63-U63-V63-W63,"")) | Y63: =IF($B63="","",IF(AND(ISNUMBER(R63),R63>0),X63/R63,"")) | Z63: =IF($B63="","",IF(AND(ISNUMBER(R63),ISNUMBER(G63)),R63-G63,"")) | AA63: =IF($B63="","",IF(NOT(ISNUMBER(R63)),"Percentuais ≥ 100%",IF(N(D63)=0,"Sem tempo",IF(J63=0,"Sem materiais",""))))
B64: Lipo de papada cirúrgica | C64: HOF | D64: 0 | E64: 0 | F64: 0 | G64: 5500 | I64: 0.2 | J64: =IF($B64="","",SUMIFS(Itens!$E$2:$E$158,Itens!$A$2:$A$158,$B64)+N(F64)) | K64: =IF($B64="","",N(D64)/60*Parâmetros!$B$57) | L64: =IF($B64="","",N(D64)/60*Parâmetros!$B$60) | M64: =IF($B64="","",J64+N(E64)+K64+L64) | N64: =IF($B64="","",IF(H64="",Parâmetros!$B$62,H64)) | O64: =IF($B64="","",IF(I64="",Parâmetros!$B$63,I64)) | P64: =IF($B64="","",IF(1-(Parâmetros!$B$61+N64+Parâmetros!$B$78)-Parâmetros!$B$66-O64<=0,"ERRO",M64/(1-(Parâmetros!$B$61+N64+Parâmetros!$B$78)-Parâmetros!$B$66-O64))) | Q64: =IF($B64="","",IF((1-Parâmetros!$B$65)*(1-(Parâmetros!$B$61+N64+Parâmetros!$B$78))-O64<=0,"ERRO",(1-Parâmetros!$B$65)*M64/((1-Parâmetros!$B$65)*(1-(Parâmetros!$B$61+N64+Parâmetros!$B$78))-O64))) | R64: =IF($B64="","",IF(Parâmetros!$B$64=2,P64,Q64)) | S64: =IF($B64="","",IF(Parâmetros!$B$64=2,IF(1-(Parâmetros!$B$61+N64+Parâmetros!$B$78)-Parâmetros!$B$66<=0,"ERRO",M64/(1-(Parâmetros!$B$61+N64+Parâmetros!$B$78)-Parâmetros!$B$66)),IF((1-Parâmetros!$B$65)*(1-(Parâmetros!$B$61+N64+Parâmetros!$B$78))<=0,"ERRO",(1-Parâmetros!$B$65)*M64/((1-Parâmetros!$B$65)*(1-(Parâmetros!$B$61+N64+Parâmetros!$B$78)))))) | T64: =IF($B64="","",IF(ISNUMBER(R64),R64*Parâmetros!$B$61,"")) | U64: =IF($B64="","",IF(ISNUMBER(R64),R64*N64,"")) | V64: =IF($B64="","",IF(ISNUMBER(R64),R64*Parâmetros!$B$78,"")) | W64: =IF($B64="","",IF(ISNUMBER(R64),IF(Parâmetros!$B$64=2,R64*Parâmetros!$B$66,Parâmetros!$B$65*(R64-M64-R64*(Parâmetros!$B$61+N64+Parâmetros!$B$78))),"")) | X64: =IF($B64="","",IF(ISNUMBER(R64),R64-M64-T64-U64-V64-W64,"")) | Y64: =IF($B64="","",IF(AND(ISNUMBER(R64),R64>0),X64/R64,"")) | Z64: =IF($B64="","",IF(AND(ISNUMBER(R64),ISNUMBER(G64)),R64-G64,"")) | AA64: =IF($B64="","",IF(NOT(ISNUMBER(R64)),"Percentuais ≥ 100%",IF(N(D64)=0,"Sem tempo",IF(J64=0,"Sem materiais",""))))
B65: Botox testa | C65: HOF | D65: 0 | E65: 0 | F65: 0 | G65: 110 | I65: 0.2 | J65: =IF($B65="","",SUMIFS(Itens!$E$2:$E$158,Itens!$A$2:$A$158,$B65)+N(F65)) | K65: =IF($B65="","",N(D65)/60*Parâmetros!$B$57) | L65: =IF($B65="","",N(D65)/60*Parâmetros!$B$60) | M65: =IF($B65="","",J65+N(E65)+K65+L65) | N65: =IF($B65="","",IF(H65="",Parâmetros!$B$62,H65)) | O65: =IF($B65="","",IF(I65="",Parâmetros!$B$63,I65)) | P65: =IF($B65="","",IF(1-(Parâmetros!$B$61+N65+Parâmetros!$B$78)-Parâmetros!$B$66-O65<=0,"ERRO",M65/(1-(Parâmetros!$B$61+N65+Parâmetros!$B$78)-Parâmetros!$B$66-O65))) | Q65: =IF($B65="","",IF((1-Parâmetros!$B$65)*(1-(Parâmetros!$B$61+N65+Parâmetros!$B$78))-O65<=0,"ERRO",(1-Parâmetros!$B$65)*M65/((1-Parâmetros!$B$65)*(1-(Parâmetros!$B$61+N65+Parâmetros!$B$78))-O65))) | R65: =IF($B65="","",IF(Parâmetros!$B$64=2,P65,Q65)) | S65: =IF($B65="","",IF(Parâmetros!$B$64=2,IF(1-(Parâmetros!$B$61+N65+Parâmetros!$B$78)-Parâmetros!$B$66<=0,"ERRO",M65/(1-(Parâmetros!$B$61+N65+Parâmetros!$B$78)-Parâmetros!$B$66)),IF((1-Parâmetros!$B$65)*(1-(Parâmetros!$B$61+N65+Parâmetros!$B$78))<=0,"ERRO",(1-Parâmetros!$B$65)*M65/((1-Parâmetros!$B$65)*(1-(Parâmetros!$B$61+N65+Parâmetros!$B$78)))))) | T65: =IF($B65="","",IF(ISNUMBER(R65),R65*Parâmetros!$B$61,"")) | U65: =IF($B65="","",IF(ISNUMBER(R65),R65*N65,"")) | V65: =IF($B65="","",IF(ISNUMBER(R65),R65*Parâmetros!$B$78,"")) | W65: =IF($B65="","",IF(ISNUMBER(R65),IF(Parâmetros!$B$64=2,R65*Parâmetros!$B$66,Parâmetros!$B$65*(R65-M65-R65*(Parâmetros!$B$61+N65+Parâmetros!$B$78))),"")) | X65: =IF($B65="","",IF(ISNUMBER(R65),R65-M65-T65-U65-V65-W65,"")) | Y65: =IF($B65="","",IF(AND(ISNUMBER(R65),R65>0),X65/R65,"")) | Z65: =IF($B65="","",IF(AND(ISNUMBER(R65),ISNUMBER(G65)),R65-G65,"")) | AA65: =IF($B65="","",IF(NOT(ISNUMBER(R65)),"Percentuais ≥ 100%",IF(N(D65)=0,"Sem tempo",IF(J65=0,"Sem materiais",""))))
B66: Botox olhos | C66: HOF | D66: 0 | E66: 0 | F66: 0 | G66: 420 | I66: 0.2 | J66: =IF($B66="","",SUMIFS(Itens!$E$2:$E$158,Itens!$A$2:$A$158,$B66)+N(F66)) | K66: =IF($B66="","",N(D66)/60*Parâmetros!$B$57) | L66: =IF($B66="","",N(D66)/60*Parâmetros!$B$60) | M66: =IF($B66="","",J66+N(E66)+K66+L66) | N66: =IF($B66="","",IF(H66="",Parâmetros!$B$62,H66)) | O66: =IF($B66="","",IF(I66="",Parâmetros!$B$63,I66)) | P66: =IF($B66="","",IF(1-(Parâmetros!$B$61+N66+Parâmetros!$B$78)-Parâmetros!$B$66-O66<=0,"ERRO",M66/(1-(Parâmetros!$B$61+N66+Parâmetros!$B$78)-Parâmetros!$B$66-O66))) | Q66: =IF($B66="","",IF((1-Parâmetros!$B$65)*(1-(Parâmetros!$B$61+N66+Parâmetros!$B$78))-O66<=0,"ERRO",(1-Parâmetros!$B$65)*M66/((1-Parâmetros!$B$65)*(1-(Parâmetros!$B$61+N66+Parâmetros!$B$78))-O66))) | R66: =IF($B66="","",IF(Parâmetros!$B$64=2,P66,Q66)) | S66: =IF($B66="","",IF(Parâmetros!$B$64=2,IF(1-(Parâmetros!$B$61+N66+Parâmetros!$B$78)-Parâmetros!$B$66<=0,"ERRO",M66/(1-(Parâmetros!$B$61+N66+Parâmetros!$B$78)-Parâmetros!$B$66)),IF((1-Parâmetros!$B$65)*(1-(Parâmetros!$B$61+N66+Parâmetros!$B$78))<=0,"ERRO",(1-Parâmetros!$B$65)*M66/((1-Parâmetros!$B$65)*(1-(Parâmetros!$B$61+N66+Parâmetros!$B$78)))))) | T66: =IF($B66="","",IF(ISNUMBER(R66),R66*Parâmetros!$B$61,"")) | U66: =IF($B66="","",IF(ISNUMBER(R66),R66*N66,"")) | V66: =IF($B66="","",IF(ISNUMBER(R66),R66*Parâmetros!$B$78,"")) | W66: =IF($B66="","",IF(ISNUMBER(R66),IF(Parâmetros!$B$64=2,R66*Parâmetros!$B$66,Parâmetros!$B$65*(R66-M66-R66*(Parâmetros!$B$61+N66+Parâmetros!$B$78))),"")) | X66: =IF($B66="","",IF(ISNUMBER(R66),R66-M66-T66-U66-V66-W66,"")) | Y66: =IF($B66="","",IF(AND(ISNUMBER(R66),R66>0),X66/R66,"")) | Z66: =IF($B66="","",IF(AND(ISNUMBER(R66),ISNUMBER(G66)),R66-G66,"")) | AA66: =IF($B66="","",IF(NOT(ISNUMBER(R66)),"Percentuais ≥ 100%",IF(N(D66)=0,"Sem tempo",IF(J66=0,"Sem materiais",""))))
B67: Botox glabela | C67: HOF | D67: 0 | E67: 0 | F67: 0 | G67: 770 | I67: 0.2 | J67: =IF($B67="","",SUMIFS(Itens!$E$2:$E$158,Itens!$A$2:$A$158,$B67)+N(F67)) | K67: =IF($B67="","",N(D67)/60*Parâmetros!$B$57) | L67: =IF($B67="","",N(D67)/60*Parâmetros!$B$60) | M67: =IF($B67="","",J67+N(E67)+K67+L67) | N67: =IF($B67="","",IF(H67="",Parâmetros!$B$62,H67)) | O67: =IF($B67="","",IF(I67="",Parâmetros!$B$63,I67)) | P67: =IF($B67="","",IF(1-(Parâmetros!$B$61+N67+Parâmetros!$B$78)-Parâmetros!$B$66-O67<=0,"ERRO",M67/(1-(Parâmetros!$B$61+N67+Parâmetros!$B$78)-Parâmetros!$B$66-O67))) | Q67: =IF($B67="","",IF((1-Parâmetros!$B$65)*(1-(Parâmetros!$B$61+N67+Parâmetros!$B$78))-O67<=0,"ERRO",(1-Parâmetros!$B$65)*M67/((1-Parâmetros!$B$65)*(1-(Parâmetros!$B$61+N67+Parâmetros!$B$78))-O67))) | R67: =IF($B67="","",IF(Parâmetros!$B$64=2,P67,Q67)) | S67: =IF($B67="","",IF(Parâmetros!$B$64=2,IF(1-(Parâmetros!$B$61+N67+Parâmetros!$B$78)-Parâmetros!$B$66<=0,"ERRO",M67/(1-(Parâmetros!$B$61+N67+Parâmetros!$B$78)-Parâmetros!$B$66)),IF((1-Parâmetros!$B$65)*(1-(Parâmetros!$B$61+N67+Parâmetros!$B$78))<=0,"ERRO",(1-Parâmetros!$B$65)*M67/((1-Parâmetros!$B$65)*(1-(Parâmetros!$B$61+N67+Parâmetros!$B$78)))))) | T67: =IF($B67="","",IF(ISNUMBER(R67),R67*Parâmetros!$B$61,"")) | U67: =IF($B67="","",IF(ISNUMBER(R67),R67*N67,"")) | V67: =IF($B67="","",IF(ISNUMBER(R67),R67*Parâmetros!$B$78,"")) | W67: =IF($B67="","",IF(ISNUMBER(R67),IF(Parâmetros!$B$64=2,R67*Parâmetros!$B$66,Parâmetros!$B$65*(R67-M67-R67*(Parâmetros!$B$61+N67+Parâmetros!$B$78))),"")) | X67: =IF($B67="","",IF(ISNUMBER(R67),R67-M67-T67-U67-V67-W67,"")) | Y67: =IF($B67="","",IF(AND(ISNUMBER(R67),R67>0),X67/R67,"")) | Z67: =IF($B67="","",IF(AND(ISNUMBER(R67),ISNUMBER(G67)),R67-G67,"")) | AA67: =IF($B67="","",IF(NOT(ISNUMBER(R67)),"Percentuais ≥ 100%",IF(N(D67)=0,"Sem tempo",IF(J67=0,"Sem materiais",""))))
B68: Botox terço superior | C68: HOF | D68: 0 | E68: 0 | F68: 0 | G68: 2000 | I68: 0.2 | J68: =IF($B68="","",SUMIFS(Itens!$E$2:$E$158,Itens!$A$2:$A$158,$B68)+N(F68)) | K68: =IF($B68="","",N(D68)/60*Parâmetros!$B$57) | L68: =IF($B68="","",N(D68)/60*Parâmetros!$B$60) | M68: =IF($B68="","",J68+N(E68)+K68+L68) | N68: =IF($B68="","",IF(H68="",Parâmetros!$B$62,H68)) | O68: =IF($B68="","",IF(I68="",Parâmetros!$B$63,I68)) | P68: =IF($B68="","",IF(1-(Parâmetros!$B$61+N68+Parâmetros!$B$78)-Parâmetros!$B$66-O68<=0,"ERRO",M68/(1-(Parâmetros!$B$61+N68+Parâmetros!$B$78)-Parâmetros!$B$66-O68))) | Q68: =IF($B68="","",IF((1-Parâmetros!$B$65)*(1-(Parâmetros!$B$61+N68+Parâmetros!$B$78))-O68<=0,"ERRO",(1-Parâmetros!$B$65)*M68/((1-Parâmetros!$B$65)*(1-(Parâmetros!$B$61+N68+Parâmetros!$B$78))-O68))) | R68: =IF($B68="","",IF(Parâmetros!$B$64=2,P68,Q68)) | S68: =IF($B68="","",IF(Parâmetros!$B$64=2,IF(1-(Parâmetros!$B$61+N68+Parâmetros!$B$78)-Parâmetros!$B$66<=0,"ERRO",M68/(1-(Parâmetros!$B$61+N68+Parâmetros!$B$78)-Parâmetros!$B$66)),IF((1-Parâmetros!$B$65)*(1-(Parâmetros!$B$61+N68+Parâmetros!$B$78))<=0,"ERRO",(1-Parâmetros!$B$65)*M68/((1-Parâmetros!$B$65)*(1-(Parâmetros!$B$61+N68+Parâmetros!$B$78)))))) | T68: =IF($B68="","",IF(ISNUMBER(R68),R68*Parâmetros!$B$61,"")) | U68: =IF($B68="","",IF(ISNUMBER(R68),R68*N68,"")) | V68: =IF($B68="","",IF(ISNUMBER(R68),R68*Parâmetros!$B$78,"")) | W68: =IF($B68="","",IF(ISNUMBER(R68),IF(Parâmetros!$B$64=2,R68*Parâmetros!$B$66,Parâmetros!$B$65*(R68-M68-R68*(Parâmetros!$B$61+N68+Parâmetros!$B$78))),"")) | X68: =IF($B68="","",IF(ISNUMBER(R68),R68-M68-T68-U68-V68-W68,"")) | Y68: =IF($B68="","",IF(AND(ISNUMBER(R68),R68>0),X68/R68,"")) | Z68: =IF($B68="","",IF(AND(ISNUMBER(R68),ISNUMBER(G68)),R68-G68,"")) | AA68: =IF($B68="","",IF(NOT(ISNUMBER(R68)),"Percentuais ≥ 100%",IF(N(D68)=0,"Sem tempo",IF(J68=0,"Sem materiais",""))))
J69: =IF($B69="","",SUMIFS(Itens!$E$2:$E$158,Itens!$A$2:$A$158,$B69)+N(F69)) | K69: =IF($B69="","",N(D69)/60*Parâmetros!$B$57) | L69: =IF($B69="","",N(D69)/60*Parâmetros!$B$60) | M69: =IF($B69="","",J69+N(E69)+K69+L69) | N69: =IF($B69="","",IF(H69="",Parâmetros!$B$62,H69)) | O69: =IF($B69="","",IF(I69="",Parâmetros!$B$63,I69)) | P69: =IF($B69="","",IF(1-(Parâmetros!$B$61+N69+Parâmetros!$B$78)-Parâmetros!$B$66-O69<=0,"ERRO",M69/(1-(Parâmetros!$B$61+N69+Parâmetros!$B$78)-Parâmetros!$B$66-O69))) | Q69: =IF($B69="","",IF((1-Parâmetros!$B$65)*(1-(Parâmetros!$B$61+N69+Parâmetros!$B$78))-O69<=0,"ERRO",(1-Parâmetros!$B$65)*M69/((1-Parâmetros!$B$65)*(1-(Parâmetros!$B$61+N69+Parâmetros!$B$78))-O69))) | R69: =IF($B69="","",IF(Parâmetros!$B$64=2,P69,Q69)) | S69: =IF($B69="","",IF(Parâmetros!$B$64=2,IF(1-(Parâmetros!$B$61+N69+Parâmetros!$B$78)-Parâmetros!$B$66<=0,"ERRO",M69/(1-(Parâmetros!$B$61+N69+Parâmetros!$B$78)-Parâmetros!$B$66)),IF((1-Parâmetros!$B$65)*(1-(Parâmetros!$B$61+N69+Parâmetros!$B$78))<=0,"ERRO",(1-Parâmetros!$B$65)*M69/((1-Parâmetros!$B$65)*(1-(Parâmetros!$B$61+N69+Parâmetros!$B$78)))))) | T69: =IF($B69="","",IF(ISNUMBER(R69),R69*Parâmetros!$B$61,"")) | U69: =IF($B69="","",IF(ISNUMBER(R69),R69*N69,"")) | V69: =IF($B69="","",IF(ISNUMBER(R69),R69*Parâmetros!$B$78,"")) | W69: =IF($B69="","",IF(ISNUMBER(R69),IF(Parâmetros!$B$64=2,R69*Parâmetros!$B$66,Parâmetros!$B$65*(R69-M69-R69*(Parâmetros!$B$61+N69+Parâmetros!$B$78))),"")) | X69: =IF($B69="","",IF(ISNUMBER(R69),R69-M69-T69-U69-V69-W69,"")) | Y69: =IF($B69="","",IF(AND(ISNUMBER(R69),R69>0),X69/R69,"")) | Z69: =IF($B69="","",IF(AND(ISNUMBER(R69),ISNUMBER(G69)),R69-G69,"")) | AA69: =IF($B69="","",IF(NOT(ISNUMBER(R69)),"Percentuais ≥ 100%",IF(N(D69)=0,"Sem tempo",IF(J69=0,"Sem materiais",""))))
J70: =IF($B70="","",SUMIFS(Itens!$E$2:$E$158,Itens!$A$2:$A$158,$B70)+N(F70)) | K70: =IF($B70="","",N(D70)/60*Parâmetros!$B$57) | L70: =IF($B70="","",N(D70)/60*Parâmetros!$B$60) | M70: =IF($B70="","",J70+N(E70)+K70+L70) | N70: =IF($B70="","",IF(H70="",Parâmetros!$B$62,H70)) | O70: =IF($B70="","",IF(I70="",Parâmetros!$B$63,I70)) | P70: =IF($B70="","",IF(1-(Parâmetros!$B$61+N70+Parâmetros!$B$78)-Parâmetros!$B$66-O70<=0,"ERRO",M70/(1-(Parâmetros!$B$61+N70+Parâmetros!$B$78)-Parâmetros!$B$66-O70))) | Q70: =IF($B70="","",IF((1-Parâmetros!$B$65)*(1-(Parâmetros!$B$61+N70+Parâmetros!$B$78))-O70<=0,"ERRO",(1-Parâmetros!$B$65)*M70/((1-Parâmetros!$B$65)*(1-(Parâmetros!$B$61+N70+Parâmetros!$B$78))-O70))) | R70: =IF($B70="","",IF(Parâmetros!$B$64=2,P70,Q70)) | S70: =IF($B70="","",IF(Parâmetros!$B$64=2,IF(1-(Parâmetros!$B$61+N70+Parâmetros!$B$78)-Parâmetros!$B$66<=0,"ERRO",M70/(1-(Parâmetros!$B$61+N70+Parâmetros!$B$78)-Parâmetros!$B$66)),IF((1-Parâmetros!$B$65)*(1-(Parâmetros!$B$61+N70+Parâmetros!$B$78))<=0,"ERRO",(1-Parâmetros!$B$65)*M70/((1-Parâmetros!$B$65)*(1-(Parâmetros!$B$61+N70+Parâmetros!$B$78)))))) | T70: =IF($B70="","",IF(ISNUMBER(R70),R70*Parâmetros!$B$61,"")) | U70: =IF($B70="","",IF(ISNUMBER(R70),R70*N70,"")) | V70: =IF($B70="","",IF(ISNUMBER(R70),R70*Parâmetros!$B$78,"")) | W70: =IF($B70="","",IF(ISNUMBER(R70),IF(Parâmetros!$B$64=2,R70*Parâmetros!$B$66,Parâmetros!$B$65*(R70-M70-R70*(Parâmetros!$B$61+N70+Parâmetros!$B$78))),"")) | X70: =IF($B70="","",IF(ISNUMBER(R70),R70-M70-T70-U70-V70-W70,"")) | Y70: =IF($B70="","",IF(AND(ISNUMBER(R70),R70>0),X70/R70,"")) | Z70: =IF($B70="","",IF(AND(ISNUMBER(R70),ISNUMBER(G70)),R70-G70,"")) | AA70: =IF($B70="","",IF(NOT(ISNUMBER(R70)),"Percentuais ≥ 100%",IF(N(D70)=0,"Sem tempo",IF(J70=0,"Sem materiais",""))))
J71: =IF($B71="","",SUMIFS(Itens!$E$2:$E$158,Itens!$A$2:$A$158,$B71)+N(F71)) | K71: =IF($B71="","",N(D71)/60*Parâmetros!$B$57) | L71: =IF($B71="","",N(D71)/60*Parâmetros!$B$60) | M71: =IF($B71="","",J71+N(E71)+K71+L71) | N71: =IF($B71="","",IF(H71="",Parâmetros!$B$62,H71)) | O71: =IF($B71="","",IF(I71="",Parâmetros!$B$63,I71)) | P71: =IF($B71="","",IF(1-(Parâmetros!$B$61+N71+Parâmetros!$B$78)-Parâmetros!$B$66-O71<=0,"ERRO",M71/(1-(Parâmetros!$B$61+N71+Parâmetros!$B$78)-Parâmetros!$B$66-O71))) | Q71: =IF($B71="","",IF((1-Parâmetros!$B$65)*(1-(Parâmetros!$B$61+N71+Parâmetros!$B$78))-O71<=0,"ERRO",(1-Parâmetros!$B$65)*M71/((1-Parâmetros!$B$65)*(1-(Parâmetros!$B$61+N71+Parâmetros!$B$78))-O71))) | R71: =IF($B71="","",IF(Parâmetros!$B$64=2,P71,Q71)) | S71: =IF($B71="","",IF(Parâmetros!$B$64=2,IF(1-(Parâmetros!$B$61+N71+Parâmetros!$B$78)-Parâmetros!$B$66<=0,"ERRO",M71/(1-(Parâmetros!$B$61+N71+Parâmetros!$B$78)-Parâmetros!$B$66)),IF((1-Parâmetros!$B$65)*(1-(Parâmetros!$B$61+N71+Parâmetros!$B$78))<=0,"ERRO",(1-Parâmetros!$B$65)*M71/((1-Parâmetros!$B$65)*(1-(Parâmetros!$B$61+N71+Parâmetros!$B$78)))))) | T71: =IF($B71="","",IF(ISNUMBER(R71),R71*Parâmetros!$B$61,"")) | U71: =IF($B71="","",IF(ISNUMBER(R71),R71*N71,"")) | V71: =IF($B71="","",IF(ISNUMBER(R71),R71*Parâmetros!$B$78,"")) | W71: =IF($B71="","",IF(ISNUMBER(R71),IF(Parâmetros!$B$64=2,R71*Parâmetros!$B$66,Parâmetros!$B$65*(R71-M71-R71*(Parâmetros!$B$61+N71+Parâmetros!$B$78))),"")) | X71: =IF($B71="","",IF(ISNUMBER(R71),R71-M71-T71-U71-V71-W71,"")) | Y71: =IF($B71="","",IF(AND(ISNUMBER(R71),R71>0),X71/R71,"")) | Z71: =IF($B71="","",IF(AND(ISNUMBER(R71),ISNUMBER(G71)),R71-G71,"")) | AA71: =IF($B71="","",IF(NOT(ISNUMBER(R71)),"Percentuais ≥ 100%",IF(N(D71)=0,"Sem tempo",IF(J71=0,"Sem materiais",""))))
J72: =IF($B72="","",SUMIFS(Itens!$E$2:$E$158,Itens!$A$2:$A$158,$B72)+N(F72)) | K72: =IF($B72="","",N(D72)/60*Parâmetros!$B$57) | L72: =IF($B72="","",N(D72)/60*Parâmetros!$B$60) | M72: =IF($B72="","",J72+N(E72)+K72+L72) | N72: =IF($B72="","",IF(H72="",Parâmetros!$B$62,H72)) | O72: =IF($B72="","",IF(I72="",Parâmetros!$B$63,I72)) | P72: =IF($B72="","",IF(1-(Parâmetros!$B$61+N72+Parâmetros!$B$78)-Parâmetros!$B$66-O72<=0,"ERRO",M72/(1-(Parâmetros!$B$61+N72+Parâmetros!$B$78)-Parâmetros!$B$66-O72))) | Q72: =IF($B72="","",IF((1-Parâmetros!$B$65)*(1-(Parâmetros!$B$61+N72+Parâmetros!$B$78))-O72<=0,"ERRO",(1-Parâmetros!$B$65)*M72/((1-Parâmetros!$B$65)*(1-(Parâmetros!$B$61+N72+Parâmetros!$B$78))-O72))) | R72: =IF($B72="","",IF(Parâmetros!$B$64=2,P72,Q72)) | S72: =IF($B72="","",IF(Parâmetros!$B$64=2,IF(1-(Parâmetros!$B$61+N72+Parâmetros!$B$78)-Parâmetros!$B$66<=0,"ERRO",M72/(1-(Parâmetros!$B$61+N72+Parâmetros!$B$78)-Parâmetros!$B$66)),IF((1-Parâmetros!$B$65)*(1-(Parâmetros!$B$61+N72+Parâmetros!$B$78))<=0,"ERRO",(1-Parâmetros!$B$65)*M72/((1-Parâmetros!$B$65)*(1-(Parâmetros!$B$61+N72+Parâmetros!$B$78)))))) | T72: =IF($B72="","",IF(ISNUMBER(R72),R72*Parâmetros!$B$61,"")) | U72: =IF($B72="","",IF(ISNUMBER(R72),R72*N72,"")) | V72: =IF($B72="","",IF(ISNUMBER(R72),R72*Parâmetros!$B$78,"")) | W72: =IF($B72="","",IF(ISNUMBER(R72),IF(Parâmetros!$B$64=2,R72*Parâmetros!$B$66,Parâmetros!$B$65*(R72-M72-R72*(Parâmetros!$B$61+N72+Parâmetros!$B$78))),"")) | X72: =IF($B72="","",IF(ISNUMBER(R72),R72-M72-T72-U72-V72-W72,"")) | Y72: =IF($B72="","",IF(AND(ISNUMBER(R72),R72>0),X72/R72,"")) | Z72: =IF($B72="","",IF(AND(ISNUMBER(R72),ISNUMBER(G72)),R72-G72,"")) | AA72: =IF($B72="","",IF(NOT(ISNUMBER(R72)),"Percentuais ≥ 100%",IF(N(D72)=0,"Sem tempo",IF(J72=0,"Sem materiais",""))))
J73: =IF($B73="","",SUMIFS(Itens!$E$2:$E$158,Itens!$A$2:$A$158,$B73)+N(F73)) | K73: =IF($B73="","",N(D73)/60*Parâmetros!$B$57) | L73: =IF($B73="","",N(D73)/60*Parâmetros!$B$60) | M73: =IF($B73="","",J73+N(E73)+K73+L73) | N73: =IF($B73="","",IF(H73="",Parâmetros!$B$62,H73)) | O73: =IF($B73="","",IF(I73="",Parâmetros!$B$63,I73)) | P73: =IF($B73="","",IF(1-(Parâmetros!$B$61+N73+Parâmetros!$B$78)-Parâmetros!$B$66-O73<=0,"ERRO",M73/(1-(Parâmetros!$B$61+N73+Parâmetros!$B$78)-Parâmetros!$B$66-O73))) | Q73: =IF($B73="","",IF((1-Parâmetros!$B$65)*(1-(Parâmetros!$B$61+N73+Parâmetros!$B$78))-O73<=0,"ERRO",(1-Parâmetros!$B$65)*M73/((1-Parâmetros!$B$65)*(1-(Parâmetros!$B$61+N73+Parâmetros!$B$78))-O73))) | R73: =IF($B73="","",IF(Parâmetros!$B$64=2,P73,Q73)) | S73: =IF($B73="","",IF(Parâmetros!$B$64=2,IF(1-(Parâmetros!$B$61+N73+Parâmetros!$B$78)-Parâmetros!$B$66<=0,"ERRO",M73/(1-(Parâmetros!$B$61+N73+Parâmetros!$B$78)-Parâmetros!$B$66)),IF((1-Parâmetros!$B$65)*(1-(Parâmetros!$B$61+N73+Parâmetros!$B$78))<=0,"ERRO",(1-Parâmetros!$B$65)*M73/((1-Parâmetros!$B$65)*(1-(Parâmetros!$B$61+N73+Parâmetros!$B$78)))))) | T73: =IF($B73="","",IF(ISNUMBER(R73),R73*Parâmetros!$B$61,"")) | U73: =IF($B73="","",IF(ISNUMBER(R73),R73*N73,"")) | V73: =IF($B73="","",IF(ISNUMBER(R73),R73*Parâmetros!$B$78,"")) | W73: =IF($B73="","",IF(ISNUMBER(R73),IF(Parâmetros!$B$64=2,R73*Parâmetros!$B$66,Parâmetros!$B$65*(R73-M73-R73*(Parâmetros!$B$61+N73+Parâmetros!$B$78))),"")) | X73: =IF($B73="","",IF(ISNUMBER(R73),R73-M73-T73-U73-V73-W73,"")) | Y73: =IF($B73="","",IF(AND(ISNUMBER(R73),R73>0),X73/R73,"")) | Z73: =IF($B73="","",IF(AND(ISNUMBER(R73),ISNUMBER(G73)),R73-G73,"")) | AA73: =IF($B73="","",IF(NOT(ISNUMBER(R73)),"Percentuais ≥ 100%",IF(N(D73)=0,"Sem tempo",IF(J73=0,"Sem materiais",""))))
J74: =IF($B74="","",SUMIFS(Itens!$E$2:$E$158,Itens!$A$2:$A$158,$B74)+N(F74)) | K74: =IF($B74="","",N(D74)/60*Parâmetros!$B$57) | L74: =IF($B74="","",N(D74)/60*Parâmetros!$B$60) | M74: =IF($B74="","",J74+N(E74)+K74+L74) | N74: =IF($B74="","",IF(H74="",Parâmetros!$B$62,H74)) | O74: =IF($B74="","",IF(I74="",Parâmetros!$B$63,I74)) | P74: =IF($B74="","",IF(1-(Parâmetros!$B$61+N74+Parâmetros!$B$78)-Parâmetros!$B$66-O74<=0,"ERRO",M74/(1-(Parâmetros!$B$61+N74+Parâmetros!$B$78)-Parâmetros!$B$66-O74))) | Q74: =IF($B74="","",IF((1-Parâmetros!$B$65)*(1-(Parâmetros!$B$61+N74+Parâmetros!$B$78))-O74<=0,"ERRO",(1-Parâmetros!$B$65)*M74/((1-Parâmetros!$B$65)*(1-(Parâmetros!$B$61+N74+Parâmetros!$B$78))-O74))) | R74: =IF($B74="","",IF(Parâmetros!$B$64=2,P74,Q74)) | S74: =IF($B74="","",IF(Parâmetros!$B$64=2,IF(1-(Parâmetros!$B$61+N74+Parâmetros!$B$78)-Parâmetros!$B$66<=0,"ERRO",M74/(1-(Parâmetros!$B$61+N74+Parâmetros!$B$78)-Parâmetros!$B$66)),IF((1-Parâmetros!$B$65)*(1-(Parâmetros!$B$61+N74+Parâmetros!$B$78))<=0,"ERRO",(1-Parâmetros!$B$65)*M74/((1-Parâmetros!$B$65)*(1-(Parâmetros!$B$61+N74+Parâmetros!$B$78)))))) | T74: =IF($B74="","",IF(ISNUMBER(R74),R74*Parâmetros!$B$61,"")) | U74: =IF($B74="","",IF(ISNUMBER(R74),R74*N74,"")) | V74: =IF($B74="","",IF(ISNUMBER(R74),R74*Parâmetros!$B$78,"")) | W74: =IF($B74="","",IF(ISNUMBER(R74),IF(Parâmetros!$B$64=2,R74*Parâmetros!$B$66,Parâmetros!$B$65*(R74-M74-R74*(Parâmetros!$B$61+N74+Parâmetros!$B$78))),"")) | X74: =IF($B74="","",IF(ISNUMBER(R74),R74-M74-T74-U74-V74-W74,"")) | Y74: =IF($B74="","",IF(AND(ISNUMBER(R74),R74>0),X74/R74,"")) | Z74: =IF($B74="","",IF(AND(ISNUMBER(R74),ISNUMBER(G74)),R74-G74,"")) | AA74: =IF($B74="","",IF(NOT(ISNUMBER(R74)),"Percentuais ≥ 100%",IF(N(D74)=0,"Sem tempo",IF(J74=0,"Sem materiais",""))))
J75: =IF($B75="","",SUMIFS(Itens!$E$2:$E$158,Itens!$A$2:$A$158,$B75)+N(F75)) | K75: =IF($B75="","",N(D75)/60*Parâmetros!$B$57) | L75: =IF($B75="","",N(D75)/60*Parâmetros!$B$60) | M75: =IF($B75="","",J75+N(E75)+K75+L75) | N75: =IF($B75="","",IF(H75="",Parâmetros!$B$62,H75)) | O75: =IF($B75="","",IF(I75="",Parâmetros!$B$63,I75)) | P75: =IF($B75="","",IF(1-(Parâmetros!$B$61+N75+Parâmetros!$B$78)-Parâmetros!$B$66-O75<=0,"ERRO",M75/(1-(Parâmetros!$B$61+N75+Parâmetros!$B$78)-Parâmetros!$B$66-O75))) | Q75: =IF($B75="","",IF((1-Parâmetros!$B$65)*(1-(Parâmetros!$B$61+N75+Parâmetros!$B$78))-O75<=0,"ERRO",(1-Parâmetros!$B$65)*M75/((1-Parâmetros!$B$65)*(1-(Parâmetros!$B$61+N75+Parâmetros!$B$78))-O75))) | R75: =IF($B75="","",IF(Parâmetros!$B$64=2,P75,Q75)) | S75: =IF($B75="","",IF(Parâmetros!$B$64=2,IF(1-(Parâmetros!$B$61+N75+Parâmetros!$B$78)-Parâmetros!$B$66<=0,"ERRO",M75/(1-(Parâmetros!$B$61+N75+Parâmetros!$B$78)-Parâmetros!$B$66)),IF((1-Parâmetros!$B$65)*(1-(Parâmetros!$B$61+N75+Parâmetros!$B$78))<=0,"ERRO",(1-Parâmetros!$B$65)*M75/((1-Parâmetros!$B$65)*(1-(Parâmetros!$B$61+N75+Parâmetros!$B$78)))))) | T75: =IF($B75="","",IF(ISNUMBER(R75),R75*Parâmetros!$B$61,"")) | U75: =IF($B75="","",IF(ISNUMBER(R75),R75*N75,"")) | V75: =IF($B75="","",IF(ISNUMBER(R75),R75*Parâmetros!$B$78,"")) | W75: =IF($B75="","",IF(ISNUMBER(R75),IF(Parâmetros!$B$64=2,R75*Parâmetros!$B$66,Parâmetros!$B$65*(R75-M75-R75*(Parâmetros!$B$61+N75+Parâmetros!$B$78))),"")) | X75: =IF($B75="","",IF(ISNUMBER(R75),R75-M75-T75-U75-V75-W75,"")) | Y75: =IF($B75="","",IF(AND(ISNUMBER(R75),R75>0),X75/R75,"")) | Z75: =IF($B75="","",IF(AND(ISNUMBER(R75),ISNUMBER(G75)),R75-G75,"")) | AA75: =IF($B75="","",IF(NOT(ISNUMBER(R75)),"Percentuais ≥ 100%",IF(N(D75)=0,"Sem tempo",IF(J75=0,"Sem materiais",""))))
J76: =IF($B76="","",SUMIFS(Itens!$E$2:$E$158,Itens!$A$2:$A$158,$B76)+N(F76)) | K76: =IF($B76="","",N(D76)/60*Parâmetros!$B$57) | L76: =IF($B76="","",N(D76)/60*Parâmetros!$B$60) | M76: =IF($B76="","",J76+N(E76)+K76+L76) | N76: =IF($B76="","",IF(H76="",Parâmetros!$B$62,H76)) | O76: =IF($B76="","",IF(I76="",Parâmetros!$B$63,I76)) | P76: =IF($B76="","",IF(1-(Parâmetros!$B$61+N76+Parâmetros!$B$78)-Parâmetros!$B$66-O76<=0,"ERRO",M76/(1-(Parâmetros!$B$61+N76+Parâmetros!$B$78)-Parâmetros!$B$66-O76))) | Q76: =IF($B76="","",IF((1-Parâmetros!$B$65)*(1-(Parâmetros!$B$61+N76+Parâmetros!$B$78))-O76<=0,"ERRO",(1-Parâmetros!$B$65)*M76/((1-Parâmetros!$B$65)*(1-(Parâmetros!$B$61+N76+Parâmetros!$B$78))-O76))) | R76: =IF($B76="","",IF(Parâmetros!$B$64=2,P76,Q76)) | S76: =IF($B76="","",IF(Parâmetros!$B$64=2,IF(1-(Parâmetros!$B$61+N76+Parâmetros!$B$78)-Parâmetros!$B$66<=0,"ERRO",M76/(1-(Parâmetros!$B$61+N76+Parâmetros!$B$78)-Parâmetros!$B$66)),IF((1-Parâmetros!$B$65)*(1-(Parâmetros!$B$61+N76+Parâmetros!$B$78))<=0,"ERRO",(1-Parâmetros!$B$65)*M76/((1-Parâmetros!$B$65)*(1-(Parâmetros!$B$61+N76+Parâmetros!$B$78)))))) | T76: =IF($B76="","",IF(ISNUMBER(R76),R76*Parâmetros!$B$61,"")) | U76: =IF($B76="","",IF(ISNUMBER(R76),R76*N76,"")) | V76: =IF($B76="","",IF(ISNUMBER(R76),R76*Parâmetros!$B$78,"")) | W76: =IF($B76="","",IF(ISNUMBER(R76),IF(Parâmetros!$B$64=2,R76*Parâmetros!$B$66,Parâmetros!$B$65*(R76-M76-R76*(Parâmetros!$B$61+N76+Parâmetros!$B$78))),"")) | X76: =IF($B76="","",IF(ISNUMBER(R76),R76-M76-T76-U76-V76-W76,"")) | Y76: =IF($B76="","",IF(AND(ISNUMBER(R76),R76>0),X76/R76,"")) | Z76: =IF($B76="","",IF(AND(ISNUMBER(R76),ISNUMBER(G76)),R76-G76,"")) | AA76: =IF($B76="","",IF(NOT(ISNUMBER(R76)),"Percentuais ≥ 100%",IF(N(D76)=0,"Sem tempo",IF(J76=0,"Sem materiais",""))))
J77: =IF($B77="","",SUMIFS(Itens!$E$2:$E$158,Itens!$A$2:$A$158,$B77)+N(F77)) | K77: =IF($B77="","",N(D77)/60*Parâmetros!$B$57) | L77: =IF($B77="","",N(D77)/60*Parâmetros!$B$60) | M77: =IF($B77="","",J77+N(E77)+K77+L77) | N77: =IF($B77="","",IF(H77="",Parâmetros!$B$62,H77)) | O77: =IF($B77="","",IF(I77="",Parâmetros!$B$63,I77)) | P77: =IF($B77="","",IF(1-(Parâmetros!$B$61+N77+Parâmetros!$B$78)-Parâmetros!$B$66-O77<=0,"ERRO",M77/(1-(Parâmetros!$B$61+N77+Parâmetros!$B$78)-Parâmetros!$B$66-O77))) | Q77: =IF($B77="","",IF((1-Parâmetros!$B$65)*(1-(Parâmetros!$B$61+N77+Parâmetros!$B$78))-O77<=0,"ERRO",(1-Parâmetros!$B$65)*M77/((1-Parâmetros!$B$65)*(1-(Parâmetros!$B$61+N77+Parâmetros!$B$78))-O77))) | R77: =IF($B77="","",IF(Parâmetros!$B$64=2,P77,Q77)) | S77: =IF($B77="","",IF(Parâmetros!$B$64=2,IF(1-(Parâmetros!$B$61+N77+Parâmetros!$B$78)-Parâmetros!$B$66<=0,"ERRO",M77/(1-(Parâmetros!$B$61+N77+Parâmetros!$B$78)-Parâmetros!$B$66)),IF((1-Parâmetros!$B$65)*(1-(Parâmetros!$B$61+N77+Parâmetros!$B$78))<=0,"ERRO",(1-Parâmetros!$B$65)*M77/((1-Parâmetros!$B$65)*(1-(Parâmetros!$B$61+N77+Parâmetros!$B$78)))))) | T77: =IF($B77="","",IF(ISNUMBER(R77),R77*Parâmetros!$B$61,"")) | U77: =IF($B77="","",IF(ISNUMBER(R77),R77*N77,"")) | V77: =IF($B77="","",IF(ISNUMBER(R77),R77*Parâmetros!$B$78,"")) | W77: =IF($B77="","",IF(ISNUMBER(R77),IF(Parâmetros!$B$64=2,R77*Parâmetros!$B$66,Parâmetros!$B$65*(R77-M77-R77*(Parâmetros!$B$61+N77+Parâmetros!$B$78))),"")) | X77: =IF($B77="","",IF(ISNUMBER(R77),R77-M77-T77-U77-V77-W77,"")) | Y77: =IF($B77="","",IF(AND(ISNUMBER(R77),R77>0),X77/R77,"")) | Z77: =IF($B77="","",IF(AND(ISNUMBER(R77),ISNUMBER(G77)),R77-G77,"")) | AA77: =IF($B77="","",IF(NOT(ISNUMBER(R77)),"Percentuais ≥ 100%",IF(N(D77)=0,"Sem tempo",IF(J77=0,"Sem materiais",""))))
J78: =IF($B78="","",SUMIFS(Itens!$E$2:$E$158,Itens!$A$2:$A$158,$B78)+N(F78)) | K78: =IF($B78="","",N(D78)/60*Parâmetros!$B$57) | L78: =IF($B78="","",N(D78)/60*Parâmetros!$B$60) | M78: =IF($B78="","",J78+N(E78)+K78+L78) | N78: =IF($B78="","",IF(H78="",Parâmetros!$B$62,H78)) | O78: =IF($B78="","",IF(I78="",Parâmetros!$B$63,I78)) | P78: =IF($B78="","",IF(1-(Parâmetros!$B$61+N78+Parâmetros!$B$78)-Parâmetros!$B$66-O78<=0,"ERRO",M78/(1-(Parâmetros!$B$61+N78+Parâmetros!$B$78)-Parâmetros!$B$66-O78))) | Q78: =IF($B78="","",IF((1-Parâmetros!$B$65)*(1-(Parâmetros!$B$61+N78+Parâmetros!$B$78))-O78<=0,"ERRO",(1-Parâmetros!$B$65)*M78/((1-Parâmetros!$B$65)*(1-(Parâmetros!$B$61+N78+Parâmetros!$B$78))-O78))) | R78: =IF($B78="","",IF(Parâmetros!$B$64=2,P78,Q78)) | S78: =IF($B78="","",IF(Parâmetros!$B$64=2,IF(1-(Parâmetros!$B$61+N78+Parâmetros!$B$78)-Parâmetros!$B$66<=0,"ERRO",M78/(1-(Parâmetros!$B$61+N78+Parâmetros!$B$78)-Parâmetros!$B$66)),IF((1-Parâmetros!$B$65)*(1-(Parâmetros!$B$61+N78+Parâmetros!$B$78))<=0,"ERRO",(1-Parâmetros!$B$65)*M78/((1-Parâmetros!$B$65)*(1-(Parâmetros!$B$61+N78+Parâmetros!$B$78)))))) | T78: =IF($B78="","",IF(ISNUMBER(R78),R78*Parâmetros!$B$61,"")) | U78: =IF($B78="","",IF(ISNUMBER(R78),R78*N78,"")) | V78: =IF($B78="","",IF(ISNUMBER(R78),R78*Parâmetros!$B$78,"")) | W78: =IF($B78="","",IF(ISNUMBER(R78),IF(Parâmetros!$B$64=2,R78*Parâmetros!$B$66,Parâmetros!$B$65*(R78-M78-R78*(Parâmetros!$B$61+N78+Parâmetros!$B$78))),"")) | X78: =IF($B78="","",IF(ISNUMBER(R78),R78-M78-T78-U78-V78-W78,"")) | Y78: =IF($B78="","",IF(AND(ISNUMBER(R78),R78>0),X78/R78,"")) | Z78: =IF($B78="","",IF(AND(ISNUMBER(R78),ISNUMBER(G78)),R78-G78,"")) | AA78: =IF($B78="","",IF(NOT(ISNUMBER(R78)),"Percentuais ≥ 100%",IF(N(D78)=0,"Sem tempo",IF(J78=0,"Sem materiais",""))))
J79: =IF($B79="","",SUMIFS(Itens!$E$2:$E$158,Itens!$A$2:$A$158,$B79)+N(F79)) | K79: =IF($B79="","",N(D79)/60*Parâmetros!$B$57) | L79: =IF($B79="","",N(D79)/60*Parâmetros!$B$60) | M79: =IF($B79="","",J79+N(E79)+K79+L79) | N79: =IF($B79="","",IF(H79="",Parâmetros!$B$62,H79)) | O79: =IF($B79="","",IF(I79="",Parâmetros!$B$63,I79)) | P79: =IF($B79="","",IF(1-(Parâmetros!$B$61+N79+Parâmetros!$B$78)-Parâmetros!$B$66-O79<=0,"ERRO",M79/(1-(Parâmetros!$B$61+N79+Parâmetros!$B$78)-Parâmetros!$B$66-O79))) | Q79: =IF($B79="","",IF((1-Parâmetros!$B$65)*(1-(Parâmetros!$B$61+N79+Parâmetros!$B$78))-O79<=0,"ERRO",(1-Parâmetros!$B$65)*M79/((1-Parâmetros!$B$65)*(1-(Parâmetros!$B$61+N79+Parâmetros!$B$78))-O79))) | R79: =IF($B79="","",IF(Parâmetros!$B$64=2,P79,Q79)) | S79: =IF($B79="","",IF(Parâmetros!$B$64=2,IF(1-(Parâmetros!$B$61+N79+Parâmetros!$B$78)-Parâmetros!$B$66<=0,"ERRO",M79/(1-(Parâmetros!$B$61+N79+Parâmetros!$B$78)-Parâmetros!$B$66)),IF((1-Parâmetros!$B$65)*(1-(Parâmetros!$B$61+N79+Parâmetros!$B$78))<=0,"ERRO",(1-Parâmetros!$B$65)*M79/((1-Parâmetros!$B$65)*(1-(Parâmetros!$B$61+N79+Parâmetros!$B$78)))))) | T79: =IF($B79="","",IF(ISNUMBER(R79),R79*Parâmetros!$B$61,"")) | U79: =IF($B79="","",IF(ISNUMBER(R79),R79*N79,"")) | V79: =IF($B79="","",IF(ISNUMBER(R79),R79*Parâmetros!$B$78,"")) | W79: =IF($B79="","",IF(ISNUMBER(R79),IF(Parâmetros!$B$64=2,R79*Parâmetros!$B$66,Parâmetros!$B$65*(R79-M79-R79*(Parâmetros!$B$61+N79+Parâmetros!$B$78))),"")) | X79: =IF($B79="","",IF(ISNUMBER(R79),R79-M79-T79-U79-V79-W79,"")) | Y79: =IF($B79="","",IF(AND(ISNUMBER(R79),R79>0),X79/R79,"")) | Z79: =IF($B79="","",IF(AND(ISNUMBER(R79),ISNUMBER(G79)),R79-G79,"")) | AA79: =IF($B79="","",IF(NOT(ISNUMBER(R79)),"Percentuais ≥ 100%",IF(N(D79)=0,"Sem tempo",IF(J79=0,"Sem materiais",""))))
J80: =IF($B80="","",SUMIFS(Itens!$E$2:$E$158,Itens!$A$2:$A$158,$B80)+N(F80)) | K80: =IF($B80="","",N(D80)/60*Parâmetros!$B$57) | L80: =IF($B80="","",N(D80)/60*Parâmetros!$B$60) | M80: =IF($B80="","",J80+N(E80)+K80+L80) | N80: =IF($B80="","",IF(H80="",Parâmetros!$B$62,H80)) | O80: =IF($B80="","",IF(I80="",Parâmetros!$B$63,I80)) | P80: =IF($B80="","",IF(1-(Parâmetros!$B$61+N80+Parâmetros!$B$78)-Parâmetros!$B$66-O80<=0,"ERRO",M80/(1-(Parâmetros!$B$61+N80+Parâmetros!$B$78)-Parâmetros!$B$66-O80))) | Q80: =IF($B80="","",IF((1-Parâmetros!$B$65)*(1-(Parâmetros!$B$61+N80+Parâmetros!$B$78))-O80<=0,"ERRO",(1-Parâmetros!$B$65)*M80/((1-Parâmetros!$B$65)*(1-(Parâmetros!$B$61+N80+Parâmetros!$B$78))-O80))) | R80: =IF($B80="","",IF(Parâmetros!$B$64=2,P80,Q80)) | S80: =IF($B80="","",IF(Parâmetros!$B$64=2,IF(1-(Parâmetros!$B$61+N80+Parâmetros!$B$78)-Parâmetros!$B$66<=0,"ERRO",M80/(1-(Parâmetros!$B$61+N80+Parâmetros!$B$78)-Parâmetros!$B$66)),IF((1-Parâmetros!$B$65)*(1-(Parâmetros!$B$61+N80+Parâmetros!$B$78))<=0,"ERRO",(1-Parâmetros!$B$65)*M80/((1-Parâmetros!$B$65)*(1-(Parâmetros!$B$61+N80+Parâmetros!$B$78)))))) | T80: =IF($B80="","",IF(ISNUMBER(R80),R80*Parâmetros!$B$61,"")) | U80: =IF($B80="","",IF(ISNUMBER(R80),R80*N80,"")) | V80: =IF($B80="","",IF(ISNUMBER(R80),R80*Parâmetros!$B$78,"")) | W80: =IF($B80="","",IF(ISNUMBER(R80),IF(Parâmetros!$B$64=2,R80*Parâmetros!$B$66,Parâmetros!$B$65*(R80-M80-R80*(Parâmetros!$B$61+N80+Parâmetros!$B$78))),"")) | X80: =IF($B80="","",IF(ISNUMBER(R80),R80-M80-T80-U80-V80-W80,"")) | Y80: =IF($B80="","",IF(AND(ISNUMBER(R80),R80>0),X80/R80,"")) | Z80: =IF($B80="","",IF(AND(ISNUMBER(R80),ISNUMBER(G80)),R80-G80,"")) | AA80: =IF($B80="","",IF(NOT(ISNUMBER(R80)),"Percentuais ≥ 100%",IF(N(D80)=0,"Sem tempo",IF(J80=0,"Sem materiais",""))))
... J108: =IF($B108="","",SUMIFS(Itens!$E$2:$E$158,Itens!$A$2:$A$158,$B108)+N(F108)) | K108: =IF($B108="","",N(D108)/60*Parâmetros!$B$57) | L108: =IF($B108="","",N(D108)/60*Parâmetros!$B$60) | M108: =IF($B108="","",J108+N(E108)+K108+L108) | N108: =IF($B108="","",IF(H108="",Parâmetros!$B$62,H108)) | O108: =IF($B108="","",IF(I108="",Parâmetros!$B$63,I108)) | P108: =IF($B108="","",IF(1-(Parâmetros!$B$61+N108+Parâmetros!$B$78)-Parâmetros!$B$66-O108<=0,"ERRO",M108/(1-(Parâmetros!$B$61+N108+Parâmetros!$B$78)-Parâmetros!$B$66-O108))) | Q108: =IF($B108="","",IF((1-Parâmetros!$B$65)*(1-(Parâmetros!$B$61+N108+Parâmetros!$B$78))-O108<=0,"ERRO",(1-Parâmetros!$B$65)*M108/((1-Parâmetros!$B$65)*(1-(Parâmetros!$B$61+N108+Parâmetros!$B$78))-O108))) | R108: =IF($B108="","",IF(Parâmetros!$B$64=2,P108,Q108)) | S108: =IF($B108="","",IF(Parâmetros!$B$64=2,IF(1-(Parâmetros!$B$61+N108+Parâmetros!$B$78)-Parâmetros!$B$66<=0,"ERRO",M108/(1-(Parâmetros!$B$61+N108+Parâmetros!$B$78)-Parâmetros!$B$66)),IF((1-Parâmetros!$B$65)*(1-(Parâmetros!$B$61+N108+Parâmetros!$B$78))<=0,"ERRO",(1-Parâmetros!$B$65)*M108/((1-Parâmetros!$B$65)*(1-(Parâmetros!$B$61+N108+Parâmetros!$B$78)))))) | T108: =IF($B108="","",IF(ISNUMBER(R108),R108*Parâmetros!$B$61,"")) | U108: =IF($B108="","",IF(ISNUMBER(R108),R108*N108,"")) | V108: =IF($B108="","",IF(ISNUMBER(R108),R108*Parâmetros!$B$78,"")) | W108: =IF($B108="","",IF(ISNUMBER(R108),IF(Parâmetros!$B$64=2,R108*Parâmetros!$B$66,Parâmetros!$B$65*(R108-M108-R108*(Parâmetros!$B$61+N108+Parâmetros!$B$78))),"")) | X108: =IF($B108="","",IF(ISNUMBER(R108),R108-M108-T108-U108-V108-W108,"")) | Y108: =IF($B108="","",IF(AND(ISNUMBER(R108),R108>0),X108/R108,"")) | Z108: =IF($B108="","",IF(AND(ISNUMBER(R108),ISNUMBER(G108)),R108-G108,"")) | AA108: =IF($B108="","",IF(NOT(ISNUMBER(R108)),"Percentuais ≥ 100%",IF(N(D108)=0,"Sem tempo",IF(J108=0,"Sem materiais",""))))
